Workbook
Name Autosys_output_commas: 'TRIS Autosys Jobs'!$A$3:$AM$145

Sheet Job Summary
A1: Legacy Job Name | B1: New TRIS JOB | C1: Tested
A2: TRIS_RH_ARCOS_Daily_Box | B2: =IF(_xlfn.XLOOKUP(A2,'Job Details'!A:A,'Job Details'!I:I,"Not in schedule")=0,"Pending",_xlfn.XLOOKUP(A2,'Job Details'!A:A,'Job Details'!I:I,"Not in schedule")) -> Pending | C2: =IF(_xlfn.XLOOKUP(A2,'Job Details'!A:A,'Job Details'!AU:AU,"Job Details")=0,"Pending",_xlfn.XLOOKUP(A2,'Job Details'!A:A,'Job Details'!AU:AU,"Not In Job Details")) -> Pending
A3: TRIS_RH_ARCOS_Overtime_Daily | B3: =IF(_xlfn.XLOOKUP(A3,'Job Details'!A:A,'Job Details'!I:I,"Not in schedule")=0,"Pending",_xlfn.XLOOKUP(A3,'Job Details'!A:A,'Job Details'!I:I,"Not in schedule")) -> Pending | C3: =IF(_xlfn.XLOOKUP(A3,'Job Details'!A:A,'Job Details'!AU:AU,"Job Details")=0,"Pending",_xlfn.XLOOKUP(A3,'Job Details'!A:A,'Job Details'!AU:AU,"Not In Job Details")) -> Pending
A4: TRIS_RH_ARCOS_HR_Daily | B4: =IF(_xlfn.XLOOKUP(A4,'Job Details'!A:A,'Job Details'!I:I,"Not in schedule")=0,"Pending",_xlfn.XLOOKUP(A4,'Job Details'!A:A,'Job Details'!I:I,"Not in schedule")) -> Pending | C4: =IF(_xlfn.XLOOKUP(A4,'Job Details'!A:A,'Job Details'!AU:AU,"Job Details")=0,"Pending",_xlfn.XLOOKUP(A4,'Job Details'!A:A,'Job Details'!AU:AU,"Not In Job Details")) -> Pending
A5: TRIS_RH_ARCOS_Sched_Daily | B5: =IF(_xlfn.XLOOKUP(A5,'Job Details'!A:A,'Job Details'!I:I,"Not in schedule")=0,"Pending",_xlfn.XLOOKUP(A5,'Job Details'!A:A,'Job Details'!I:I,"Not in schedule")) -> Pending | C5: =IF(_xlfn.XLOOKUP(A5,'Job Details'!A:A,'Job Details'!AU:AU,"Job Details")=0,"Pending",_xlfn.XLOOKUP(A5,'Job Details'!A:A,'Job Details'!AU:AU,"Not In Job Details")) -> Pending
A6: TRIS_RH_ARCOS_SFTP_Daily | B6: =IF(_xlfn.XLOOKUP(A6,'Job Details'!A:A,'Job Details'!I:I,"Not in schedule")=0,"Pending",_xlfn.XLOOKUP(A6,'Job Details'!A:A,'Job Details'!I:I,"Not in schedule")) -> Pending | C6: =IF(_xlfn.XLOOKUP(A6,'Job Details'!A:A,'Job Details'!AU:AU,"Job Details")=0,"Pending",_xlfn.XLOOKUP(A6,'Job Details'!A:A,'Job Details'!AU:AU,"Not In Job Details")) -> Pending
A7: TRIS_RH_ARCOS_Delete_files | B7: =IF(_xlfn.XLOOKUP(A7,'Job Details'!A:A,'Job Details'!I:I,"Not in schedule")=0,"Pending",_xlfn.XLOOKUP(A7,'Job Details'!A:A,'Job Details'!I:I,"Not in schedule")) -> Pending | C7: =IF(_xlfn.XLOOKUP(A7,'Job Details'!A:A,'Job Details'!AU:AU,"Job Details")=0,"Pending",_xlfn.XLOOKUP(A7,'Job Details'!A:A,'Job Details'!AU:AU,"Not In Job Details")) -> Pending
A8: TRIS_RH_ARCOS_Weekly_Box | B8: =IF(_xlfn.XLOOKUP(A8,'Job Details'!A:A,'Job Details'!I:I,"Not in schedule")=0,"Pending",_xlfn.XLOOKUP(A8,'Job Details'!A:A,'Job Details'!I:I,"Not in schedule")) -> Pending | C8: =IF(_xlfn.XLOOKUP(A8,'Job Details'!A:A,'Job Details'!AU:AU,"Job Details")=0,"Pending",_xlfn.XLOOKUP(A8,'Job Details'!A:A,'Job Details'!AU:AU,"Not In Job Details")) -> Pending
A9: TRIS_RH_ARCOS_Overtime_Weekly | B9: =IF(_xlfn.XLOOKUP(A9,'Job Details'!A:A,'Job Details'!I:I,"Not in schedule")=0,"Pending",_xlfn.XLOOKUP(A9,'Job Details'!A:A,'Job Details'!I:I,"Not in schedule")) -> Pending | C9: =IF(_xlfn.XLOOKUP(A9,'Job Details'!A:A,'Job Details'!AU:AU,"Job Details")=0,"Pending",_xlfn.XLOOKUP(A9,'Job Details'!A:A,'Job Details'!AU:AU,"Not In Job Details")) -> Pending
A10: TRIS_RH_ARCOS_Yearly_Box | B10: =IF(_xlfn.XLOOKUP(A10,'Job Details'!A:A,'Job Details'!I:I,"Not in schedule")=0,"Pending",_xlfn.XLOOKUP(A10,'Job Details'!A:A,'Job Details'!I:I,"Not in schedule")) -> Pending | C10: =IF(_xlfn.XLOOKUP(A10,'Job Details'!A:A,'Job Details'!AU:AU,"Job Details")=0,"Pending",_xlfn.XLOOKUP(A10,'Job Details'!A:A,'Job Details'!AU:AU,"Not In Job Details")) -> Pending
A11: TRIS_RH_ARCOS_Overtime_Yearly | B11: =IF(_xlfn.XLOOKUP(A11,'Job Details'!A:A,'Job Details'!I:I,"Not in schedule")=0,"Pending",_xlfn.XLOOKUP(A11,'Job Details'!A:A,'Job Details'!I:I,"Not in schedule")) -> Pending | C11: =IF(_xlfn.XLOOKUP(A11,'Job Details'!A:A,'Job Details'!AU:AU,"Job Details")=0,"Pending",_xlfn.XLOOKUP(A11,'Job Details'!A:A,'Job Details'!AU:AU,"Not In Job Details")) -> Pending
A12: TRIS_RH_Contract_Final | B12: =IF(_xlfn.XLOOKUP(A12,'Job Details'!A:A,'Job Details'!I:I,"Not in schedule")=0,"Pending",_xlfn.XLOOKUP(A12,'Job Details'!A:A,'Job Details'!I:I,"Not in schedule")) -> Pending | C12: =IF(_xlfn.XLOOKUP(A12,'Job Details'!A:A,'Job Details'!AU:AU,"Job Details")=0,"Pending",_xlfn.XLOOKUP(A12,'Job Details'!A:A,'Job Details'!AU:AU,"Not In Job Details")) -> Pending
A13: TRIS_RH_Contract_Final_010_BuildPayrollFiles_vJOB_TR | B13: =IF(_xlfn.XLOOKUP(A13,'Job Details'!A:A,'Job Details'!I:I,"Not in schedule")=0,"Pending",_xlfn.XLOOKUP(A13,'Job Details'!A:A,'Job Details'!I:I,"Not in schedule")) -> Pending | C13: =IF(_xlfn.XLOOKUP(A13,'Job Details'!A:A,'Job Details'!AU:AU,"Job Details")=0,"Pending",_xlfn.XLOOKUP(A13,'Job Details'!A:A,'Job Details'!AU:AU,"Not In Job Details")) -> Pending
... A160: TRIS_RN_monthly_single_050_MF_TR33318 | B160: =IF(_xlfn.XLOOKUP(A160,'Job Details'!A:A,'Job Details'!I:I,"Not in schedule")=0,"Pending",_xlfn.XLOOKUP(A160,'Job Details'!A:A,'Job Details'!I:I,"Not in schedule")) -> Pending | C160: =IF(_xlfn.XLOOKUP(A160,'Job Details'!A:A,'Job Details'!AU:AU,"Job Details")=0,"Pending",_xlfn.XLOOKUP(A160,'Job Details'!A:A,'Job Details'!AU:AU,"Not In Job Details")) -> Pending

Sheet Job Details
A1: Please see the bottom Notes for more info on highlighted jobs.
A2: Job Name | B2: Box | C2: Step | D2: Days | E2: Time | F2: Old process/Command | G2: Gateway URL | H2: Status | I2: New autosys | J2: Description of Job | K2: Wipro Contact | L2: New TRIS Csharp Jobs | M2: Description | N2: Job Type | O2: Box Name | P2: Owner | Q2: Machine | R2: Command | S2: Permissions | T2: JCL library | U2: JCL member | V2: Has Date Condition | W2: Start Time | X2: Run Calendar | Y2: Exclude Calendar | Z2: Alarm | AA2: Profile | AB2: Send Notification | AC2: Schedule Priority | AD2: Email Notified | AE2: Email Message | AF2: Mainframe Condtion Code | AG2: Start Mins | AH2: std out file | AI2: std err file | AJ2: FTP transfer type | AK2: FTP transfer direction | AL2: FTP local name | AM2: FTP remote name | AN2: FTP server name | AO2: FTP use ssl | AP2: FTP local user | AQ2: FTP user type | AR2: max run alarm | AS2: box terminator | AT2: term run time | AU2: Test Status
A3: TRIS_RH_ARCOS_Daily_Box | D3: su,mo,tu,we,th,fr,sa | E3: 0.5 | M3: TRIS ARCOS Daily Interface Files CHG0000000xxxxx | N3: BOX | P3: TRISBATCH@ameren | S3: gx,mx | V3: 1 | W3: 0.54166667 | Z3: 1 | AC3: 3
A4: TRIS_RH_ARCOS_Overtime_Daily | B4: TRIS_RH_ARCOS_Daily_Box | C4: 1 | F4: C:\TRISBatch\ARCOSOvertimeInterface\ARCOSOvertimeInterface.exe | L4: /api/core/payroll/v1/ARCOSHRInterface/strike/process | M4: TRIS daily ARCOS HR interface #RH#DV-HR-TR# CHG CHG0000000xxxxx | N4: CMD | O4: TRIS_RH_ARCOS_Daily_Box | P4: TRISBATCH@ameren | Q4: V_TRIS_BATCH | R4: $$TRIS_BATCHDIR\ARCOSHRInterface\ARCOSHRInterface.exe | S4: gx,mx | V4: 0 | Z4: 1 | AA4: TRIS | AB4: F | AC4: 3 | AD4: DLTRISTeam@ameren.com | AE4: TRIS_RH_ARCOS_HR_Daily FAILED. | AH4: >>$$TRIS_BATCHDIR\Logs\%AUTO_JOB_NAME%_stdout.txt | AI4: >>$$TRIS_BATCHDIR\Logs\%AUTO_JOB_NAME%_stderr.txt
A5: TRIS_RH_ARCOS_HR_Daily | B5: TRIS_RH_ARCOS_Daily_Box | C5: 2 | D5: s(TRIS_RH_ARCOS_Overtime_Daily) | F5: C:\TRISBatch\ARCOSHRInterface\ARCOSHRInterface.exe | L5: /api/core/payroll/v1/ArcosOvertimeInterface/interface | M5: TRIS daily ARCOS Overtime interface #RH#DV-HR-TR# CHG0000000xxxxx | N5: CMD | O5: TRIS_RH_ARCOS_Daily_Box | P5: TRISBATCH@ameren | Q5: V_TRIS_BATCH | R5: $$TRIS_BATCHDIR\ARCOSOvertimeInterface\ARCOSOvertimeInterface.exe | S5: gx,mx | V5: 0 | Z5: 1 | AA5: TRIS | AB5: F | AC5: 3 | AD5: DLTRISTeam@ameren.com | AE5: TRIS_RH_ARCOS_Overtime_Daily FAILED. | AH5: >>$$TRIS_BATCHDIR\Logs\%AUTO_JOB_NAME%_stdout.txt | AI5: >>$$TRIS_BATCHDIR\Logs\%AUTO_JOB_NAME%_stderr.txt
A6: TRIS_RH_ARCOS_Sched_Daily | B6: TRIS_RH_ARCOS_Daily_Box | C6: 3 | D6: s(TRIS_RH_ARCOS_HR_Daily) | F6: C:\TRISBatch\ARCOSScheduleInterface\ARCOSSchedulingInterface.exe | L6: /api/core/payroll/v1/ARCOSOvertimeWeekly/build-all-standings | M6: TRIS weekly ARCOS Build Next Standing #RN#DV-HR-TR# CHG0000000xxxxx | N6: CMD | O6: TRIS_RH_ARCOS_Weekly_Box | P6: TRISBATCH@ameren | Q6: V_TRIS_BATCH | R6: $$TRIS_BATCHDIR\ARCOSOvertimeWeeklyProcess\ARCOSOvertimeWeeklyProcess.exe | S6: gx,mx | V6: 0 | Z6: 1 | AA6: TRIS | AB6: F | AC6: 3 | AD6: DLTRISTeam@ameren.com | AE6: TRIS_RH_ARCOS_Overtime_Weekly FAILED. | AH6: >>$$TRIS_BATCHDIR\Logs\%AUTO_JOB_NAME%_stdout.txt | AI6: >>$$TRIS_BATCHDIR\Logs\%AUTO_JOB_NAME%_stderr.txt
A7: TRIS_RH_ARCOS_SFTP_Daily | B7: TRIS_RH_ARCOS_Daily_Box | C7: 4 | D7: s(TRIS_RH_ARCOS_Sched_Daily) | L7: /api/core/payroll/v1/ARCOSOvertimeYearly/rezero-standings | M7: TRIS ARCOS Yearly -- Re-Zero Standings -- Jim Barnett 314-630-7969 #RN#DV-HR-TR# CHG0000000xxxxx | N7: CMD | O7: TRIS_RH_ARCOS_Yearly_Box | P7: TRISBATCH@ameren | Q7: V_TRIS_BATCH | R7: $$TRIS_BATCHDIR\ARCOSOvertimeYearlyProcess\ARCOSOvertimeYearlyProcess.exe | S7: gx,mx | V7: 0 | Z7: 1 | AA7: TRIS | AB7: F | AC7: 3 | AD7: DLTRISTeam@ameren.com | AE7: TRIS_RH_ARCOS_Overtime_Yearly FAILED. | AH7: >>$$TRIS_BATCHDIR\Logs\%AUTO_JOB_NAME%_stdout.txt | AI7: >>$$TRIS_BATCHDIR\Logs\%AUTO_JOB_NAME%_stderr.txt
A8: TRIS_RH_ARCOS_Delete_files | B8: TRIS_RH_ARCOS_Daily_Box | C8: 5 | D8: s(TRIS_RH_ARCOS_SFTP_Daily) | F8: $$TRIS_BATCHDIR\ARCOSDeleteFiles\ARCOSDeleteFiles.exe | L8: /api/core/payroll/v1/ARCOSSchedulingInterface/build-schedule-file | M8: TRIS daily ARCOS Schedule interface #RH#DV-HR-TR# CHG CHG0000000xxxxx | N8: CMD | O8: TRIS_RH_ARCOS_Daily_Box | P8: TRISBATCH@ameren | Q8: V_TRIS_BATCH | R8: $$TRIS_BATCHDIR\ARCOSScheduleInterface\ARCOSSchedulingInterface.exe | S8: gx,mx | V8: 0 | Z8: 1 | AA8: TRIS | AB8: F | AC8: 3 | AD8: DLTRISTeam@ameren.com | AE8: TRIS_RH_ARCOS_Sched_Daily FAILED. | AH8: >>$$TRIS_BATCHDIR\Logs\%AUTO_JOB_NAME%_stdout.txt | AI8: >>$$TRIS_BATCHDIR\Logs\%AUTO_JOB_NAME%_stderr.txt
A9: TRIS_RH_ARCOS_Weekly_Box | D9: we | E9: 0.25 | L9: /api/core/payroll/v1/ARCOSOvertimeWeekly/build-all-standings | M9: TRIS ARCOS Weekly Create next Standing CHG0000000xxxxx | N9: BOX | P9: TRISBATCH@ameren | S9: gx,mx | V9: 1 | W9: 0.25 | Z9: 1 | AC9: 3
A10: TRIS_RH_ARCOS_Overtime_Weekly | B10: TRIS_RH_ARCOS_Weekly_Box | C10: 1 | F10: C:\TRISBatch\ARCOSOvertimeWeeklyProcess\ARCOSOvertimeWeeklyProcess.exe | L10: /api/core/payroll/v1/ARCOSOvertimeYearly/rezero-standings | M10: TRIS ARCOS Yearly -- Re-Zero Standings -- Jim Barnett 314-630-7969 CHG0000000xxxxx | N10: BOX | P10: TRISBATCH@ameren | S10: gx,mx | V10: 1 | W10: 0.27083333 | Z10: 1 | AC10: 3
A11: TRIS_RH_ARCOS_Yearly_Box | D11: AM_1st_WED_JAN | E11: 0.27083333 | M11: This runs the TRIS portion of the contract payroll | N11: BOX | P11: TRISBATCH@ameren | S11: gx,mx | V11: 0 | Z11: 1 | AC11: 3
A12: TRIS_RH_ARCOS_Overtime_Yearly | B12: TRIS_RH_ARCOS_Yearly_Box | C12: 1 | F12: C:\TRISBatch\ARCOSOvertimeYearlyProcess\ARCOSOvertimeYearlyProcess.exe | L12: /api/core/notification/v1/jobs/buildFile | M12: Build File for DB2 Load of VJOB_TR #RH#DV-HR-TR# CHG0000000xxxxx | N12: CMD | O12: TRIS_RH_Contract_Final | P12: TRISBATCH@ameren | Q12: V_TRIS_BATCH | R12: $$TRIS_BATCHDIR\BuildDB2LoadFiles\BuildVjob\BuildVjob.exe | S12: gx,mx | V12: 0 | Z12: 1 | AA12: TRIS | AB12: F | AC12: 3 | AD12: DLTRISTeam@ameren.com | AE12: TRIS_RH_Contract_Final_010_BuildPayrollFiles_vJOB_TR FAILED | AH12: >>$$TRIS_BATCHDIR\Logs\%AUTO_JOB_NAME%_stdout.txt | AI12: >>$$TRIS_BATCHDIR\Logs\%AUTO_JOB_NAME%_stderr.txt
A13: TRIS_RH_Contract_Final | D13: On demand | L13: /api/core/notification/v1/departments/buildFile | M13: Build File for DB2 Load of VDEPT_TBL_TR #RH#DV-HR-TR# CHG0000000xxxxx | N13: CMD | O13: TRIS_RH_Contract_Final | P13: TRISBATCH@ameren | Q13: V_TRIS_BATCH | R13: $$TRIS_BATCHDIR\BuildDB2LoadFiles\BuildVdept\BuildVdept.exe | S13: gx,mx | V13: 0 | Z13: 1 | AA13: TRIS | AB13: F | AC13: 3 | AD13: DLTRISTeam@ameren.com | AE13: TRIS_RH_Contract_Final_020_BuildPayrollFiles_vDEPT_TBL_TR FAILED | AH13: >>$$TRIS_BATCHDIR\Logs\%AUTO_JOB_NAME%_stdout.txt | AI13: >>$$TRIS_BATCHDIR\Logs\%AUTO_JOB_NAME%_stderr.txt
A14: TRIS_RH_Contract_Final_010_BuildPayrollFiles_vJOB_TR | B14: TRIS_RH_Contract_Final | C14: 1 | F14: C:\TRISBatch\BuildDB2LoadFiles\BuildVjob\BuildVjob.exe | L14: /api/core/notification/v1/jobcodes/buildFile | M14: Build File for DB2 Load of VJOBCODE_TBL_TR #RH#DV-HR-TR# CHG0000000xxxxx | N14: CMD | O14: TRIS_RH_Contract_Final | P14: TRISBATCH@ameren | Q14: V_TRIS_BATCH | R14: $$TRIS_BATCHDIR\BuildDB2LoadFiles\BuildVjobcode\BuildVjobcode.exe | S14: gx,mx | V14: 0 | Z14: 1 | AA14: TRIS | AB14: F | AC14: 3 | AD14: DLTRISTeam@ameren.com | AE14: TRIS_RH_Contract_Final_030_BuildPayrollFiles_vJOBCODE_TBL_TR FAILED | AH14: >>$$TRIS_BATCHDIR\Logs\%AUTO_JOB_NAME%_stdout.txt | AI14: >>$$TRIS_BATCHDIR\Logs\%AUTO_JOB_NAME%_stderr.txt
A15: TRIS_RH_Contract_Final_020_BuildPayrollFiles_vDEPT_TBL_TR | B15: TRIS_RH_Contract_Final | C15: 2 | D15: s(TRIS_RH_Contract_Final_010_BuildPayrollFiles_vJOB_TR) | F15: C:\TRISBatch\BuildDB2LoadFiles\BuildVdept\BuildVdept.exe | L15: /api/core/common/v1/JobSalaryStep/generate-file | M15: Build File for DB2 Load of VSAL_STEP_TBL_TR #RH#DV-HR-TR# CHG0000000xxxxx | N15: CMD | O15: TRIS_RH_Contract_Final | P15: TRISBATCH@ameren | Q15: V_TRIS_BATCH | R15: $$TRIS_BATCHDIR\BuildDB2LoadFiles\BuildVsalarystep\BuildVsalarystep.exe | S15: gx,mx | V15: 0 | Z15: 1 | AA15: TRIS | AB15: F | AC15: 3 | AD15: DLTRISTeam@ameren.com | AE15: TRIS_RH_Contract_Final_040_BuildPayrollFiles_vSAL_STEP_TR FAILED | AH15: >>$$TRIS_BATCHDIR\Logs\%AUTO_JOB_NAME%_stdout.txt | AI15: >>$$TRIS_BATCHDIR\Logs\%AUTO_JOB_NAME%_stderr.txt
A16: TRIS_RH_Contract_Final_030_BuildPayrollFiles_vJOBCODE_TR | B16: TRIS_RH_Contract_Final | C16: 3 | D16: s(TRIS_RH_Contract_Final_020_BuildPayrollFiles_vDEPT_TBL_TR) | F16: C:\TRISBatch\BuildDB2LoadFiles\BuildVjobcode\BuildVjobcode.exe | L16: NA | M16: FTP of file to load into VJOB_TR load #RH#DV-HR-TR# CHG0000000xxxxx | N16: FTP | O16: TRIS_RH_Contract_Final | P16: ASYSFTPP@SYSC | Q16: V_TRIS_BATCH | S16: gx,mx | V16: 0 | Z16: 1 | AB16: F | AC16: 3 | AD16: DLTRISTeam@ameren.com | AE16: TRIS_RH_Contract_Final_050_BuildPayrollFiles_FTP_vJOB_TR FAILED | AJ16: A | AK16: UPLOAD | AL16: $$TRIS_BATCHDIR\\DB2LoadFiles\\VJOB-TR-EXTRACT.txt | AM16: ITP.DATA.JOB | AN16: SYSC.ameren.com | AO16: 0 | AP16: TRISBATCH@ameren | AQ16: Simple
A17: TRIS_RH_Contract_Final_040_BuildPayrollFiles_vSAL_STEP_TR | B17: TRIS_RH_Contract_Final | C17: 4 | D17: S(TRIS_RH_Contract_Final_030_BuildPayrollFiles_vJOBCODE_TR ) | F17: C:\TRISBatch\BuildDB2LoadFiles\BuildVsalarystep\BuildVsalarystep.exe | L17: NA | M17: FTP of file to load into VDEPT_TBL_TR load #RH#DV-HR-TR# CHG0000000xxxxx | N17: FTP | O17: TRIS_RH_Contract_Final | P17: ASYSFTPP@SYSC | Q17: V_TRIS_BATCH | S17: gx,mx | V17: 0 | Z17: 1 | AB17: F | AC17: 3 | AD17: DLTRISTeam@ameren.com | AE17: TRIS_RH_Contract_Final_060_BuildPayrollFiles_FTP_vDEPT_TR FAILED | AJ17: A | AK17: UPLOAD | AL17: $$TRIS_BATCHDIR\\DB2LoadFiles\\VDEPT-TBL-TR-EXTRACT.txt | AM17: ITP.DATA.DEPT | AN17: SYSC.ameren.com | AO17: 0 | AP17: TRISBATCH@ameren | AQ17: Simple
A18: TRIS_RH_Contract_Final_050_BuildPayrollFiles_FTP_vJOB_TR | B18: TRIS_RH_Contract_Final | C18: 5 | D18: S(TRIS_RH_Contract_Final_040_BuildPayrollFiles_vSAL_STEP_TR) | L18: NA | M18: FTP of file to load into VJOBCODE_TBL_TR load #RH#DV-HR-TR# CHG0000000xxxxx | N18: FTP | O18: TRIS_RH_Contract_Final | P18: ASYSFTPP@SYSC | Q18: V_TRIS_BATCH | S18: gx,mx | V18: 0 | Z18: 1 | AB18: F | AC18: 3 | AD18: DLTRISTeam@ameren.com | AE18: TRIS_RH_Contract_Final_070_BuildPayrollFiles_FTP_vJOBCODE FAILED | AJ18: A | AK18: UPLOAD | AL18: $$TRIS_BATCHDIR\\DB2LoadFiles\\VJOBCODE-TBL-TR-EXTRACT.txt | AM18: ITP.DATA.JOBCODE | AN18: SYSC.ameren.com | AO18: 0 | AP18: TRISBATCH@ameren | AQ18: Simple
A19: TRIS_RH_Contract_Final_060_BuildPayrollFiles_FTP_vDEPT_TR | B19: TRIS_RH_Contract_Final | C19: 6 | D19: S(TRIS_RH_Contract_Final_050_BuildPayrollFiles_FTP_vJOB_TR) | L19: NA | M19: FTP of file to load into VSAL_STEP_TBL_TR load #RH#DV-HR-TR# CHG0000000xxxxx | N19: FTP | O19: TRIS_RH_Contract_Final | P19: ASYSFTPP@SYSC | Q19: V_TRIS_BATCH | S19: gx,mx | V19: 0 | Z19: 1 | AB19: F | AC19: 3 | AD19: DLTRISTeam@ameren.com | AE19: TRIS_RH_Contract_Final_080_BuildPayrollFiles_FTP_vSAL FAILED | AJ19: A | AK19: UPLOAD | AL19: $$TRIS_BATCHDIR\\DB2LoadFiles\\VSAL-STEP-TBL-TR-EXTRACT.txt | AM19: ITP.DATA.SAL.STP | AN19: SYSC.ameren.com | AO19: 0 | AP19: TRISBATCH@ameren | AQ19: Simple
A20: TRIS_RH_Contract_Final_070_BuildPayrollFiles_FTP_vJOBCODE | B20: TRIS_RH_Contract_Final | C20: 7 | D20: S(TRIS_RH_Contract_Final_060_BuildPayrollFiles_FTP_vDEPT_TR) | L20: Cobol | M20: Loads the FTP files that contained HR data for Payroll into DB2 Tables #RH#DV-HR-TR# CHG0000000xxxxx | N20: ZOS | O20: TRIS_RH_Contract_Final | P20: ESPAE | Q20: V_TRIS_TRJobs2MF | T20: CF.STARTPDS | U20: AR13895 | V20: 0 | Z20: 1 | AB20: F | AD20: DLTRISTeam@ameren.com | AE20: TRIS_RH_Contract_Final_200_MF_AR13895 FAILED. Loads the FTP files that contained HR data for Payroll into DB2 Tables | AF20: action=STOP,rc=4\:4095,result=FAILURE
A21: TRIS_RH_Contract_Final_080_BuildPayrollFiles_FTP_vSAL | B21: TRIS_RH_Contract_Final | C21: 8 | D21: S(TRIS_RH_Contract_Final_050_BuildPayrollFiles_FTP_vJOB_TR) | M21: Fills tables for view VJOB_TR_EFF which allows the HR History records to have a start and end date versus just an effective date. #RH#DV-HR-TR# CHG00000000xxxx | N21: CMD | O21: TRIS_RH_Contract_Final | P21: TRISBATCH@ameren | Q21: V_TRIS_BATCH | R21: $$TRIS_BATCHDIR\PSJobViewRefresh\PS2TRIS.exe | S21: gx,mx | V21: 0 | Z21: 1 | AA21: TRIS | AB21: F | AC21: 3 | AD21: DLTRISTeam@ameren.com | AE21: TRIS_RH_Contract_Final_300_Build_HR_History_View FAILED. Fills tables for view VJOB_TR_EFF which allows the HR History records to have a start and end date versus just an effective date. Look in \C\\TRISBatch\\Logs\ on server | AH21: >>$$TRIS_BATCHDIR\Logs\%AUTO_JOB_NAME%_stdout.txt | AI21: >>$$TRIS_BATCHDIR\Logs\%AUTO_JOB_NAME%_stderr.txt
A22: TRIS_RH_Contract_Final_200_MF_AR13895 | B22: TRIS_RH_Contract_Final | C22: 9 | D22: S(TRIS_RH_Contract_Final_080_BuildPayrollFiles_FTP_Vsal) | F22: TR33003: IEBGENERs to manage files and Utilities to load tables | L22: Cobol | M22: Mainframe Contract Payroll processing that produces Payroll file that is used in TRIS_RH_Contract_Final_550_Send_ToPayroll to build a JSON request to send to Workday #RH#DV-HR-TR# CHG0000000xxxxx | N22: ZOS | O22: TRIS_RH_Contract_Final | P22: ESPAE | Q22: V_TRIS_TRJobs2MF | T22: UE.STARTPDS | U22: TR33200 | V22: 0 | Z22: 1 | AB22: F | AD22: DLTRISTeam@ameren.com | AE22: TRIS_RH_Contract_Final_410_MF_TR33200 FAILED. Mainframe Contract Payroll processing that produces Payroll file that is used in TRIS_RH_Contract_Final_550_Send_ToPayroll to build a JSON request to send to Workday | AF22: action=STOP,rc=1\:4095,result=FAILURE
A23: TRIS_RH_Contract_Final_300_Build_HR_History_View | B23: TRIS_RH_Contract_Final | C23: 10 | D23: s(TRIS_RH_Contract_Final_200_MF_AR13895) | F23: C:\TRISBatch\PSJobViewRefresh\PS2TRIS.exe | L23: Cobol | M23: FTPs Mainframe Payroll File built in TRIS_RH_Contract_Final_410_MF_TR33200 to Autosys server #RH#DV-HR-TR# CHG0000000xxxxx | N23: ZOS | O23: TRIS_RH_Contract_Final | P23: ESPAE | Q23: V_TRIS_TRJobs2MF | T23: CF.STARTPDS | U23: AR13687 | V23: 0 | Z23: 1 | AB23: F | AD23: DLTRISTeam@ameren.com | AE23: TRIS_RH_Contract_Final_420_MF_AR13687 FAILED. FTPs Mainframe Payroll File built in TRIS_RH_Contract_Final_410_MF_TR33200 to Autosys server | AF23: action=STOP,rc=1\:4095,result=FAILURE
A24: TRIS_RH_Contract_Final_410_MF_TR33200 | B24: TRIS_RH_Contract_Final | C24: 11 | D24: s(TRIS_RH_Contract_Final_300_Build_HR_History_View) | F24: TR33200: TR001-Extract actual time and adjustments TR039-Missing time report (33729) TR051-Allowed time records TR052-Split extract file for sick leave TR003-Allowed time (actual time) processing TR050-Create sick leave detail TR021-Adjustment processing TR003C-CIPS Allowed time (actual time) processing (Report 33708) TR050-Create CIPS sick leave detail TR021C CIPS Adjustment processing TR105-Load sick leave detail and banks work tables TR106-Process sick leave TR131-Sick leave LTD messages TR108-Sick leave messages report (Report TR33801) TR004-Payroll earnings proof (Report 33700) TR005-Payroll deviations (Rpeort 33703) TR060-Paysheet prep TR061-Print repor 33781 paysheet memo report TR033-Unlock departments TR037-Update final cycle number | G24: https://rxvavgtcv7.execute-api.us-east-1.amazonaws.com/dev/tr-33200 | I24: TR_RN_ContractPayroll_TR33200_Trigger_Box | L24: Cobol | M24: Copies Mainframe payroll file on the Autosys server to the RIS folder on the Corporate share drive #RH#DV-HR-TR# CHG0000000xxxxx | N24: CMD | O24: TRIS_RH_Contract_Final | P24: TRISBATCH@ameren | Q24: V_TRIS_MFFTP | R24: %FTPDir2%\Exec\copy_file.bat %FTPDir%\tr_payroll_cont.txt \\corp.dir.ameren.com\dfs\Orgdrv\TRIS\MKS\tr_payroll_cont.txt | S24: gx,mx | V24: 0 | Z24: 1 | AA24: TRIS | AB24: F | AC24: 3 | AD24: DLTRISTeam@ameren.com | AE24: TRIS_RH_Contract_Final_530_Send_Copy_PayrollFile JOB FAILED. Copies Mainframe payroll file on the Autosys server to the RIS folder on the Corporate share drive | AH24: %FTPDir2%\Logs\Payroll_stdout.txt | AI24: %FTPDir2%\Logs\Payroll_stderr.txt
A25: TRIS_RH_Contract_Final_420_MF_AR13687 | B25: TRIS_RH_Contract_Final | C25: 12a | D25: s(TRIS_RH_Contract_Final_410_MF_TR33200) | F25: TR33007(Sends (FTP) contract payroll file to be processed to workday payroll) | L25: Cobol | M25: Moves Mainframe Payroll file from the TRIS folder on the Corporate share drive to the TRIS Server (V_TRIS_BATCH) #RH#DV-HR-TR# CHG0000000xxxxx | N25: CMD | O25: TRIS_RH_Contract_Final | P25: TRISBATCH@ameren | Q25: V_TRIS_BATCH | R25: $$TRIS_BATCHDIR\MoveMainframeFiles\MovePayrollFile\MovePayrollFile.exe | S25: gx,mx | V25: 0 | Z25: 1 | AA25: TRIS | AB25: F | AC25: 3 | AD25: DLTRISTeam@ameren.com | AE25: TRIS_RH_Contract_Final_540_Send_Move_PayrollFile FAILED. Moves Mainframe Payroll file from the TRIS folder on the Corporate share drive to the TRIS Server (V_TRIS_BATCH) | AH25: >>$$TRIS_BATCHDIR\Logs\%AUTO_JOB_NAME%_stdout.txt | AI25: >>$$TRIS_BATCHDIR\Logs\%AUTO_JOB_NAME%_stderr.txt
A26: TRIS_RH_Contract_Final_530_Send_Copy_PayrollFile | B26: TRIS_RH_Contract_Final | C26: 13a | D26: s(TRIS_RH_Contract_Final_420_MF_AR13687) | F26: %FTPDir2%\Exec\copy_file.bat %FTPDir%\tr_payroll_cont.txt \\corp.dir.ameren.com\dfs\Orgdrv\TRIS\MKS\tr_payroll_cont.txt | L26: /api/core/notification/v1/WorkdayPayroll/execute | M26: Send Payroll to Workday #RH#DV-HR-TR# CHG0000000xxxxx | N26: CMD | O26: TRIS_RH_Contract_Final | P26: TRISBATCH@ameren | Q26: V_TRIS_BATCH | R26: $$TRIS_BATCHDIR\WorkdayPayrollInterface\WorkdayPayrollInterface.exe | S26: gx,mx | V26: 0 | Z26: 1 | AA26: TRIS | AB26: F | AC26: 3 | AD26: DLTRISTeam@ameren.com | AE26: TRIS_RH_Contract_Final_550_Send_ToPayroll FAILED | AH26: >>$$TRIS_BATCHDIR\Logs\%AUTO_JOB_NAME%_stdout.txt | AI26: >>$$TRIS_BATCHDIR\Logs\%AUTO_JOB_NAME%_stderr.txt
A27: TRIS_RH_Contract_Final_540_Send_Move_PayrollFile | B27: TRIS_RH_Contract_Final | C27: 14a | D27: s(TRIS_RH_Contract_Final_530_Send_Copy_PayrollFile) | F27: C:\TRISBatch\MoveMainframeFiles\MovePayrollFile\MovePayrollFile.exe | L27: Cobol | M27: Updates the sick leave banks to be viewed in TRIS after the Contract Final Job completes TRIS_RH_Contract_Final_210_MF_TR33200 #RH#DV-HR-TR# CHG0000000xxxxx (dynamic sick leave processing) | N27: ZOS | O27: TRIS_RH_Contract_Final | P27: ESPAE | Q27: V_TRIS_TRJobs2MF | T27: UE.STARTPDS | U27: TR33206 | V27: 0 | Z27: 1 | AB27: F | AD27: DLTRISTeam@ameren.com | AE27: TRIS_RH_Contract_Final_600_MF_TR33206 FAILED. Updates the sick leave banks to be viewed in TRIS after the Contract Final Job completes TRIS_RH_Contract_Final_210_MF_TR33200 | AF27: action=STOP,rc=1\:4095,result=FAILURE
A28: TRIS_RH_Contract_Final_550_Send_ToPayroll | B28: TRIS_RH_Contract_Final | C28: 15a | D28: s(TRIS_RH_Contract_Final_540_Send_Move_PayrollFile) | F28: C:\TRISBatch\WorkdayPayrollInterface\WorkdayPayrollInterface.exe | L28: Cobol | M28: Contract Preliminary Job on Request #RH#DV-HR-TR# CHG0000000xxxxx | N28: ZOS | P28: ESPAE | Q28: V_TRIS_TRJobs2MF | T28: UE.STARTPDS | U28: TR33103N | V28: 0 | Z28: 1 | AB28: F | AD28: DLTRISTeam@ameren.com | AE28: TRIS_RH_Contract_Preliminary_OnRequest_MF_TR33103N FAILED. Contract Preliminary Job on Request | AF28: action=STOP,rc=1\:4095,result=FAILURE
A29: TRIS_RH_Contract_Final_600_MF_TR33206 | B29: TRIS_RH_Contract_Final | C29: 12b | D29: s(TRIS_RH_Contract_Final_410_MF_TR33200) | F29: TR33206: TR109-Update sick leave banks with current balances TR107-Update sick leave detail and banks from work tables TR077-Sick leave detail report TR042-CIPS/Gen local 702 sick leave reports TR029-Report 33701-Reported Time Adjustments TR026-Split Exception codes for allowed time TR135-Allowed time detail table update TR136-Relief Hours table update TR137-Hours worked of relief reports TR111-Temporary Referral worker (TRW) report TR134-Union OA 12 hour shift sick leave certiification (day 4 only) | G29: https://rxvavgtcv7.execute-api.us-east-1.amazonaws.com/dev/tr-33206 | I29: TR_RN_ContractPayroll_TR33206_Trigger_Box | L29: /api/core/notification/v1/departments/common/buildFile | M29: Builds File for DB2 Load of TAR_COMN_DEPT_TBL. #RH#DV-HR-TR# CHG0000000xxxxx | N29: CMD | O29: TRIS_RH_dailyBox | P29: TRISBATCH@ameren | Q29: V_TRIS_BATCH | R29: $$TRIS_BATCHDIR\BuildDB2LoadFiles\BuildCommonDepartment\BuildCommonDepartment.exe | S29: gx,mx | V29: 0 | Z29: 1 | AA29: TRIS | AB29: F | AC29: 3 | AD29: DLTRISTeam@ameren.com | AE29: TRIS_RH_daily_010_BuildCommon_Department FAILED. Builds File for DB2 Load of TAR_COMN_DEPT_TBL. Look in \C\\TRISBatch\\Logs\ on server | AH29: >>$$TRIS_BATCHDIR\Logs\%AUTO_JOB_NAME%_stdout.txt | AI29: >>$$TRIS_BATCHDIR\Logs\%AUTO_JOB_NAME%_stderr.txt
A30: TRIS_RH_Contract_Preliminary_OnRequest_MF_TR33103N | D30: Failure of mainframe job | F30: TR33103: TR033-Lock departments on the last prelim run before final TR001-Extract actual time and adjustments TR039-Missing time report (33729) TR051-Allowed time records TR052-Split extract file for sick leave TR003-Allowed time (actual time) processing TR050-Create sick leave detail TR021-Adjustment processing TR117-702 check previous year fmla TR003C-CIPS Allowed time (actual time) processing TR050-Create sick leave detail TR021C CIPS Adjustment processing TR104-Sick leave certification TR115-Sick leave FMLA updates TR105-Load sick leave detail and banks work tables TR106-Process sick leave TR108-Sick leave messages report (Report TR33801) TR004-Payroll earnings proof (Report 33700) TR005-Payroll deviations (Rpeort 33703) TR077-Sick leave detail report TR029-Report 33701-Reported Time Adjustments (33701) | G30: https://rxvavgtcv7.execute-api.us-east-1.amazonaws.com/dev/tr-33103n | I30: TR_RN_ContractPayroll_TR33103N_Trigger_Box | L30: /api/core/notification/v1/employees/buildFile | M30: Builds File for DB2 Load of TAR_COMN_EMP_TBL and Builds for DB2 Load of THRDB_EMPLOYEE_TBL #RH#DV-HR-TR# CHG0000000xxxxx | N30: CMD | O30: TRIS_RH_dailyBox | P30: TRISBATCH@ameren | Q30: V_TRIS_BATCH | R30: $$TRIS_BATCHDIR\BuildDB2LoadFiles\BuildCommonEmployeeFile\BuildCommonEmployeeFile.exe | S30: gx,mx | V30: 0 | Z30: 1 | AA30: TRIS | AB30: F | AC30: 3 | AD30: DLTRISTeam@ameren.com | AE30: TRIS_RH_daily_020_BuildCommon_Employee FAILED. Builds File for DB2 Load of TAR_COMN_EMP_TBL and Builds for DB2 Load of THRDB_EMPLOYEE_TBL. Look in \C\\TRISBatch\\Logs\ on server | AH30: >>$$TRIS_BATCHDIR\Logs\%AUTO_JOB_NAME%_stdout.txt | AI30: >>$$TRIS_BATCHDIR\Logs\%AUTO_JOB_NAME%_stderr.txt
A31: TRIS_RH_dailyBox | L31: NA | M31: FTP of file to load into TAR_COMN_DEPT_TBL. #RH#DV-HR-TR# CHG0000000xxxxx | N31: FTP | O31: TRIS_RH_dailyBox | P31: ASYSFTPP@SYSC | Q31: V_TRIS_BATCH | S31: gx,mx | V31: 0 | Z31: 1 | AB31: F | AC31: 3 | AD31: DLTRISTeam@ameren.com | AE31: TRIS_RH_daily_030_BuildCommon_FTP_Department FAILED. FTP of file to load into TAR_COMN_DEPT_TBL. | AJ31: A | AK31: UPLOAD | AL31: $$TRIS_BATCHDIR\\DB2LoadFiles\\CommonDepartment-EXTRACT.txt | AM31: ITP.DATA.GDG.DEPT.EXTRT | AN31: SYSC.ameren.com | AO31: 0 | AP31: TRISBATCH@ameren | AQ31: Simple
A32: TRIS_RH_daily_010_BuildCommon_Department | B32: TRIS_RH_dailyBox | C32: 1 | D32: mo,tu,we,th,fr,sa | E32: 0.041666667 | F32: C:\TRISBatch\BuildDB2LoadFiles\BuildCommonDepartment\BuildCommonDepartment.exe | L32: NA | M32: FTP a file to load into TAR_COMN_EMPL_TBL. #RH#DV-HR-TR# CHG0000000xxxxx | N32: FTP | O32: TRIS_RH_dailyBox | P32: ASYSFTPP@SYSC | Q32: V_TRIS_BATCH | S32: gx,mx | V32: 0 | Z32: 1 | AB32: F | AC32: 3 | AD32: DLTRISTeam@ameren.com | AE32: TRIS_RH_daily_040_BuildCommon_FTP_Employee FAILED. FTP a file to load into TAR_COMN_EMPL_TBL | AJ32: A | AK32: UPLOAD | AL32: $$TRIS_BATCHDIR\\DB2LoadFiles\\COMNEMPL-EXTRACT.txt | AM32: ITP.DATA.GDG.EMPL.EXTRT | AN32: SYSC.ameren.com | AO32: 0 | AP32: TRISBATCH@ameren | AQ32: Simple
A33: TRIS_RH_daily_020_BuildCommon_Employee | B33: TRIS_RH_dailyBox | C33: 2 | D33: s(TRIS_RH_daily_010_BuildCommon_Department) | F33: C:\TRISBatch\BuildDB2LoadFiles\BuildCommonEmployeeFile\BuildCommonEmployeeFile.exe | L33: NA | M33: FTP a File for DB2 Load of THRDB_EMPLOYEE_TBL #RH#DV-HR-TR# CHG0000000xxxxx | N33: FTP | O33: TRIS_RH_dailyBox | P33: ASYSFTPP@SYSC | Q33: V_TRIS_BATCH | S33: gx,mx | V33: 0 | Z33: 1 | AB33: F | AC33: 3 | AD33: DLTRISTeam@ameren.com | AE33: TRIS_RH_daily_050_BuildCommon_FTP_THRDBEmployee FAILED. FTP a File for DB2 Load of THRDB_EMPLOYEE_TBL | AJ33: A | AK33: UPLOAD | AL33: $$TRIS_BATCHDIR\\DB2LoadFiles\\THRDB-EMPLOYEE-EXTRACT.txt | AM33: ITP.DATA.GDG.EMPL.DB2 | AN33: SYSC.ameren.com | AO33: 0 | AP33: TRISBATCH@ameren | AQ33: Simple
A34: TRIS_RH_daily_030_BuildCommon_FTP_Department | B34: TRIS_RH_dailyBox | C34: 3 | D34: s(TRIS_RH_daily_020_BuildCommon_Employee | L34: /api/core/notification/v1/build/associations/buildFile | M34: Builds File for maintaining the TTR_ASSOCIATIONS table in mainframe job UE.STARTPDS(TR33107N). #RH#DV-HR-TR# CHG0000000xxxxx | N34: CMD | O34: TRIS_RH_dailyBox | P34: TRISBATCH@ameren | Q34: V_TRIS_BATCH | R34: $$TRIS_BATCHDIR\BuildDB2LoadFiles\BuildAssociations\BuildAssociations.exe | S34: gx,mx | V34: 0 | Z34: 1 | AA34: TRIS | AB34: F | AC34: 3 | AD34: DLTRISTeam@ameren.com | AE34: TRIS_RH_daily_070_BuildCommon_Associations FAILED. Builds File for maintaining the TTR_ASSOCIATIONS table in mainframe job UE.STARTPDS(TR33107N). Look in \C\\TRISBatch\\Logs\ on server | AH34: >>$$TRIS_BATCHDIR\Logs\%AUTO_JOB_NAME%_stdout.txt | AI34: >>$$TRIS_BATCHDIR\Logs\%AUTO_JOB_NAME%_stderr.txt
A35: TRIS_RH_daily_040_BuildCommon_FTP_Employee | B35: TRIS_RH_dailyBox | C35: 4 | D35: s(TRIS_RH_daily_030_BuildCommon_FTP_Department | L35: NA | M35: FTP a file to process in UE.STARTPDS(TR33107N). #RH#DV-HR-TR# CHG0000000xxxxx | N35: FTP | O35: TRIS_RH_dailyBox | P35: ASYSFTPP@SYSC | Q35: V_TRIS_BATCH | S35: gx,mx | V35: 0 | Z35: 1 | AB35: F | AC35: 3 | AD35: DLTRISTeam@ameren.com | AE35: TRIS_RH_daily_080_BuildCommon_FTP_Associations FAILED. FTP a file to process in UE.STARTPDS(TR33107N). | AJ35: A | AK35: UPLOAD | AL35: $$TRIS_BATCHDIR\\DB2LoadFiles\\TTR-ASSOCIATIONS-EXTRACT.txt | AM35: ITP.DATA..DPTTABLE | AN35: SYSC.ameren.com | AO35: 0 | AP35: TRISBATCH@ameren | AQ35: Simple
A36: TRIS_RH_daily_050_BuildCommon_FTP_THRDBEmployee | B36: TRIS_RH_dailyBox | C36: 5 | D36: s(TRIS_RH_daily_040_BuildCommon_FTP_Employee | L36: /api/core/notification/v1/jobs/buildFile | M36: Build File for DB2 Load of VJOB_TR #RH#DV-HR-TR# CHG0000000xxxxx | N36: CMD | O36: TRIS_RH_dailyBox | P36: TRISBATCH@ameren | Q36: V_TRIS_BATCH | R36: $$TRIS_BATCHDIR\BuildDB2LoadFiles\BuildVjob\BuildVjob.exe | S36: gx,mx | V36: 0 | Z36: 1 | AA36: TRIS | AB36: F | AC36: 3 | AD36: DLTRISTeam@ameren.com | AE36: TRIS_RH_daily_100_BuildPayrollFiles_vJOB_TR FAILED. Build File for DB2 Load of VJOB_TR. Look in \C\\TRISBatch\\Logs\ on server | AH36: >>$$TRIS_BATCHDIR\Logs\%AUTO_JOB_NAME%_stdout.txt | AI36: >>$$TRIS_BATCHDIR\Logs\%AUTO_JOB_NAME%_stderr.txt
A37: TRIS_RH_daily_070_BuildCommon_Associations | B37: TRIS_RH_dailyBox | C37: 6 | D37: s(TRIS_RH_daily_050_BuildCommon_FTP_THRDBEmployee | F37: C:\TRISBatch\BuildDB2LoadFiles\BuildAssociations\BuildAssociations.exe | L37: /api/core/notification/v1/departments/buildFile | M37: Build File for DB2 Load of VDEPT_TBL_TR #RH#DV-HR-TR# CHG0000000xxxxx | N37: CMD | O37: TRIS_RH_dailyBox | P37: TRISBATCH@ameren | Q37: V_TRIS_BATCH | R37: $$TRIS_BATCHDIR\BuildDB2LoadFiles\BuildVdept\BuildVdept.exe | S37: gx,mx | V37: 0 | Z37: 1 | AA37: TRIS | AB37: F | AC37: 3 | AD37: DLTRISTeam@ameren.com | AE37: TRIS_RH_daily_110_BuildPayrollFiles_vDEPT_TBL_TR FAILED. Build File for DB2 Load of VDEPT_TBL_TR. Look in \C\\TRISBatch\\Logs\ on server | AH37: >>$$TRIS_BATCHDIR\Logs\%AUTO_JOB_NAME%_stdout.txt | AI37: >>$$TRIS_BATCHDIR\Logs\%AUTO_JOB_NAME%_stderr.txt
A38: TRIS_RH_daily_080_BuildCommon_FTP_Associations | B38: TRIS_RH_dailyBox | C38: 7 | D38: s(TRIS_RH_daily_070_BuildCommon_Associations | L38: /api/core/notification/v1/jobcodes/buildFile | M38: Build File for DB2 Load of VJOBCODE_TBL_TR #RH#DV-HR-TR# CHG0000000xxxxx | N38: CMD | O38: TRIS_RH_dailyBox | P38: TRISBATCH@ameren | Q38: V_TRIS_BATCH | R38: $$TRIS_BATCHDIR\BuildDB2LoadFiles\BuildVjobcode\BuildVjobcode.exe | S38: gx,mx | V38: 0 | Z38: 1 | AA38: TRIS | AB38: F | AC38: 3 | AD38: DLTRISTeam@ameren.com | AE38: TRIS_RH_daily_120_BuildPayrollFiles_vJOBCODE_TBL_TR FAILED. Build File for DB2 Load of VJOBCODE_TBL_TR. Look in \C\\TRISBatch\\Logs\ on server | AH38: >>$$TRIS_BATCHDIR\Logs\%AUTO_JOB_NAME%_stdout.txt | AI38: >>$$TRIS_BATCHDIR\Logs\%AUTO_JOB_NAME%_stderr.txt
A39: TRIS_RH_daily_100_BuildPayrollFiles_vJOB_TR | B39: TRIS_RH_dailyBox | C39: 8 | D39: s(TRIS_RH_daily_080_BuildCommon_FTP_Associations | F39: C:\TRISBatch\BuildDB2LoadFiles\BuildVjob\BuildVjob.exe | L39: /api/core/common/v1/JobSalaryStep/generate-file | M39: Build File for DB2 Load of VSAL_STEP_TBL_TR #RH#DV-HR-TR# CHG0000000xxxxx | N39: CMD | O39: TRIS_RH_dailyBox | P39: TRISBATCH@ameren | Q39: V_TRIS_BATCH | R39: $$TRIS_BATCHDIR\BuildDB2LoadFiles\BuildVsalarystep\BuildVsalarystep.exe | S39: gx,mx | V39: 0 | Z39: 1 | AA39: TRIS | AB39: F | AC39: 3 | AD39: DLTRISTeam@ameren.com | AE39: TRIS_RH_daily_130_BuildPayrollFiles_vSAL_STEP_TBL_TR FAILED. Build File for DB2 Load of VSAL_STEP_TBL_TR. Look in \C\\TRISBatch\\Logs\ on server | AH39: >>$$TRIS_BATCHDIR\Logs\%AUTO_JOB_NAME%_stdout.txt | AI39: >>$$TRIS_BATCHDIR\Logs\%AUTO_JOB_NAME%_stderr.txt
A40: TRIS_RH_daily_110_BuildPayrollFiles_vDEPT_TBL_TR | B40: TRIS_RH_dailyBox | C40: 9 | D40: s(TRIS_RH_daily_100_BuildPayrollFiles_vJOB_TR | F40: C:\TRISBatch\BuildDB2LoadFiles\BuildVdept\BuildVdept.exe | L40: NA | M40: FTP of file to load into VJOB_TR load #RH#DV-HR-TR# CHG0000000xxxxx | N40: FTP | O40: TRIS_RH_dailyBox | P40: ASYSFTPP@SYSC | Q40: V_TRIS_BATCH | S40: gx,mx | V40: 0 | Z40: 1 | AB40: F | AC40: 3 | AD40: DLTRISTeam@ameren.com | AE40: TRIS_RH_daily_140_BuildPayrollFiles_FTP_vJOB_TR FAILED. FTP of file to load into VJOB_TR load. | AJ40: A | AK40: UPLOAD | AL40: $$TRIS_BATCHDIR\\DB2LoadFiles\\VJOB-TR-EXTRACT.txt | AM40: ITP.DATA.JOB | AN40: SYSC.ameren.com | AO40: 0 | AP40: TRISBATCH@ameren | AQ40: Simple
A41: TRIS_RH_daily_120_BuildPayrollFiles_vJOBCODE_TBL_TR | B41: TRIS_RH_dailyBox | C41: 10 | D41: s(TRIS_RH_daily_110_BuildPayrollFiles_vDEPT_TBL_TR | F41: C:\TRISBatch\BuildDB2LoadFiles\BuildVjobcode\BuildVjobcode.exe | L41: NA | M41: FTP of file to load into VDEPT_TBL_TR #RH#DV-HR-TR# CHG0000000xxxxx | N41: FTP | O41: TRIS_RH_dailyBox | P41: ASYSFTPP@SYSC | Q41: V_TRIS_BATCH | S41: gx,mx | V41: 0 | Z41: 1 | AB41: F | AC41: 3 | AD41: DLTRISTeam@ameren.com | AE41: TRIS_RH_daily_150_BuildPayrollFiles_FTP_vDEPT_TBL_TR FAILED. FTP of file to load into VDEPT_TBL_TR. | AJ41: A | AK41: UPLOAD | AL41: $$TRIS_BATCHDIR\\DB2LoadFiles\\VDEPT-TBL-TR-EXTRACT.txt | AM41: ITP.DATA.DEPT | AN41: SYSC.ameren.com | AO41: 0 | AP41: TRISBATCH@ameren | AQ41: Simple
A42: TRIS_RH_daily_130_BuildPayrollFiles_vSAL_STEP_TBL_TR | B42: TRIS_RH_dailyBox | C42: 11 | D42: s(TRIS_RH_daily_120_BuildPayrollFiles_vJOBCODE_TBL_TR | F42: C:\TRISBatch\BuildDB2LoadFiles\BuildVsalarystep\BuildVsalarystep.exe | L42: NA | M42: FTP of file to load into VJOBCODE_TBL_TR #RH#DV-HR-TR# CHG0000000xxxxx | N42: FTP | O42: TRIS_RH_dailyBox | P42: ASYSFTPP@SYSC | Q42: V_TRIS_BATCH | S42: gx,mx | V42: 0 | Z42: 1 | AB42: F | AC42: 3 | AD42: DLTRISTeam@ameren.com | AE42: TRIS_RH_daily_160_BuildPayrollFiles_FTP_vJOBCODE_TBL_TR FAILED. FTP of file to load into VJOBCODE_TBL_TR | AJ42: A | AK42: UPLOAD | AL42: $$TRIS_BATCHDIR\\DB2LoadFiles\\VJOBCODE-TBL-TR-EXTRACT.txt | AM42: ITP.DATA.JOBCODE | AN42: SYSC.ameren.com | AO42: 0 | AP42: TRISBATCH@ameren | AQ42: Simple
A43: TRIS_RH_daily_140_BuildPayrollFiles_FTP_vJOB_TR | B43: TRIS_RH_dailyBox | C43: 12 | D43: s(TRIS_RH_daily_130_BuildPayrollFiles_vSAL_STEP_TBL_TR | L43: NA | M43: FTP of file to load into VSAL_STEP_TBL_TR #RH#DV-HR-TR# CHG0000000xxxxx | N43: FTP | O43: TRIS_RH_dailyBox | P43: ASYSFTPP@SYSC | Q43: V_TRIS_BATCH | S43: gx,mx | V43: 0 | Z43: 1 | AB43: F | AC43: 3 | AD43: DLTRISTeam@ameren.com | AE43: TRIS_RH_daily_170_BuildPayrollFiles_FTP_vSAL_STEP_TBL_TR FAILED. FTP of file to load into VSAL_STEP_TBL_TR | AJ43: A | AK43: UPLOAD | AL43: $$TRIS_BATCHDIR\\DB2LoadFiles\\VSAL-STEP-TBL-TR-EXTRACT.txt | AM43: ITP.DATA.SAL.STP | AN43: SYSC.ameren.com | AO43: 0 | AP43: TRISBATCH@ameren | AQ43: Simple
A44: TRIS_RH_daily_150_BuildPayrollFiles_FTP_vDEPT_TBL_TR | B44: TRIS_RH_dailyBox | C44: 13 | D44: s(TRIS_RH_daily_140_BuildPayrollFiles_FTP_vJOB_TR | L44: Cobol | M44: Moves the Associations File that were sent in job TRIS_RH_daily_080_BuildCommon_FTP_Associations from Mainframe FTP directory to a Mainframe dataset. #RH#DV-HR-TR# CHG0000000xxxxx | N44: ZOS | O44: TRIS_RH_dailyBox | P44: ESPAE | Q44: V_TRIS_TRJobs2MF | T44: CF.STARTPDS | U44: AR13872 | V44: 0 | Z44: 1 | AB44: F | AD44: DLTRISTeam@ameren.com | AE44: TRIS_RH_daily_300_MF_AR13872 FAILED. Moves the Associations File that were sent in job TRIS_RH_daily_080_BuildCommon_FTP_Associations from Mainframe FTP directory to a Mainframe dataset. | AF44: action=STOP,rc=1\:4095,result=FAILURE
A45: TRIS_RH_daily_160_BuildPayrollFiles_FTP_vJOBCODE_TBL_TR | B45: TRIS_RH_dailyBox | C45: 14 | D45: s(TRIS_RH_daily_150_BuildPayrollFiles_FTP_vDEPT_TBL_TR | L45: Cobol | M45: Moves the Files that were sent in jobs TRIS_RH_daily_030, TRIS_RH_daily_040, & TRIS_RH_daily_050 from Mainframe FTP directory to Mainframe datasets #RH#DV-HR-TR# CHG0000000xxxxx | N45: ZOS | O45: TRIS_RH_dailyBox | P45: ESPAE | Q45: V_TRIS_TRJobs2MF | T45: CF.STARTPDS | U45: AR13999 | V45: 0 | Z45: 1 | AB45: F | AD45: DLTRISTeam@ameren.com | AE45: TRIS_RH_daily_310_MF_AR13999 FAILED. Moves the Files that were sent in jobs TRIS_RH_daily_030, TRIS_RH_daily_040, & TRIS_RH_daily_050 from Mainframe FTP directory to Mainframe datasets | AF45: action=STOP,rc=1\:4095,result=FAILURE
A46: TRIS_RH_daily_170_BuildPayrollFiles_FTP_vSAL_STEP_TBL_TR | B46: TRIS_RH_dailyBox | C46: 15 | D46: s(TRIS_RH_daily_160_BuildPayrollFiles_FTP_vJOBCODE_TBL_TR | L46: Cobol | M46: Moves the Files that were sent in jobs TRIS_RH_daily_140, TRIS_RH_daily_150, TRIS_RH_daily_160, & TRIS_RH_daily_170 from Mainframe FTP directory to Mainframe datasets. It then loads the data into DB2 Tables #RH#DV-HR-TR# CHG0000000xxxxx | N46: ZOS | O46: TRIS_RH_dailyBox | P46: ESPAE | Q46: V_TRIS_TRJobs2MF | T46: CF.STARTPDS | U46: AR13895 | V46: 0 | Z46: 1 | AB46: F | AD46: DLTRISTeam@ameren.com | AE46: TRIS_RH_daily_320_MF_AR13895 FAILED. Moves the Files that were sent in jobs TRIS_RH_daily_140, TRIS_RH_daily_150, TRIS_RH_daily_160, & TRIS_RH_daily_170 from Mainframe FTP directory to Mainframe datasets. It then loads the data into DB2 Tables | AF46: action=STOP,rc=5\:4095,result=FAILURE
A47: TRIS_RH_daily_300_MF_AR13872 | B47: TRIS_RH_dailyBox | C47: 16 | D47: s(TRIS_RH_daily_170_BuildPayrollFiles_FTP_vSAL_STEP_TBL_TR | F47: TR33004-moves/copies file | L47: Cobol | M47: Loads the Common Employee and Common Department tables sent from jobs TRIS_RH_daily_030, TRIS_RH_daily_040 and moved in job TRIS_RH_daily_310_MF_AR13999 #RH#DV-HR-TR# CHG0000000xxxxx | N47: ZOS | O47: TRIS_RH_dailyBox | P47: ESPAE | Q47: V_TRIS_TRJobs2MF | T47: UE.STARTPDS | U47: DB12287N | V47: 0 | Z47: 1 | AB47: F | AD47: DLTRISTeam@ameren.com | AE47: TRIS_RH_daily_330_MF_DB12287N FAILED. Loads the Common Employee and Common Department tables sent from jobs TRIS_RH_daily_030, TRIS_RH_daily_040 and moved in job TRIS_RH_daily_310_MF_AR13999 | AF47: action=STOP,rc=1\:4095,result=FAILURE
A48: TRIS_RH_daily_310_MF_AR13999 | B48: TRIS_RH_dailyBox | C48: 17 | D48: s(TRIS_RH_daily_300_MF_AR13872) | F48: TR33002 | L48: Cobol | M48: Loads the THRDB Employee table sent from job TRIS_RH_daily_050 and moved in job TRIS_RH_daily_310_MF_AR13999 #RH#DV-HR-TR# CHG0000000xxxxx | N48: ZOS | O48: TRIS_RH_dailyBox | P48: ESPAE | Q48: V_TRIS_TRJobs2MF | T48: UE.STARTPDS | U48: DB12005N | V48: 0 | Z48: 1 | AB48: F | AD48: DLTRISTeam@ameren.com | AE48: TRIS_RH_daily_340_MF_DB12005N FAILED. Loads the THRDB Employee table sent from job TRIS_RH_daily_050 and moved in job TRIS_RH_daily_310_MF_AR13999 | AF48: action=STOP,rc=1\:4095,result=FAILURE
A49: TRIS_RH_daily_320_MF_AR13895 | B49: TRIS_RH_dailyBox | C49: 18 | D49: s(TRIS_RH_daily_310_MF_AR13999) | F49: TR33003 | M49: Fills tables for view VJOB_TR_EFF which allows the HR History records to have a start and end date versus just an effective date. #RH#DV-HR-TR# CHG00000000xxxx | N49: CMD | O49: TRIS_RH_dailyBox | P49: TRISBATCH@ameren | Q49: V_TRIS_BATCH | R49: $$TRIS_BATCHDIR\PSJobViewRefresh\PS2TRIS.exe | S49: gx,mx | V49: 0 | Z49: 1 | AA49: TRIS | AB49: F | AC49: 3 | AD49: DLTRISTeam@ameren.com | AE49: TRIS_RH_daily_380_Build_HR_History_View FAILED. Fills tables for view VJOB_TR_EFF which allows the HR History records to have a start and end date versus just an effective date | AH49: >>$$TRIS_BATCHDIR\Logs\%AUTO_JOB_NAME%_stdout.txt | AI49: >>$$TRIS_BATCHDIR\Logs\%AUTO_JOB_NAME%_stderr.txt
A50: TRIS_RH_daily_330_MF_DB12287N | B50: TRIS_RH_dailyBox | C50: 19 | D50: s(TRIS_RH_daily_320_MF_AR13895) | F50: Loads the Common Employee and Common Department tables | L50: Cobol | M50: Maintains the TTR_JOBS table (TR014) #RH#DV-HR-TR# CHG0000000xxxxx | N50: ZOS | O50: TRIS_RH_dailyBox | P50: ESPAE | Q50: V_TRIS_TRJobs2MF | T50: UE.STARTPDS | U50: TR33106N | V50: 0 | Z50: 1 | AB50: F | AD50: DLTRISTeam@ameren.com | AE50: TRIS_RH_daily_410_MF_TR33106 FAILED. Maintains the TTR_JOBS table (TR014) | AF50: action=STOP,rc=1\:4095,result=FAILURE
A51: TRIS_RH_daily_340_MF_DB12005N | B51: TRIS_RH_dailyBox | C51: 20 | D51: s(TRIS_RH_daily_330_MF_DB12287N) | F51: Loads the THRDB Employee table sent from job TRIS_RH_daily_050 | L51: Cobol | M51: Maintains the TTR_ASSOCIATIONS table (TR015) #RH#DV-HR-TR# CHG0000000xxxxx | N51: ZOS | O51: TRIS_RH_dailyBox | P51: ESPAE | Q51: V_TRIS_TRJobs2MF | T51: UE.STARTPDS | U51: TR33107N | V51: 0 | Z51: 1 | AB51: F | AD51: DLTRISTeam@ameren.com | AE51: TRIS_RH_daily_420_MF_TR33107 FAILED. Maintains the TTR_ASSOCIATIONS table (TR015) | AF51: action=STOP,rc=1\:4095,result=FAILURE
A52: TRIS_RH_daily_380_Build_HR_History_View | B52: TRIS_RH_dailyBox | C52: 21 | D52: s(TRIS_RH_daily_340_MF_DB12005N) | F52: C:\TRISBatch\PSJobViewRefresh\PS2TRIS.exe | L52: Cobol | M52: HR/TRIS interface employee update (TR009 & TR129) #RH#DV-HR-TR# CHG0000000xxxxx | N52: ZOS | O52: TRIS_RH_dailyBox | P52: ESPAE | Q52: V_TRIS_TRJobs2MF | T52: UE.STARTPDS | U52: TR33102N | V52: 0 | Z52: 1 | AB52: F | AD52: DLTRISTeam@ameren.com | AE52: TRIS_RH_daily_430_MF_TR33102 FAILED. HR/TRIS interface employee update (TR009 & TR129) | AF52: action=STOP,rc=1\:4095,result=FAILURE
A53: TRIS_RH_daily_410_MF_TR33106 | B53: TRIS_RH_dailyBox | C53: 22 | D53: s(TRIS_RH_daily_380_Build_HR_History_View) | F53: TR33106 TR014-Update job table | G53: https://rxvavgtcv7.execute-api.us-east-1.amazonaws.com/dev/batch-job | H53: Pass | I53: TR_RN_Maintain_TR33106N_Trigger_Box | L53: /api/core/payroll/v1/VacAllotment/Main | M53: Updates the Vacation allotment for new hires | N53: CMD | O53: TRIS_RH_dailyBox | P53: TRISBATCH@ameren | Q53: V_TRIS_BATCH | R53: $$TRIS_BATCHDIR\VacationAllotment\Ameren.TRIS.Server.Batch.VAllotment.exe | S53: gs,mx | V53: 0 | Z53: 1 | AB53: F | AD53: DLTRISTeam@ameren.com | AE53: TRIS_RH_daily_435_Vacation_Allotment FAILED | AH53: >>$$TRIS_BATCHDIR\Logs\%AUTO_JOB_NAME%_stdout.txt | AI53: >>$$TRIS_BATCHDIR\Logs\%AUTO_JOB_NAME%_stderr.txt | AU53: Pass
A54: TRIS_RH_daily_420_MF_TR33107 | B54: TRIS_RH_dailyBox | C54: 23 | D54: s(TRIS_RH_daily_410_MF_TR33106) | F54: TR33107 TR015-Assocation table maitenance TR085-Association table data issue | G54: https://rxvavgtcv7.execute-api.us-east-1.amazonaws.com/dev/tr-33107 | H54: Pass Pass | I54: TR_RN_Maintain_TR33107_Trigger_Box | L54: Need to update | M54: Removes exceptions for terminated employees and add Holidays for new hires | N54: CMD | O54: TRIS_RH_dailyBox | P54: TRISBATCH@ameren | Q54: V_TRIS_BATCH | R54: $$TRIS_BATCHDIR\MaintainHolidays\MaintainHolidays.exe | S54: gx,mx | V54: 0 | Z54: 1 | AB54: F | AD54: DLTRISTeam@ameren.com | AE54: TRIS_RH_daily_437_Maintain_Holidays FAILED | AH54: >>$$TRIS_BATCHDIR\Logs\%AUTO_JOB_NAME%_stdout.txt | AI54: >>$$TRIS_BATCHDIR\Logs\%AUTO_JOB_NAME%_stderr.txt | AU54: Pass
A55: TRIS_RH_daily_430_MF_TR33102 | B55: TRIS_RH_dailyBox | C55: 24 | D55: s(TRIS_RH_daily_420_MF_TR33107) | F55: TR33102: TR009-HR/TRIS Interface TR129-Update employee effective dates | G55: https://rxvavgtcv7.execute-api.us-east-1.amazonaws.com/dev/tr-33102 | I55: TR_RN_Maintain_TR33102_Trigger_Box | L55: Cobol | M55: Seniority accrual -- Adds one day of seniority (TI0510) #RH#DV-HR-TR# CHG0000000xxxxx | N55: ZOS | O55: TRIS_RH_dailyBox | P55: ESPAE | Q55: V_TRIS_TRJobs2MF | T55: UE.STARTPDS | U55: TR33136N | V55: 0 | Z55: 1 | AB55: F | AD55: DLTRISTeam@ameren.com | AE55: TRIS_RH_daily_440_MF_TR33136 FAILED. Seniority accrual -- Adds one day of seniority (TI0510) | AF55: action=STOP,rc=1\:4095,result=FAILURE | AU55: Pass
A56: TRIS_RH_daily_435_Vacation_Allotment | B56: TRIS_RH_dailyBox | C56: 25 | D56: s(TRIS_RH_daily_430_MF_TR33102) | F56: $$TRIS_BATCHDIR\VacationAllotment\Ameren.TRIS.Server.Batch.VAllotment.exe | L56: /api/core/notification/v1/WorkdaySeniority/execute | M56: Send Seniority to Workday #RH#DV-HR-TR# CHG0000000xxxxx | N56: CMD | O56: TRIS_RH_dailyBox | P56: TRISBATCH@ameren | Q56: V_TRIS_BATCH | R56: $$TRIS_BATCHDIR\WorkdaySeniorityInterface\WorkdaySeniorityInterface.exe | S56: gx,mx | V56: 0 | Z56: 1 | AA56: TRIS | AB56: F | AC56: 3 | AD56: DLTRISTeam@ameren.com | AE56: TRIS_RH_workday_Seniority_Interface FAILED | AH56: >>$$TRIS_BATCHDIR\Logs\%AUTO_JOB_NAME%_stdout.txt | AI56: >>$$TRIS_BATCHDIR\Logs\%AUTO_JOB_NAME%_stderr.txt
A57: TRIS_RH_daily_437_Maintain_Holidays | B57: TRIS_RH_dailyBox | C57: 26 | D57: s(TRIS_RH_daily_435_Vacation_Allotment) | F57: $$TRIS_BATCHDIR\MaintainHolidays\MaintainHolidays.exe | L57: Cobol | M57: Auto Builds scheduled exception (Holiday, Vacation) time for employees in variable departments and all time for employees in fixed & exception based departments. #RH#DV-HR-TR# CHG0000000xxxxx (i.e. TRBE) | N57: ZOS | O57: TRIS_RH_dailyBox | P57: ESPAE | Q57: V_TRIS_TRJobs2MF | T57: UE.STARTPDS | U57: TR33115N | V57: 0 | Z57: 1 | AB57: F | AD57: DLTRISTeam@ameren.com | AE57: TRIS_RH_daily_450_MF_TR33115 FAILED. Auto Builds scheduled exception (Holiday, Vacation) time for employees in variable departments and all time for employees in fixed & exception based departments. | AF57: action=STOP,rc=1\:4095,result=FAILURE
A58: TRIS_RH_daily_440_MF_TR33136 | B58: TRIS_RH_dailyBox | C58: 27 | D58: s(TRIS_RH_daily_437_Maintain_Holidays) | F58: tr33136 TI0510-Seniority accruals TR127-TRIS to HCM seniority interface file | G58: https://rxvavgtcv7.execute-api.us-east-1.amazonaws.com/dev/tr-33136n | L58: Cobol | M58: Contract Preliminary Job #RH#DV-HR-TR# CHG0000000xxxxx | N58: ZOS | O58: TRIS_RH_dailyBox | P58: ESPAE | Q58: V_TRIS_TRJobs2MF | T58: UE.STARTPDS | U58: TR33103N | V58: 0 | W58: 01:00 | Y58: exclude_calendar: AM_holidays | Z58: 1 | AB58: F | AD58: DLTRISTeam@ameren.com | AE58: TRIS_RH_daily_600_MF_TR33103N FAILED. Contract Preliminary Job | AF58: action=STOP,rc=1\:4095,result=FAILURE
A59: TRIS_RH_daily_445_workday_Seniority_Interface | B59: TRIS_RH_dailyBox | C59: 28 | D59: s(TRIS_RH_daily_440_MF_TR33136) | F59: C:\TRISBatch\WorkdaySeniorityInterface\WorkdaySeniorityInterface.exe | L59: Cobol | M59: Contract Daily Job #RH#DV-HR-TR# CHG0000000xxxxx | N59: ZOS | O59: TRIS_RH_dailyBox | P59: ESPAE | Q59: V_TRIS_TRJobs2MF | T59: UE.STARTPDS | U59: TR33101N | V59: 0 | Z59: 1 | AB59: F | AD59: DLTRISTeam@ameren.com | AE59: TRIS_RH_daily_700_MF_TR33101N FAILED. Contract Daily Job | AF59: action=STOP,rc=1\:4095,result=FAILURE
A60: TRIS_RH_daily_450_MF_TR33115 | B60: TRIS_RH_dailyBox | C60: 29 | D60: s(TRIS_RH_daily_445_workday_Seniority_Interface) | F60: TR33115(TRBE) TI0504-Calculate TRBE date TI0503-TRBE build schduled time TI0538-TRBE straight time rebuild TI0507-TRBE retry locked employee (Not on Sunder's list) TI1003-TRBE error report TI0508-Update TRBE Sunday date | G60: https://rxvavgtcv7.execute-api.us-east-1.amazonaws.com/dev/tr-33115n | L60: Cobol | M60: TRIS BI extract #RN#DV-HR-TR# CHG00000000xxxx | N60: CMD | O60: TRIS_RH_dailyBox | P60: TRISBATCH@ameren | Q60: V_TRIS_BATCH | R60: $$TRIS_BATCHDIR\TRISIMRInterface\TRISBIExtract.exe | S60: gx,mx | V60: 1 | W60: 01:30 | Z60: 1 | AA60: TRIS | AB60: F | AC60: 3 | AD60: DLTRISTeam@ameren.com | AE60: TRISBI_RN_TRISBIExtract FAILED. | AH60: >>$$TRIS_BATCHDIR\Logs\%AUTO_JOB_NAME%_stdout.txt | AI60: >>$$TRIS_BATCHDIR\Logs\%AUTO_JOB_NAME%_stderr.txt | AU60: Pass
A61: TRIS_RH_daily_700_MF_TR33101N | B61: TRIS_RH_dailyBox | C61: 31 | D61: s(TRIS_RH_daily_450_MF_TR33115) | F61: TR33101N-Contract TRIS Daily job TR001-Extract actual time and adjustments TR051-Allowed time records TR052-Split extract file for sick leave TR003-Allowed time (actual time) processing TR050-Create sick leave detail TR021-Adjustment processing (TR33709) TR003C-CIPS Allowed time (actual time) processing (33708) TR050-Create CIPS Sick leave detail TR021C-CIPS adjustment processing TR105-Load sick leave detail and banks work tables TR106-Process sick leave TR108-Sick leave messages Report TR004-Payroll earnings proof (Report 33700) TR005-Payroll deviations (Report 33703) TR077-Sick Leave Detail Report (33780) TR029-Report 33701-Reported Time Adjustments (33701) | G61: https://rxvavgtcv7.execute-api.us-east-1.amazonaws.com/dev/tr-33101n | H61: TR_RN_ContractPayroll_TR33103N_Trigger_Box | I61: TR_RN_ContractPayroll_TR33103N_Trigger_Box | L61: /api/core/notification/v1/TRISIMRInterface/execute | M61: TRIS IMR email #RN#DV-HR-TR# CHG00000000xxxx | N61: CMD | O61: TRIS_RH_dailyBox | P61: TRISBATCH@ameren | Q61: V_TRIS_BATCH | R61: $$TRIS_BATCHDIR\TRISIMRInterface\IMREmail.exe | S61: gx,mx | V61: 1 | W61: 01:30 | Z61: 1 | AA61: TRIS | AB61: F | AC61: 3 | AD61: DLTRISTeam@ameren.com | AE61: TRISBI_RN_IMREmail FAILED. | AH61: >>$$TRIS_BATCHDIR\Logs\%AUTO_JOB_NAME%_stdout.txt | AI61: >>$$TRIS_BATCHDIR\Logs\%AUTO_JOB_NAME%_stderr.txt
A62: TRIS_RH_daily_600_MF_TR33103N | C62: 1 | D62: s(TRIS_RH_daily_700_MF_TR33101N,03.00) | F62: TR33103: TR033-Lock departments on the last prelim run before final TR001-Extract actual time and adjustments TR039-Missing time report (33729) TR051-Allowed time records TR052-Split extract file for sick leave TR003-Allowed time (actual time) processing TR050-Create sick leave detail TR021-Adjustment processing TR117-702 check previous year fmla TR003C-CIPS Allowed time (actual time) processing TR050-Create sick leave detail TR021C CIPS Adjustment processing TR104-Sick leave certification TR115-Sick leave FMLA updates TR105-Load sick leave detail and banks work tables TR106-Process sick leave TR108-Sick leave messages report (Report TR33801) TR004-Payroll earnings proof (Report 33700) TR005-Payroll deviations (Rpeort 33703) TR077-Sick leave detail report TR029-Report 33701-Reported Time Adjustments (33701) | G62: https://rxvavgtcv7.execute-api.us-east-1.amazonaws.com/dev/tr-33103n | I62: TR_RN_ContractPayroll_TR33103N_Trigger_Box | L62: Cobol | M62: Processes delayed overtime bank charges (TR008) at 00:05 every day. #RH#DV-HR-TR# CHG0000000xxxxx | N62: ZOS | P62: ESPAE | Q62: V_TRIS_TRJobs2MF | T62: UE.STARTTPDS | U62: TR33108 | V62: 1 | W62: 0.0034722222 | Z62: 1 | AB62: F | AD62: DLTRISTeam@ameren.com | AE62: TRIS_RH_Daily_everyday_0005_DelayedOTBanks_MF_TR33108. Processes delayed overtime bank charges at 00:05 every day. | AF62: action=STOP,rc=1\:4095,result=FAILURE
A63: TRIS_RH_daily_800_TRISBIExtract | D63: s(TRIS_RH_daily_450_MF_TR33115,03.00) | F63: C:\TRISBatch\TRISIMRInterface\TRISBIExtract.exe | L63: Need to update | M63: Maintains the TRIS TTR_DEPT table using the Accounting System Department Master from TRIS_RH_Daily_everyday_1900_DeptMaint_01_MF_TR33321 (TR013) #RH#DV-HR-TR# CHG0000000xxxxx | N63: ZOS | P63: ESPAE | Q63: V_TRIS_TRJobs2MF | T63: ITP.DV.STARTPDS | U63: TR33300N (NOT USED) | V63: 0 | Z63: 1 | AB63: F | AD63: DLTRISTeam@ameren.com | AE63: TRIS_RH_Daily_everyday_1900_DeptMaint_02_MF_TR33300 FAILED. Maintains the TRIS TTR_DEPT table using the Accounting System Department Master from TRIS_RH_Daily_everyday_1900_DeptMaint_01_MF_TR33321 (TR013) | AF63: action=STOP,rc=1\:4095,result=FAILURE
A64: TRIS_RH_daily_810_IMREmail | D64: s(TRIS_RH_daily_800_TRISBIExtract,01.00) | F64: C:\TRISBatch\TRISIMRInterface\IMREmail.exe | L64: /api/core/notification/v1/WorkdayFmla/execute | M64: Get Workday FMLA data to maintain the TTR_EMP_FMLA table. Runs at 19:00 everyday TTR_EMP_FMLA #RH#DV-HR-TR# CHG0000000xxxxx | N64: CMD | P64: TRISBATCH@ameren | Q64: V_TRIS_BATCH | R64: $$TRIS_BATCHDIR\WorkdayFLMAInterface\WorkdayFLMAInterface.exe | V64: 1 | W64: 0.79166667 | Z64: 1 | AA64: TRIS | AB64: F | AC64: 3 | AD64: DLTRISTeam@ameren.com | AE64: TRIS_RH_Daily_everyday_1900_workday_FMLA_Interface FAILED. Get Workday FMLA data to maintain the TTR_EMP_FMLA table. Look in \C\\TRISBatch\\Logs\ on server | AH64: >>$$TRIS_BATCHDIR\Logs\%AUTO_JOB_NAME%_stdout.txt | AI64: >>$$TRIS_BATCHDIR\Logs\%AUTO_JOB_NAME%_stderr.txt
A65: TRIS_RH_Daily_everyday_0005_DelayedOTBanks_MF_TR33108 | D65: su,mo,tu,we,th,fr,sa | E65: 0.0034722222 | F65: TR33108 TR008-Update of OT banks with the temporary OT banks | G65: https://rxvavgtcv7.execute-api.us-east-1.amazonaws.com/dev/batch-job | M65: Runs TRIS Daily Processes Monday through Saturday | N65: BOX | P65: TRISBATCH@ameren | S65: gx,mx | V65: 1 | W65: 0.041666667 | Z65: 1 | AC65: 3
A66: TRIS_RH_Daily_everyday_1900_DepartmentMaintenance | C66: 1 | D66: su,mo,tu,we,th,fr,sa | E66: 0.79166667 | F66: $$TRIS_BATCHDIR\DepartmentMaintenance\DepartmentMaintenance.exe | L66: /api/core/notification/v1/WorkdayPayroll/execute | M66: This runs the TRIS portion of the Executive payroll | N66: BOX | P66: TRISBATCH@ameren | S66: gx,mx | V66: 0 | Z66: 1 | AC66: 3
A67: TRIS_RH_Daily_everyday_1900_workday_FMLA_Interface | C67: 1 | D67: su,mo,tu,we,th,fr,sa | E67: 0.98958333 | F67: C:\TRISBatch\WorkdayFLMAInterface\WorkdayFLMAInterface.exe | L67: /api/core/notification/v1/jobs/buildFile | M67: Build File for DB2 Load of VJOB_TR #RH#DV-HR-TR# CHG0000000xxxxx | N67: CMD | O67: TRIS_RH_Executive_Final | P67: TRISBATCH@ameren | Q67: V_TRIS_BATCH | R67: $$TRIS_BATCHDIR\BuildDB2LoadFiles\BuildVjob\BuildVjob.exe | S67: gx,mx | V67: 0 | Z67: 1 | AA67: TRIS | AB67: F | AC67: 3 | AD67: DLTRISTeam@ameren.com | AE67: TRIS_RH_Executive_Final_010_BuildPayrollFiles_vJOB_TR FAILED | AH67: >>$$TRIS_BATCHDIR\Logs\%AUTO_JOB_NAME%_stdout.txt | AI67: >>$$TRIS_BATCHDIR\Logs\%AUTO_JOB_NAME%_stderr.txt
A68: TRIS_RH_Contract_Preliminary_OnRequest_MF_TR33103N | C68: 1 | D68: On demand | F68: TR33103: TR033-Lock departments on the last prelim run before final TR001-Extract actual time and adjustments TR039-Missing time report (33729) TR051-Allowed time records TR052-Split extract file for sick leave TR003-Allowed time (actual time) processing TR050-Create sick leave detail TR021-Adjustment processing TR117-702 check previous year fmla TR003C-CIPS Allowed time (actual time) processing TR050-Create sick leave detail TR021C CIPS Adjustment processing TR104-Sick leave certification TR115-Sick leave FMLA updates TR105-Load sick leave detail and banks work tables TR106-Process sick leave TR108-Sick leave messages report (Report TR33801) TR004-Payroll earnings proof (Report 33700) TR005-Payroll deviations (Rpeort 33703) TR077-Sick leave detail report TR029-Report 33701-Reported Time Adjustments (33701) | G68: https://rxvavgtcv7.execute-api.us-east-1.amazonaws.com/dev/tr-33103n | I68: TR_RN_ContractPayroll_TR33103N_Trigger_Box | L68: /api/core/notification/v1/departments/buildFile | M68: Build File for DB2 Load of VDEPT_TBL_TR #RH#DV-HR-TR# CHG0000000xxxxx | N68: CMD | O68: TRIS_RH_Executive_Final | P68: TRISBATCH@ameren | Q68: V_TRIS_BATCH | R68: $$TRIS_BATCHDIR\BuildDB2LoadFiles\BuildVdept\BuildVdept.exe | S68: gx,mx | V68: 0 | Z68: 1 | AA68: TRIS | AB68: F | AC68: 3 | AD68: DLTRISTeam@ameren.com | AE68: TRIS_RH_Executive_Final_020_BuildPayrollFiles_vDEPT_TBL_TR FAILED | AH68: >>$$TRIS_BATCHDIR\Logs\%AUTO_JOB_NAME%_stdout.txt | AI68: >>$$TRIS_BATCHDIR\Logs\%AUTO_JOB_NAME%_stderr.txt
L69: /api/core/notification/v1/jobcodes/buildFile | M69: Build File for DB2 Load of VJOBCODE_TBL_TR #RH#DV-HR-TR# CHG0000000xxxxx | N69: CMD | O69: TRIS_RH_Executive_Final | P69: TRISBATCH@ameren | Q69: V_TRIS_BATCH | R69: $$TRIS_BATCHDIR\BuildDB2LoadFiles\BuildVjobcode\BuildVjobcode.exe | S69: gx,mx | V69: 0 | Z69: 1 | AA69: TRIS | AB69: F | AC69: 3 | AD69: DLTRISTeam@ameren.com | AE69: TRIS_RH_Executive_Final_030_BuildPayrollFiles_vJOBCODE_TR FAILED | AH69: >>$$TRIS_BATCHDIR\Logs\%AUTO_JOB_NAME%_stdout.txt | AI69: >>$$TRIS_BATCHDIR\Logs\%AUTO_JOB_NAME%_stderr.txt
A70: TRIS_RH_Executive_Final | L70: /api/core/common/v1/JobSalaryStep/generate-file | M70: Build File for DB2 Load of VSAL_STEP_TBL_TR #RH#DV-HR-TR# CHG0000000xxxxx | N70: CMD | O70: TRIS_RH_Executive_Final | P70: TRISBATCH@ameren | Q70: V_TRIS_BATCH | R70: $$TRIS_BATCHDIR\BuildDB2LoadFiles\BuildVsalarystep\BuildVsalarystep.exe | S70: gx,mx | V70: 0 | Z70: 1 | AA70: TRIS | AB70: F | AC70: 3 | AD70: DLTRISTeam@ameren.com | AE70: TRIS_RH_Executive_Final_040_BuildPayrollFiles_vSAL_STEP_TR FAILED | AH70: >>$$TRIS_BATCHDIR\Logs\%AUTO_JOB_NAME%_stdout.txt | AI70: >>$$TRIS_BATCHDIR\Logs\%AUTO_JOB_NAME%_stderr.txt
A71: TRIS_RH_Executive_Final_010_BuildPayrollFiles_vJOB_TR | B71: TRIS_RH_Executive_Final | C71: 1 | D71: On demand | F71: C:\TRISBatch\BuildDB2LoadFiles\BuildVjob\BuildVjob.exe | L71: NA | M71: FTP of file to load into VJOB_TR load #RH#DV-HR-TR# CHG0000000xxxxx | N71: FTP | O71: TRIS_RH_Executive_Final | P71: ASYSFTPP@SYSC | Q71: V_TRIS_BATCH | S71: gx,mx | V71: 0 | Z71: 1 | AB71: F | AC71: 3 | AD71: DLTRISTeam@ameren.com | AE71: TRIS_RH_Executive_Final_050_BuildPayrollFiles_FTP_vJOB_TR FAILED | AJ71: A | AK71: UPLOAD | AL71: $$TRIS_BATCHDIR\\DB2LoadFiles\\VJOB-TR-EXTRACT.txt | AM71: ITP.DATA.JOB | AN71: SYSC.ameren.com | AO71: 0 | AP71: TRISBATCH@ameren | AQ71: Simple
A72: TRIS_RH_Executive_Final_020_BuildPayrollFiles_vDEPT_TBL_TR | B72: TRIS_RH_Executive_Final | C72: 2 | D72: s(TRIS_RH_Executive_Final_010_BuildPayrollFiles_vJOB_TR) | F72: C:\TRISBatch\BuildDB2LoadFiles\BuildVdept\BuildVdept.exe | L72: NA | M72: FTP of file to load into VDEPT_TBL_TR load #RH#DV-HR-TR# CHG0000000xxxxx | N72: FTP | O72: TRIS_RH_Executive_Final | P72: ASYSFTPP@SYSC | Q72: V_TRIS_BATCH | S72: gx,mx | V72: 0 | Z72: 1 | AB72: F | AC72: 3 | AD72: DLTRISTeam@ameren.com | AE72: TRIS_RH_Executive_Final_060_BuildPayrollFiles_FTP_vDEPT_TR FAILED | AJ72: A | AK72: UPLOAD | AL72: $$TRIS_BATCHDIR\\DB2LoadFiles\\VDEPT-TBL-TR-EXTRACT.txt | AM72: ITP.DATA.DEPT | AN72: SYSC.ameren.com | AO72: 0 | AP72: TRISBATCH@ameren | AQ72: Simple
A73: TRIS_RH_Executive_Final_030_BuildPayrollFiles_vJOBCODE_TR | B73: TRIS_RH_Executive_Final | C73: 3 | D73: s(TRIS_RH_Executive_Final_020_BuildPayrollFiles_vDEPT_TBL_TR) | F73: C:\TRISBatch\BuildDB2LoadFiles\BuildVjobcode\BuildVjobcode.exe | L73: NA | M73: FTP of file to load into VJOBCODE_TBL_TR load #RH#DV-HR-TR# CHG0000000xxxxx | N73: FTP | O73: TRIS_RH_Executive_Final | P73: ASYSFTPP@SYSC | Q73: V_TRIS_BATCH | S73: gx,mx | V73: 0 | Z73: 1 | AB73: F | AC73: 3 | AD73: DLTRISTeam@ameren.com | AE73: TRIS_RH_Executive_Final_070_BuildPayrollFiles_FTP_vJOBCODE FAILED | AJ73: A | AK73: UPLOAD | AL73: $$TRIS_BATCHDIR\\DB2LoadFiles\\VJOBCODE-TBL-TR-EXTRACT.txt | AM73: ITP.DATA.JOBCODE | AN73: SYSC.ameren.com | AO73: 0 | AP73: TRISBATCH@ameren | AQ73: Simple
A74: TRIS_RH_Executive_Final_040_BuildPayrollFiles_vSAL_STEP_TR | B74: TRIS_RH_Executive_Final | C74: 4 | D74: s(TRIS_RH_Executive_Final_030_BuildPayrollFiles_vJOBCODE_TR ) | F74: C:\TRISBatch\BuildDB2LoadFiles\BuildVsalarystep\BuildVsalarystep.exe | L74: NA | M74: FTP of file to load into VSAL_STEP_TBL_TR load #RH#DV-HR-TR# CHG0000000xxxxx | N74: FTP | O74: TRIS_RH_Executive_Final | P74: ASYSFTPP@SYSC | Q74: V_TRIS_BATCH | S74: gx,mx | V74: 0 | Z74: 1 | AB74: F | AC74: 3 | AD74: DLTRISTeam@ameren.com | AE74: TRIS_RH_Executive_Final_080_BuildPayrollFiles_FTP_vSAL FAILED | AJ74: A | AK74: UPLOAD | AL74: $$TRIS_BATCHDIR\\DB2LoadFiles\\VSAL-STEP-TBL-TR-EXTRACT.txt | AM74: ITP.DATA.SAL.STP | AN74: SYSC.ameren.com | AO74: 0 | AP74: TRISBATCH@ameren | AQ74: Simple
A75: TRIS_RH_Executive_Final_050_BuildPayrollFiles_FTP_vJOB_TR | B75: TRIS_RH_Executive_Final | C75: 5 | D75: s(TRIS_RH_Executive_Final_040_BuildPayrollFiles_vSAL_STEP_TR) | L75: Cobol | M75: Moves the Files that were sent in jobs TRIS_RH_Executive_Final_050, TRIS_RH_Executive_Final_060, TRIS_RH_Executive_Final_070, & TRIS_RH_Executive_Final_080 from Mainframe FTP directory to Mainframe datasets. It then loads the data into DB2 Tables #RH#DV-HR-TR# CHG0000000xxxxx | N75: ZOS | O75: TRIS_RH_Executive_Final | P75: ESPAE | Q75: V_TRIS_TRJobs2MF | T75: CF.STARTPDS | U75: AR13895 | V75: 0 | Z75: 1 | AB75: F | AD75: DLTRISTeam@ameren.com | AE75: TRIS_RH_Executive_Final_200_MF_AR13895 FAILED. Moves the Files that were sent in jobs TRIS_RH_Executive_Final_050, TRIS_RH_Executive_Final_060, TRIS_RH_Executive_Final_070, & TRIS_RH_Executive_Final_080 from Mainframe FTP directory to Mainframe datase | AF75: action=STOP,rc=1\:4095,result=FAILURE
A76: TRIS_RH_Executive_Final_060_BuildPayrollFiles_FTP_vDEPT_TR | B76: TRIS_RH_Executive_Final | C76: 6 | D76: s(TRIS_RH_Executive_Final_050_BuildPayrollFiles_FTP_vJOB_TR) | M76: Fills tables for view VJOB_TR_EFF which allows the HR History records to have a start and end date versus just an effective date. #RH#DV-HR-TR# CHG00000000xxxx | N76: CMD | O76: TRIS_RH_Executive_Final | P76: TRISBATCH@ameren | Q76: V_TRIS_BATCH | R76: $$TRIS_BATCHDIR\PSJobViewRefresh\PS2TRIS.exe | S76: gx,mx | V76: 0 | Z76: 1 | AA76: TRIS | AB76: F | AC76: 3 | AD76: DLTRISTeam@ameren.com | AE76: TRIS_RH_Executive_Final_300_Build_HR_History_View FAILED. Fills tables for view VJOB_TR_EFF which allows the HR History records to have a start and end date versus just an effective date. Look in \C\\TRISBatch\\Logs\ on server | AH76: >>$$TRIS_BATCHDIR\Logs\%AUTO_JOB_NAME%_stdout.txt | AI76: >>$$TRIS_BATCHDIR\Logs\%AUTO_JOB_NAME%_stderr.txt
A77: TRIS_RH_Executive_Final_070_BuildPayrollFiles_FTP_vJOBCODE | B77: TRIS_RH_Executive_Final | C77: 7 | D77: s(TRIS_RH_Executive_Final_060_BuildPayrollFiles_FTP_vDEPT_TR) | L77: /api/core/notification/v1/CopToUop/update | M77: Changes unapproved COP time to UOP #RH#DV-HR-TR# CHG0000000xxxxx | N77: CMD | O77: TRIS_RH_Executive_Final | P77: TRISBATCH@ameren | Q77: V_TRIS_BATCH | R77: $$TRIS_BATCHDIR\COPtoUOP\COPtoUOP.exe | S77: gx,mx | V77: 0 | Z77: 1 | AA77: TRIS | AB77: F | AC77: 3 | AD77: DLTRISTeam@ameren.com | AE77: TRIS_RH_Executive_Final_310_COPtoUOP FAILED | AH77: >>$$TRIS_BATCHDIR\Logs\%AUTO_JOB_NAME%_stdout.txt | AI77: >>$$TRIS_BATCHDIR\Logs\%AUTO_JOB_NAME%_stderr.txt
A78: TRIS_RH_Executive_Final_080_BuildPayrollFiles_FTP_vSAL | B78: TRIS_RH_Executive_Final | C78: 8 | D78: s(TRIS_RH_Executive_Final_070_BuildPayrollFiles_FTP_vJOBCODE) | L78: Cobol | M78: Executive Final Payroll Processing that produces Payroll file that is used in TRIS_RH_Executive_Final_550_Send_ToPayroll to build a JSON request to send to Workday #RH#DV-HR-TR# CHG0000000xxxxx | N78: ZOS | O78: TRIS_RH_Executive_Final | P78: ESPAE | Q78: V_TRIS_TRJobs2MF | T78: UE.STARTPDS | U78: TR33201N | V78: 0 | Z78: 1 | AB78: F | AD78: DLTRISTeam@ameren.com | AE78: TRIS_RH_Executive_Final_410_MF_TR33201 FAILED. Executive Final Payroll Processing that produces Payroll file that is used in TRIS_RH_Executive_Final_550_Send_ToPayroll to build a JSON request to send to Workday | AF78: action=STOP,rc=1\:4095,result=FAILURE
A79: TRIS_RH_Executive_Final_200_MF_AR13895 | B79: TRIS_RH_Executive_Final | C79: 9 | D79: s(TRIS_RH_Executive_Final_080_BuildPayrollFiles_FTP_vSAL) | F79: TR33003: IEBGENERs to manage files and Utilities to load tables | L79: Cobol | M79: Sends the Executive Payroll file built in TRIS_RH_Executive_Final_410_MF_TR33201 via FTP to the Autosys server #RH#DV-HR-TR# CHG0000000xxxxx | N79: ZOS | O79: TRIS_RH_Executive_Final | P79: ESPAE | Q79: V_TRIS_TRJobs2MF | T79: CF.STARTPDS | U79: AR13587 | V79: 0 | Z79: 1 | AB79: F | AD79: DLTRISTeam@ameren.com | AE79: TRIS_RH_Executive_Final_420_MF_AR13587 FAILED. Sends the Executive Payroll file built in TRIS_RH_Executive_Final_410_MF_TR33201 via FTP to the Autosys server | AF79: action=STOP,rc=1\:4095,result=FAILURE
A80: TRIS_RH_Executive_Final_300_Build_HR_History_View | B80: TRIS_RH_Executive_Final | C80: 10 | D80: s(TRIS_RH_Executive_Final_200_MF_AR13895) | F80: C:\TRISBatch\PSJobViewRefresh\PS2TRIS.exe | L80: Cobol | M80: Copies Mainframe payroll file on the Autosys server to the RIS folder on the Corporate share drive #RH#DV-HR-TR# CHG0000000xxxxx | N80: CMD | O80: TRIS_RH_Executive_Final | P80: TRISBATCH@ameren | Q80: V_TRIS_MFFTP | R80: %FTPDir2%\Exec\copy_file.bat %FTPDir%\tr_payroll_exec.txt \\corp.dir.ameren.com\dfs\Orgdrv\TRIS\MKS\tr_payroll_exec.txt | S80: gx,mx | V80: 0 | Z80: 1 | AA80: TRIS | AB80: F | AC80: 3 | AD80: DLTRISTeam@ameren.com | AE80: TRIS_RH_Executive_Final_530_Send_Copy_PayrollFile JOB FAILED. Copies Mainframe payroll file on the Autosys server to the RIS folder on the Corporate share drive. Look in \C\\TRISBatch\\Logs\ on server | AH80: %FTPDir2%\Logs\Payroll_stdout.txt | AI80: %FTPDir2%\Logs\Payroll_stderr.txt
A81: TRIS_RH_Executive_Final_310_COPtoUOP | B81: TRIS_RH_Executive_Final | C81: 11 | D81: s(TRIS_RH_Executive_Final_300_Build_HR_History_View) | F81: C:\TRISBatch\COPtoUOP\COPtoUOP.exe | L81: Cobol | M81: Moves Mainframe Payroll file from the TRIS folder on the Corporate share drive to the TRIS Server (V_TRIS_BATCH) #RH#DV-HR-TR# CHG0000000xxxxx | N81: CMD | O81: TRIS_RH_Executive_Final | P81: TRISBATCH@ameren | Q81: V_TRIS_BATCH | R81: $$TRIS_BATCHDIR\MoveMainframeFiles\MovePayrollFile\MovePayrollFile.exe | S81: gx,mx | V81: 0 | Z81: 1 | AA81: TRIS | AB81: F | AC81: 3 | AD81: DLTRISTeam@ameren.com | AE81: TRIS_RH_Executive_Final_540_Send_Move_PayrollFile FAILED. Moves Mainframe Payroll file from the TRIS folder on the Corporate share drive to the TRIS Server (V_TRIS_BATCH). Look in \C\\TRISBatch\\Logs\ on server | AH81: >>$$TRIS_BATCHDIR\Logs\%AUTO_JOB_NAME%_stdout.txt | AI81: >>$$TRIS_BATCHDIR\Logs\%AUTO_JOB_NAME%_stderr.txt
A82: TRIS_RH_Executive_Final_410_MF_TR33201 | B82: TRIS_RH_Executive_Final | C82: 12 | D82: s(TRIS_RH_Executive_Final_310_COPtoUOP) | F82: TR33201-Executive TRIS final job TR001-Extract actual time and adjustments TR033-Unlock departments TR039-Missing time report (33729) TR051-Allowed time records TR052-Split sick leave extract file TR003-Allowed time (actual time) processing (33708) TR050-Create sick leave detail TR021-Adjustment processing TR103-Management exempt partial day TR004-Payroll earnings proof (Report 33700) TR005-Payroll deviations (Report 33703) TR044-Assign Executive OT codes TR060-Paysheet prep TR077-Sick Leave Detail Report (33780) TR029-Report 33701-Reported Time Adjustments (33701) TR026-Split exception codes for allowed time TR135-Allowed time detail table update TI534-Create Variable accounting variation file TI1009-Create GES report TR128-Management sick leave balance report TR037-Update final cycle number | G82: https://rxvavgtcv7.execute-api.us-east-1.amazonaws.com/dev/tr-33201 | I82: TR_RN_ExecutivePayroll_TR33201_Trigger_Box | L82: /api/core/notification/v1/WorkdayPayroll/execute | M82: Sends Payroll data to Workday #RH#DV-HR-TR# CHG0000000xxxxx | N82: CMD | O82: TRIS_RH_Executive_Final | P82: TRISBATCH@ameren | Q82: V_TRIS_BATCH | R82: $$TRIS_BATCHDIR\WorkdayPayrollInterface\WorkdayPayrollInterface.exe | S82: gx,mx | V82: 0 | Z82: 1 | AA82: TRIS | AB82: F | AC82: 3 | AD82: DLTRISTeam@ameren.com | AE82: TRIS_RH_Executive_Final_550_Send_ToPayroll FAILED. Sends Payroll data to Workday. Look in \C\\TRISBatch\\Logs\ on server | AH82: >>$$TRIS_BATCHDIR\Logs\%AUTO_JOB_NAME%_stdout.txt | AI82: >>$$TRIS_BATCHDIR\Logs\%AUTO_JOB_NAME%_stderr.txt
A83: TRIS_RH_Executive_Final_420_MF_AR13587 | B83: TRIS_RH_Executive_Final | C83: 13 | D83: s(TRIS_RH_Executive_Final_410_MF_TR33201) | F83: TR33005-Executive payroll Sends executive payroll file to workday (FTP) | L83: Cobol | M83: Executive Preliminary Job on Request #RH#DV-HR-TR# CHG0000000xxxxx | N83: ZOS | P83: ESPAE | Q83: V_TRIS_TRJobs2MF | T83: UE.STARTPDS | U83: TR33112 | V83: 0 | Z83: 1 | AB83: F | AD83: DLTRISTeam@ameren.com | AE83: TRIS_RH_Executive_Preliminary_OnRequest_MF_TR33112 FAILED. Contract Preliminary Job on Request | AF83: action=STOP,rc=1\:4095,result=FAILURE
A84: TRIS_RH_Executive_Final_530_Send_Copy_PayrollFile | B84: TRIS_RH_Executive_Final | C84: 14 | D84: s(TRIS_RH_Executive_Final_420_MF_AR13587) | F84: %FTPDir2%\Exec\copy_file.bat %FTPDir%\tr_payroll_exec.txt \\corp.dir.ameren.com\dfs\Orgdrv\TRIS\MKS\tr_payroll_exec.txt | M84: The PDCLOSE process runs on the 1st working day of the month | N84: BOX | P84: TRISBATCH@ameren | S84: gx,mx | V84: 1 | W84: 0.16666667 | X84: run_calendar: AM_1stWkDyNoHol | Z84: 1 | AC84: 3
A85: TRIS_RH_Executive_Final_540_Send_Move_PayrollFile | B85: TRIS_RH_Executive_Final | C85: 15 | D85: s(TRIS_RH_Executive_Final_530_Send_Copy_PayrollFile) | F85: C:\TRISBatch\MoveMainframeFiles\MovePayrollFile\MovePayrollFile.exe | L85: /api/core/notification/v1/monthly-labor-hours/process | M85: Inserts fixed accounting allocations into METHDBA.TTR_OTTC_DEPT_FIXED_ALLOCATION & METHDBA.TTR_OTTC_EMP_FIXED_ALLOCATION. Used for Monthly Labor hours report #RH#DV-HR-TR# CHG0000000xxxxx | N85: CMD | O85: TRIS_RH_monthly_000_PDCLOSEBox | P85: TRISBATCH@ameren | Q85: V_TRIS_BATCH | R85: $$TRIS_BATCHDIR\PayrollDistributionFixedAllocationsInterface\PayrollDistributionFixedAllocationsInterface.exe | S85: gx,mx | V85: 0 | Z85: 1 | AA85: TRIS | AB85: F | AC85: 3 | AD85: DLTRISTeam@ameren.com | AE85: TRIS_RH_monthly_010_FixedAccountingAllocationsInterface failed | AH85: >>$$TRIS_BATCHDIR\Logs\%AUTO_JOB_NAME%_stdout.txt | AI85: >>$$TRIS_BATCHDIR\Logs\%AUTO_JOB_NAME%_stderr.txt
A86: TRIS_RH_Executive_Final_550_Send_ToPayroll | B86: TRIS_RH_Executive_Final | C86: 16 | D86: s(TRIS_RH_Executive_Final_540_Send_Move_PayrollFile) | F86: C:\TRISBatch\WorkdayPayrollInterface\WorkdayPayrollInterface.exe | L86: /api/core/notification/v1/accrual | M86: Inserts summarized TRIS Accrual hours by department for the Calendar month into TTR_OTTC_ACCRUAL_INTF . A process, written by the Mule Soft integration team, will follow this job and will call the GET Accrual API . #RH#DV-HR-TR# CHG0000000xxxxx | N86: CMD | O86: TRIS_RH_monthly_000_PDCLOSEBox | P86: TRISBATCH@ameren | Q86: V_TRIS_BATCH | R86: $$TRIS_BATCHDIR\PayrollAccrualMonthlyInterface\PayrollAccrualMonthlyInterface.exe | S86: gx,mx | V86: 0 | Z86: 1 | AA86: TRIS | AB86: F | AC86: 3 | AD86: DLTRISTeam@ameren.com | AE86: TRIS_RH_monthly_020_PayrollAccruals JOB FAILED. Inserts summarized TRIS Accrual hours by department f for the Calendar month into TTR_OTTC_ACCRUAL_INTF . A process, written by MuleSoft will be dependent on this job | AH86: >>$$TRIS_BATCHDIR\Logs\%AUTO_JOB_NAME%_stdout.txt | AI86: >>$$TRIS_BATCHDIR\Logs\%AUTO_JOB_NAME%_stderr.txt
L87: /api/core/payroll/v1/PayrollDistributionMonthlyInterface/monthly-labor-accounting | M87: Inserts summarized TRIS Accrual hours by department for the Calendar month into METHDBA.TTR_OTTC_LABOR_ACCOUNTING_INTF . A process, written by the Mule Soft integration team, will follow this job and will call the GET LaborAccounting API . #RH#DV-HR-TR# CHG0000000xxxxx | N87: CMD | O87: TRIS_RH_monthly_000_PDCLOSEBox | P87: TRISBATCH@ameren | Q87: V_TRIS_BATCH | R87: $$TRIS_BATCHDIR\PayrollDistributionMonthlyInterface\PayrollDistributionMonthlyInterface.exe | S87: gx,mx | V87: 0 | Z87: 1 | AA87: TRIS | AB87: F | AC87: 3 | AD87: DLTRISTeam@ameren.com | AE87: TRIS_RH_monthly_030_PayrollDistributionInterface JOB FAILED. | AH87: >>$$TRIS_BATCHDIR\Logs\%AUTO_JOB_NAME%_stdout.txt | AI87: >>$$TRIS_BATCHDIR\Logs\%AUTO_JOB_NAME%_stderr.txt
A88: TRIS_RH_Executive_Preliminary_OnRequest_MF_TR33112 | B88: TRIS_RH_Executive_Final | C88: 1 | D88: On Demand | F88: TR33112-Executive TRIS preliminary job TR033-Lock departments on the last prelim run before final TR001-Extract actual time and adjustments TR039-Missing time report (33729) TR051-Allowed time records TR052-Split sick leave extract file TR003-Allowed time (actual time) processing (33708) TR050-Create sick leave detail TR021-Adjustment Processing (33709) TR103-Management exempt partial day TR004-Payroll earnings proof (Report 33700) TR005-Payroll deviations (Report 33703) TR029-Report 33701-Reported Time Adjustments (33701) TR048-part time/ temporary hours worked TR128-Management sick leave balance report | G88: https://rxvavgtcv7.execute-api.us-east-1.amazonaws.com/dev/tr-33112 | I88: TR_RN_OnRequest_TR33112_Trigger_Box | L88: /api/core/notification/v1/MaximoAccountingInterface/create | M88: Inserts summarized TRIS time by department for each MAXIMO job number job task combination charged in TRIS for the Calendar month into TTR_ASPIRE_MAXIMO_ACCOUNTING_INTF . A process, written by the Mule Soft integration team, will follow this job and will call the GET Accounting API . #RH#DV-HR-TR# CHG0000000xxxxx | N88: CMD | P88: TRISBATCH@ameren | Q88: V_TRIS_BATCH | R88: $$TRIS_BATCHDIR\MaximoAccountingInterface\MaximoAccountingInterface.exe | S88: gx,mx | V88: 0 | W88: 0.00069444444 | X88: run_calendar: AM_1stWkDyNoHol | Z88: 1 | AA88: TRIS | AB88: F | AC88: 3 | AD88: DLTRISTeam@ameren.com | AE88: TRIS_RH_monthly_100_MaximoAccountingInterface JOB FAILED. Inserts summarized TRIS time by department for each MAXIMO job number job task combination charged in TRIS for the Calendar month into TTR_ASPIRE_MAXIMO_ACCOUNTING_INTF . A process, written by | AH88: >>$$TRIS_BATCHDIR\Logs\%AUTO_JOB_NAME%_stdout.txt | AI88: >>$$TRIS_BATCHDIR\Logs\%AUTO_JOB_NAME%_stderr.txt
L89: /api/core/notification/v1/monthly-labor-hours/process | M89: Loads the Mainframe Labor Hours file into the TTR_LABOR_HOURS table for OBIEE which will distribute the Monthly Labor Hours Reports and collects signatures. TRIS_RH_monthly_110_Copy_LaborHoursFile copied Monthly Labor Hours file to TRIS folder on the Corporate share drive. TRIS_RH_monthly_120_Move_LaborHoursFile moved the Mainframe Labor Hours file from TRIS folder on the Corporate share drive to TRIS Server. #RN#DV-HR-TR# CHG0000000xxxxx | N89: CMD | O89: TRIS_RH_monthly_000_PDCLOSEBox | P89: TRISBATCH@ameren | Q89: V_TRIS_BATCH | R89: $$TRIS_BATCHDIR\MonthlyLaborHoursInterface\MonthlyLaborHoursInterface.exe | S89: gx,mx | V89: 0 | Z89: 1 | AA89: TRIS | AB89: F | AC89: 3 | AD89: DLTRISTeam@ameren.com | AE89: TRIS_RH_monthly_130_LaborHours_Interface FAILED. Loads the Mainframe Labor Hours file into the TTR_LABOR_HOURS table for OBIEE which will distribute the Monthly Labor Hours Reports and collects signatures. TRIS_RH_monthly_110_Copy_LaborHoursFile copied | AH89: >>$$TRIS_BATCHDIR\Logs\%AUTO_JOB_NAME%_stdout.txt | AI89: >>$$TRIS_BATCHDIR\Logs\%AUTO_JOB_NAME%_stderr.txt
A90: TRIS_RH_OnRequest_HRinterface_MF_TR33102 | C90: 1 | D90: On Demand | F90: TR33102: TR009-HR/TRIS Interface TR129-Update employee effective dates | G90: https://rxvavgtcv7.execute-api.us-east-1.amazonaws.com/dev/tr-33102 | I90: TR_RN_Maintain_TR33102_Trigger_Box | L90: /api/core/notification/v1/departments/common/buildFile | M90: Build File for DB2 Load of TAR_COMN_DEPT_TBL #RH#DV-HR-TR# CHG0000000xxxxx | N90: CMD | O90: TRIS_RH_sundayBox | P90: TRISBATCH@ameren | Q90: V_TRIS_BATCH | R90: $$TRIS_BATCHDIR\BuildDB2LoadFiles\BuildCommonDepartment\BuildCommonDepartment.exe | S90: gx,mx | V90: 0 | Z90: 1 | AA90: TRIS | AB90: F | AC90: 3 | AD90: DLTRISTeam@ameren.com | AE90: TRIS_RH_sunday_010_BuildCommon_Department FAILED | AH90: >>$$TRIS_BATCHDIR\Logs\%AUTO_JOB_NAME%_stdout.txt | AI90: >>$$TRIS_BATCHDIR\Logs\%AUTO_JOB_NAME%_stderr.txt | AL90: F
L91: /api/core/notification/v1/employees/buildFile | M91: Builds File for DB2 Load of TAR_COMN_EMP_TBL and Builds for DB2 Load of THRDB_EMPLOYEE_TBL #RH#DV-HR-TR# CHG0000000xxxxx | N91: CMD | O91: TRIS_RH_sundayBox | P91: TRISBATCH@ameren | Q91: V_TRIS_BATCH | R91: $$TRIS_BATCHDIR\BuildDB2LoadFiles\BuildCommonEmployeeFile\BuildCommonEmployeeFile.exe | S91: gx,mx | V91: 0 | Z91: 1 | AA91: TRIS | AB91: F | AC91: 3 | AD91: DLTRISTeam@ameren.com | AE91: TRIS_RH_sunday_020_BuildCommon_Employee FAILED | AH91: >>$$TRIS_BATCHDIR\Logs\%AUTO_JOB_NAME%_stdout.txt | AI91: >>$$TRIS_BATCHDIR\Logs\%AUTO_JOB_NAME%_stderr.txt
A92: TRIS_RH_monthly_000_PDCLOSEBox | D92: AM_1stWkDyNoHol | E92: 0.16666667 | L92: NA | M92: FTP of file to load into TAR_COMN_DEPT_TBL load #RH#DV-HR-TR# CHG0000000xxxxx | N92: FTP | O92: TRIS_RH_sundayBox | P92: ASYSFTPP@SYSC | Q92: V_TRIS_BATCH | S92: gx,mx | V92: 0 | Z92: 1 | AB92: F | AC92: 3 | AD92: DLTRISTeam@ameren.com | AE92: TRIS_RH_sunday_030_BuildCommon_FTP_Department FAILED | AJ92: A | AK92: UPLOAD | AL92: $$TRIS_BATCHDIR\\DB2LoadFiles\\CommonDepartment-EXTRACT.txt | AM92: ITP.DATA.GDG.DEPT.EXTRT | AN92: SYSC.ameren.com | AO92: 0 | AP92: TRISBATCH@ameren | AQ92: Simple
A93: TRIS_RH_monthly_010_FixedAccountingAllocationsInterface | B93: TRIS_RH_monthly_000_PDCLOSEBox | C93: 1 | F93: $$TRIS_BATCHDIR\PayrollDistributionFixedAllocationsInterface\PayrollDistributionFixedAllocationsInterface.exe | L93: NA | M93: FTP a file to load into TAR_COMN_EMPL_TBL #RH#DV-HR-TR# CHG0000000xxxxx | N93: FTP | O93: TRIS_RH_sundayBox | P93: ASYSFTPP@SYSC | Q93: V_TRIS_BATCH | S93: gx,mx | V93: 0 | Z93: 1 | AB93: F | AC93: 3 | AD93: DLTRISTeam@ameren.com | AE93: TRIS_RH_sunday_040_BuildCommon_FTP_Employee FAILED | AJ93: A | AK93: UPLOAD | AL93: $$TRIS_BATCHDIR\\DB2LoadFiles\\COMNEMPL-EXTRACT.txt | AM93: ITP.DATA.GDG.EMPL.EXTRT | AN93: SYSC.ameren.com | AO93: 0 | AP93: TRISBATCH@ameren | AQ93: Simple
A94: TRIS_RH_monthly_020_PayrollAccruals | B94: TRIS_RH_monthly_000_PDCLOSEBox | C94: 2 | D94: s(TRIS_RH_monthly_010_FixedAccountingAllocationsInterface) | F94: $$TRIS_BATCHDIR\PayrollAccrualMonthlyInterface\PayrollAccrualMonthlyInterface.exe | L94: NA | M94: FTP a File for DB2 Load of THRDB_EMPLOYEE_TBL #RH#DV-HR-TR# CHG0000000xxxxx | N94: FTP | O94: TRIS_RH_sundayBox | P94: ASYSFTPP@SYSC | Q94: V_TRIS_BATCH | S94: gx,mx | V94: 0 | Z94: 1 | AB94: F | AC94: 3 | AD94: DLTRISTeam@ameren.com | AE94: TRIS_RH_sunday_050_BuildCommon_FTP_THRDBEmployee FAILED | AJ94: A | AK94: UPLOAD | AL94: $$TRIS_BATCHDIR\\DB2LoadFiles\\THRDB-EMPLOYEE-EXTRACT.txt | AM94: ITP.DATA.GDG.EMPL.DB2 | AN94: SYSC.ameren.com | AO94: 0 | AP94: TRISBATCH@ameren | AQ94: Simple
A95: TRIS_RH_monthly_030_PayrollDistributionInterface | B95: TRIS_RH_monthly_000_PDCLOSEBox | C95: 3 | D95: s(TRIS_RH_monthly_020_PayrollAccruals) | F95: $$TRIS_BATCHDIR\PayrollDistributionMonthlyInterface\PayrollDistributionMonthlyInterface.exe | L95: /api/core/notification/v1/build/associations/buildFile | M95: Builds File for maintaining the TTR_ASSOCIATIONS table in mainframe job UE.STARTPDS(TR33107N) #RH#DV-HR-TR# CHG0000000xxxxx | N95: CMD | O95: TRIS_RH_sundayBox | P95: TRISBATCH@ameren | Q95: V_TRIS_BATCH | R95: $$TRIS_BATCHDIR\BuildDB2LoadFiles\BuildAssociations\BuildAssociations.exe | S95: gx,mx | V95: 0 | Z95: 1 | AA95: TRIS | AB95: F | AC95: 3 | AD95: DLTRISTeam@ameren.com | AE95: TRIS_RH_sunday_070_BuildCommon_Associations FAILED | AH95: >>$$TRIS_BATCHDIR\Logs\%AUTO_JOB_NAME%_stdout.txt | AI95: >>$$TRIS_BATCHDIR\Logs\%AUTO_JOB_NAME%_stderr.txt
A96: TRIS_RH_monthly_150_LaborHours_Interface | B96: TRIS_RH_monthly_000_PDCLOSEBox | C96: 4 | D96: s(TRIS_RH_monthly_030_PayrollDistributionInterface) | F96: C:\TRISBatch\MonthlyLaborHoursInterface\MonthlyLaborHoursInterface.exe | L96: NA | M96: FTP a file to process in UE.STARTPDS(TR33107N) #RH#DV-HR-TR# CHG0000000xxxxx | N96: FTP | O96: TRIS_RH_sundayBox | P96: ASYSFTPP@SYSC | Q96: V_TRIS_BATCH | S96: gx,mx | V96: 0 | Z96: 1 | AB96: F | AC96: 3 | AD96: DLTRISTeam@ameren.com | AE96: TRIS_RH_sunday_080_BuildCommon_FTP_Associations FAILED | AJ96: A | AK96: UPLOAD | AL96: $$TRIS_BATCHDIR\\DB2LoadFiles\\TTR-ASSOCIATIONS-EXTRACT.txt | AM96: ITP.DATA.DATA.DPTTABLE | AN96: SYSC.ameren.com | AO96: 0 | AP96: TRISBATCH@ameren | AQ96: Simple
L97: /api/core/notification/v1/jobs/buildFile | M97: Build File for DB2 Load of VJOB_TR #RH#DV-HR-TR# CHG0000000xxxxx | N97: CMD | O97: TRIS_RH_sundayBox | P97: TRISBATCH@ameren | Q97: V_TRIS_BATCH | R97: $$TRIS_BATCHDIR\BuildDB2LoadFiles\BuildVjob\BuildVjob.exe | S97: gx,mx | V97: 0 | Z97: 1 | AA97: TRIS | AB97: F | AC97: 3 | AD97: DLTRISTeam@ameren.com | AE97: TRIS_RH_sunday_100_BuildPayrollFiles_vJOB_TR FAILED | AH97: >>$$TRIS_BATCHDIR\Logs\%AUTO_JOB_NAME%_stdout.txt | AI97: >>$$TRIS_BATCHDIR\Logs\%AUTO_JOB_NAME%_stderr.txt
A98: TRIS_RH_monthly_100_MaximoAccountingInterface | C98: 1 | D98: AM_1stWkDyNoHol | E98: 0.00069444444 | F98: $$TRIS_BATCHDIR\MaximoAccountingInterface\MaximoAccountingInterface.exe | L98: /api/core/notification/v1/departments/buildFile | M98: Build File for DB2 Load of VDEPT_TBL_TR #RH#DV-HR-TR# CHG0000000xxxxx | N98: CMD | O98: TRIS_RH_sundayBox | P98: TRISBATCH@ameren | Q98: V_TRIS_BATCH | R98: $$TRIS_BATCHDIR\BuildDB2LoadFiles\BuildVdept\BuildVdept.exe | S98: gx,mx | V98: 0 | Z98: 1 | AA98: TRIS | AB98: F | AC98: 3 | AD98: DLTRISTeam@ameren.com | AE98: TRIS_RH_sunday_110_BuildPayrollFiles_vDEPT_TBL_TR FAILED | AH98: >>$$TRIS_BATCHDIR\Logs\%AUTO_JOB_NAME%_stdout.txt | AI98: >>$$TRIS_BATCHDIR\Logs\%AUTO_JOB_NAME%_stderr.txt
L99: /api/core/notification/v1/jobcodes/buildFile | M99: Build File for DB2 Load of VJOBCODE_TBL_TR #RH#DV-HR-TR# CHG0000000xxxxx | N99: CMD | O99: TRIS_RH_sundayBox | P99: TRISBATCH@ameren | Q99: V_TRIS_BATCH | R99: $$TRIS_BATCHDIR\BuildDB2LoadFiles\BuildVjobcode\BuildVjobcode.exe | S99: gx,mx | V99: 0 | Z99: 1 | AA99: TRIS | AB99: F | AC99: 3 | AD99: DLTRISTeam@ameren.com | AE99: TRIS_RH_sunday_120_BuildPayrollFiles_vJOBCODE_TBL_TR FAILED | AH99: >>$$TRIS_BATCHDIR\Logs\%AUTO_JOB_NAME%_stdout.txt | AI99: >>$$TRIS_BATCHDIR\Logs\%AUTO_JOB_NAME%_stderr.txt
A100: TRIS_RH_sundayBox | D100: su | E100: 0.375 | L100: /api/core/common/v1/JobSalaryStep/generate-file | M100: Build File for DB2 Load of VSAL_STEP_TBL_TR #RH#DV-HR-TR# CHG0000000xxxxx | N100: CMD | O100: TRIS_RH_sundayBox | P100: TRISBATCH@ameren | Q100: V_TRIS_BATCH | R100: $$TRIS_BATCHDIR\BuildDB2LoadFiles\BuildVsalarystep\BuildVsalarystep.exe | S100: gx,mx | V100: 0 | Z100: 1 | AA100: TRIS | AB100: F | AC100: 3 | AD100: DLTRISTeam@ameren.com | AE100: TRIS_RH_sunday_130_BuildPayrollFiles_vSAL_STEP_TBL_TR FAILED | AH100: >>$$TRIS_BATCHDIR\Logs\%AUTO_JOB_NAME%_stdout.txt | AI100: >>$$TRIS_BATCHDIR\Logs\%AUTO_JOB_NAME%_stderr.txt
...

Sheet Job Schedule
A1: Please see the bottom Notes for more info on highlighted jobs.
A2: Job Name | B2: Box | C2: Step | D2: Days | E2: Time
A3: TRIS_RH_ARCOS_Daily_Box | D3: su,mo,tu,we,th,fr,sa | E3: 0.5
A4: TRIS_RH_ARCOS_Overtime_Daily | B4: TRIS_RH_ARCOS_Daily_Box | C4: 1
A5: TRIS_RH_ARCOS_HR_Daily | B5: TRIS_RH_ARCOS_Daily_Box | C5: 2 | D5: s(TRIS_RH_ARCOS_Overtime_Daily)
A6: TRIS_RH_ARCOS_Sched_Daily | B6: TRIS_RH_ARCOS_Daily_Box | C6: 3 | D6: s(TRIS_RH_ARCOS_HR_Daily)
A7: TRIS_RH_ARCOS_SFTP_Daily | B7: TRIS_RH_ARCOS_Daily_Box | C7: 4 | D7: s(TRIS_RH_ARCOS_Sched_Daily)
A8: TRIS_RH_ARCOS_Delete_files | B8: TRIS_RH_ARCOS_Daily_Box | C8: 5 | D8: s(TRIS_RH_ARCOS_SFTP_Daily)
A9: TRIS_RH_ARCOS_Weekly_Box | D9: we | E9: 0.25
A10: TRIS_RH_ARCOS_Overtime_Weekly | B10: TRIS_RH_ARCOS_Weekly_Box | C10: 1
A11: TRIS_RH_ARCOS_Yearly_Box | D11: AM_1st_WED_JAN | E11: 0.27083333
A12: TRIS_RH_ARCOS_Overtime_Yearly | B12: TRIS_RH_ARCOS_Yearly_Box | C12: 1
A14: TRIS_RH_Contract_Final | D14: On demand
A15: TRIS_RH_Contract_Final_010_BuildPayrollFiles_vJOB_TR | B15: TRIS_RH_Contract_Final | C15: 1
A16: TRIS_RH_Contract_Final_020_BuildPayrollFiles_vDEPT_TBL_TR | B16: TRIS_RH_Contract_Final | C16: 2 | D16: s(TRIS_RH_Contract_Final_010_BuildPayrollFiles_vJOB_TR)
A17: TRIS_RH_Contract_Final_030_BuildPayrollFiles_vJOBCODE_TR | B17: TRIS_RH_Contract_Final | C17: 3 | D17: s(TRIS_RH_Contract_Final_020_BuildPayrollFiles_vDEPT_TBL_TR)
A18: TRIS_RH_Contract_Final_040_BuildPayrollFiles_vSAL_STEP_TR | B18: TRIS_RH_Contract_Final | C18: 4 | D18: S(TRIS_RH_Contract_Final_030_BuildPayrollFiles_vJOBCODE_TR )
A19: TRIS_RH_Contract_Final_050_BuildPayrollFiles_FTP_vJOB_TR | B19: TRIS_RH_Contract_Final | C19: 5 | D19: S(TRIS_RH_Contract_Final_040_BuildPayrollFiles_vSAL_STEP_TR)
A20: TRIS_RH_Contract_Final_060_BuildPayrollFiles_FTP_vDEPT_TR | B20: TRIS_RH_Contract_Final | C20: 6 | D20: S(TRIS_RH_Contract_Final_050_BuildPayrollFiles_FTP_vJOB_TR)
A21: TRIS_RH_Contract_Final_070_BuildPayrollFiles_FTP_vJOBCODE | B21: TRIS_RH_Contract_Final | C21: 7 | D21: S(TRIS_RH_Contract_Final_060_BuildPayrollFiles_FTP_vDEPT_TR)
A22: TRIS_RH_Contract_Final_080_BuildPayrollFiles_FTP_vSAL | B22: TRIS_RH_Contract_Final | C22: 8 | D22: S(TRIS_RH_Contract_Final_050_BuildPayrollFiles_FTP_vJOB_TR)
A23: TRIS_RH_Contract_Final_200_MF_AR13895 | B23: TRIS_RH_Contract_Final | C23: 9 | D23: S(TRIS_RH_Contract_Final_080_BuildPayrollFiles_FTP_Vsal)
A24: TRIS_RH_Contract_Final_300_Build_HR_History_View | B24: TRIS_RH_Contract_Final | C24: 10 | D24: s(TRIS_RH_Contract_Final_200_MF_AR13895)
A25: TRIS_RH_Contract_Final_410_MF_TR33200 | B25: TRIS_RH_Contract_Final | C25: 11 | D25: s(TRIS_RH_Contract_Final_300_Build_HR_History_View)
A26: TRIS_RH_Contract_Final_420_MF_AR13687 | B26: TRIS_RH_Contract_Final | C26: 12a | D26: s(TRIS_RH_Contract_Final_410_MF_TR33200)
A27: TRIS_RH_Contract_Final_530_Send_Copy_PayrollFile | B27: TRIS_RH_Contract_Final | C27: 13a | D27: s(TRIS_RH_Contract_Final_420_MF_AR13687)
A28: TRIS_RH_Contract_Final_540_Send_Move_PayrollFile | B28: TRIS_RH_Contract_Final | C28: 14a | D28: s(TRIS_RH_Contract_Final_530_Send_Copy_PayrollFile)
A29: TRIS_RH_Contract_Final_550_Send_ToPayroll | B29: TRIS_RH_Contract_Final | C29: 15a | D29: s(TRIS_RH_Contract_Final_540_Send_Move_PayrollFile)
A30: TRIS_RH_Contract_Final_600_MF_TR33206 | B30: TRIS_RH_Contract_Final | C30: 12b | D30: s(TRIS_RH_Contract_Final_410_MF_TR33200)
A32: TRIS_RH_Contract_Preliminary_OnRequest_MF_TR33103N | D32: Failure of mainframe job
A34: TRIS_RH_dailyBox
A35: TRIS_RH_daily_010_BuildCommon_Department | B35: TRIS_RH_dailyBox | C35: 1 | D35: mo,tu,we,th,fr,sa | E35: 0.041666667
A36: TRIS_RH_daily_020_BuildCommon_Employee | B36: TRIS_RH_dailyBox | C36: 2 | D36: s(TRIS_RH_daily_010_BuildCommon_Department)
A37: TRIS_RH_daily_030_BuildCommon_FTP_Department | B37: TRIS_RH_dailyBox | C37: 3 | D37: s(TRIS_RH_daily_020_BuildCommon_Employee
A38: TRIS_RH_daily_040_BuildCommon_FTP_Employee | B38: TRIS_RH_dailyBox | C38: 4 | D38: s(TRIS_RH_daily_030_BuildCommon_FTP_Department
A39: TRIS_RH_daily_050_BuildCommon_FTP_THRDBEmployee | B39: TRIS_RH_dailyBox | C39: 5 | D39: s(TRIS_RH_daily_040_BuildCommon_FTP_Employee
A40: TRIS_RH_daily_070_BuildCommon_Associations | B40: TRIS_RH_dailyBox | C40: 6 | D40: s(TRIS_RH_daily_050_BuildCommon_FTP_THRDBEmployee
A41: TRIS_RH_daily_080_BuildCommon_FTP_Associations | B41: TRIS_RH_dailyBox | C41: 7 | D41: s(TRIS_RH_daily_070_BuildCommon_Associations
A42: TRIS_RH_daily_100_BuildPayrollFiles_vJOB_TR | B42: TRIS_RH_dailyBox | C42: 8 | D42: s(TRIS_RH_daily_080_BuildCommon_FTP_Associations
A43: TRIS_RH_daily_110_BuildPayrollFiles_vDEPT_TBL_TR | B43: TRIS_RH_dailyBox | C43: 9 | D43: s(TRIS_RH_daily_100_BuildPayrollFiles_vJOB_TR
A44: TRIS_RH_daily_120_BuildPayrollFiles_vJOBCODE_TBL_TR | B44: TRIS_RH_dailyBox | C44: 10 | D44: s(TRIS_RH_daily_110_BuildPayrollFiles_vDEPT_TBL_TR
A45: TRIS_RH_daily_130_BuildPayrollFiles_vSAL_STEP_TBL_TR | B45: TRIS_RH_dailyBox | C45: 11 | D45: s(TRIS_RH_daily_120_BuildPayrollFiles_vJOBCODE_TBL_TR
A46: TRIS_RH_daily_140_BuildPayrollFiles_FTP_vJOB_TR | B46: TRIS_RH_dailyBox | C46: 12 | D46: s(TRIS_RH_daily_130_BuildPayrollFiles_vSAL_STEP_TBL_TR
A47: TRIS_RH_daily_150_BuildPayrollFiles_FTP_vDEPT_TBL_TR | B47: TRIS_RH_dailyBox | C47: 13 | D47: s(TRIS_RH_daily_140_BuildPayrollFiles_FTP_vJOB_TR
... A64: TRIS_RH_daily_700_MF_TR33101N | B64: TRIS_RH_dailyBox | C64: 31 | D64: s(TRIS_RH_daily_450_MF_TR33115)
A66: TRIS_RH_daily_600_MF_TR33103N | D66: s(TRIS_RH_daily_700_MF_TR33101N,03.00)
A67: TRIS_RH_daily_800_TRISBIExtract | D67: s(TRIS_RH_daily_450_MF_TR33115,03.00)
A68: TRIS_RH_daily_810_IMREmail | D68: s(TRIS_RH_daily_800_TRISBIExtract,01.00)
A70: TRIS_RH_Daily_everyday_0005_DelayedOTBanks_MF_TR33108 | D70: su,mo,tu,we,th,fr,sa | E70: 0.0034722222
A71: TRIS_RH_Daily_everyday_1900_DepartmentMaintenance | D71: su,mo,tu,we,th,fr,sa | E71: 0.79166667
A72: TRIS_RH_Daily_everyday_1900_workday_FMLA_Interface | D72: su,mo,tu,we,th,fr,sa | E72: 0.98958333
A73: TRIS_RH_Contract_Preliminary_OnRequest_MF_TR33103N | D73: On demand
A75: TRIS_RH_Executive_Final
A76: TRIS_RH_Executive_Final_010_BuildPayrollFiles_vJOB_TR | B76: TRIS_RH_Executive_Final | C76: 1 | D76: On demand
A77: TRIS_RH_Executive_Final_020_BuildPayrollFiles_vDEPT_TBL_TR | B77: TRIS_RH_Executive_Final | C77: 2 | D77: s(TRIS_RH_Executive_Final_010_BuildPayrollFiles_vJOB_TR)
A78: TRIS_RH_Executive_Final_030_BuildPayrollFiles_vJOBCODE_TR | B78: TRIS_RH_Executive_Final | C78: 3 | D78: s(TRIS_RH_Executive_Final_020_BuildPayrollFiles_vDEPT_TBL_TR)
A79: TRIS_RH_Executive_Final_040_BuildPayrollFiles_vSAL_STEP_TR | B79: TRIS_RH_Executive_Final | C79: 4 | D79: s(TRIS_RH_Executive_Final_030_BuildPayrollFiles_vJOBCODE_TR )
A80: TRIS_RH_Executive_Final_050_BuildPayrollFiles_FTP_vJOB_TR | B80: TRIS_RH_Executive_Final | C80: 5 | D80: s(TRIS_RH_Executive_Final_040_BuildPayrollFiles_vSAL_STEP_TR)
A81: TRIS_RH_Executive_Final_060_BuildPayrollFiles_FTP_vDEPT_TR | B81: TRIS_RH_Executive_Final | C81: 6 | D81: s(TRIS_RH_Executive_Final_050_BuildPayrollFiles_FTP_vJOB_TR)
A82: TRIS_RH_Executive_Final_070_BuildPayrollFiles_FTP_vJOBCODE | B82: TRIS_RH_Executive_Final | C82: 7 | D82: s(TRIS_RH_Executive_Final_060_BuildPayrollFiles_FTP_vDEPT_TR)
A83: TRIS_RH_Executive_Final_080_BuildPayrollFiles_FTP_vSAL | B83: TRIS_RH_Executive_Final | C83: 8 | D83: s(TRIS_RH_Executive_Final_070_BuildPayrollFiles_FTP_vJOBCODE)
A84: TRIS_RH_Executive_Final_200_MF_AR13895 | B84: TRIS_RH_Executive_Final | C84: 9 | D84: s(TRIS_RH_Executive_Final_080_BuildPayrollFiles_FTP_vSAL)
A85: TRIS_RH_Executive_Final_300_Build_HR_History_View | B85: TRIS_RH_Executive_Final | C85: 10 | D85: s(TRIS_RH_Executive_Final_200_MF_AR13895)
A86: TRIS_RH_Executive_Final_310_COPtoUOP | B86: TRIS_RH_Executive_Final | C86: 11 | D86: s(TRIS_RH_Executive_Final_300_Build_HR_History_View)
A87: TRIS_RH_Executive_Final_410_MF_TR33201 | B87: TRIS_RH_Executive_Final | C87: 12 | D87: s(TRIS_RH_Executive_Final_310_COPtoUOP)
... A91: TRIS_RH_Executive_Final_550_Send_ToPayroll | B91: TRIS_RH_Executive_Final | C91: 16 | D91: s(TRIS_RH_Executive_Final_540_Send_Move_PayrollFile)
A93: TRIS_RH_Executive_Preliminary_OnRequest_MF_TR33112 | B93: TRIS_RH_Executive_Final | D93: On Demand
A95: RRIS_RH_OnRequest_HRinterface_MF_TR33102 | D95: On Demand
A97: TRIS_RH_monthly_000_PDCLOSEBox | D97: AM_1stWkDyNoHol | E97: 0.16666667
A98: TRIS_RH_monthly_010_FixedAccountingAllocationsInterface | B98: TRIS_RH_monthly_000_PDCLOSEBox | C98: 1
A99: TRIS_RH_monthly_020_PayrollAccruals | B99: TRIS_RH_monthly_000_PDCLOSEBox | C99: 2 | D99: s(TRIS_RH_monthly_010_FixedAccountingAllocationsInterface)
A100: TRIS_RH_monthly_030_PayrollDistributionInterface | B100: TRIS_RH_monthly_000_PDCLOSEBox | C100: 3 | D100: s(TRIS_RH_monthly_020_PayrollAccruals)
A101: TRIS_RH_monthly_150_LaborHours_Interface | B101: TRIS_RH_monthly_000_PDCLOSEBox | C101: 4 | D101: s(TRIS_RH_monthly_030_PayrollDistributionInterface)
A103: TRIS_RH_monthly_100_MaximoAccountingInterface | D103: AM_1stWkDyNoHol | E103: 0.00069444444
A105: TRIS_RH_sundayBox | D105: su | E105: 0.375
A106: TRIS_RH_sunday_010_BuildCommon_Department | B106: TRIS_RH_sundayBox | C106: 1
A107: TRIS_RH_sunday_020_BuildCommon_Employee | B107: TRIS_RH_sundayBox | C107: 2 | D107: s(TRIS_RH_sunday_010_BuildCommon_Department )
A108: TRIS_RH_sunday_030_BuildCommon_FTP_Department | B108: TRIS_RH_sundayBox | C108: 3 | D108: s(TRIS_RH_sunday_020_BuildCommon_Employee)
A109: TRIS_RH_sunday_040_BuildCommon_FTP_Employee | B109: TRIS_RH_sundayBox | C109: 4 | D109: s(TRIS_RH_sunday_030_BuildCommon_FTP_Department)
A110: TRIS_RH_sunday_050_BuildCommon_FTP_THRDBEmployee | B110: TRIS_RH_sundayBox | C110: 5 | D110: s(TRIS_RH_sunday_040_BuildCommon_FTP_Employee)
A111: TRIS_RH_sunday_070_BuildCommon_Associations | B111: TRIS_RH_sundayBox | C111: 6 | D111: s(TRIS_RH_sunday_050_BuildCommon_FTP_THRDBEmployee)
A112: TRIS_RH_sunday_080_BuildCommon_FTP_Associations | B112: TRIS_RH_sundayBox | C112: 7 | D112: s(TRIS_RH_sunday_070_BuildCommon_Associations)
A113: TRIS_RH_sunday_100_BuildPayrollFiles_vJOB_TR | B113: TRIS_RH_sundayBox | C113: 8 | D113: s(TRIS_RH_sunday_080_BuildCommon_FTP_Associations)
A114: TRIS_RH_sunday_110_BuildPayrollFiles_vDEPT_TBL_TR | B114: TRIS_RH_sundayBox | C114: 9 | D114: s(TRIS_RH_sunday_100_BuildPayrollFiles_vJOB_TR)
A115: TRIS_RH_sunday_120_BuildPayrollFiles_vJOBCODE_TBL_TR | B115: TRIS_RH_sundayBox | C115: 10 | D115: s(TRIS_RH_sunday_110_BuildPayrollFiles_vDEPT_TBL_TR)
A116: TRIS_RH_sunday_130_BuildPayrollFiles_vSAL_STEP_TBL_TR | B116: TRIS_RH_sundayBox | C116: 11 | D116: s(TRIS_RH_sunday_120_BuildPayrollFiles_vJOBCODE_TBL_TR)
A117: TRIS_RH_sunday_140_BuildPayrollFiles_FTP_vJOB_TR | B117: TRIS_RH_sundayBox | C117: 12 | D117: s(TRIS_RH_sunday_130_BuildPayrollFiles_vSAL_STEP_TBL_TR)
A118: TRIS_RH_sunday_150_BuildPayrollFiles_FTP_vDEPT_TBL_TR | B118: TRIS_RH_sundayBox | C118: 13 | D118: s(TRIS_RH_sunday_140_BuildPayrollFiles_FTP_vJOB_TR)
... A133: TRIS_RH_sunday_450_MF_TR33115 | B133: TRIS_RH_sundayBox | C133: 28 | D133: s(TRIS_RH_sunday_440_MF_TR33136)
A135: TRIS_RH_yearly_Jan20_1730_MF_TR33445 | D135: AM_20DOMJan | E135: 0.72916667
A136: TRIS_RH_yearly_Jan20_1800_MF_TR33446 | D136: AM_20DOMJan s(TRIS_RH_yearly_Jan20_1730_MF_TR33445) | E136: 0.75
A137: TRIS_RH_yearly_Jan20_1830_VacationAccrualReport | D137: AM_20DOMJan s(TRIS_RH_yearly_Jan20_1730_MF_TR33445) | E137: 0.77083333
A138: TRIS_RH_yearly_Jan20_2000_MF_TR33406 | D138: AM_20DOMJan s(TRIS_RH_yearly_Jan20_1800_MF_TR33446) | E138: 0.83333333
A140: TRIS_RN_BatchVerifyEnvVars | D140: On Demand
A142: TRIS_RN_FTPVerifyEnvVars | D142: On Demand
A143: TRIS_RN_Contract_Final_080_BuildPayrollFiles_FTP_vSAL | D143: On Demand
A144: TRIS_RN_Contract_final_200_MF_AR13895 | D144: On Demand
A146: TRIS_RN_monthly_day_01_MF_TR33311 | D146: AM_FOM | E146: 0.70833333
A147: TRIS_RN_monthly_day_02_MF_TR33312 | D147: AM_2DOMFebMarMayJunAugSepNovDec | E147: 0.70833333
A148: TRIS_RN_monthly_day_02_MF_TR33402 | D148: AM_2DOM | E148: 0.70833333
...

Sheet Job to Program Mapping 
B1: Process Name | C1: Job Name | D1: Description | E1: Program
B2: Reconciliation | C2: AR13999 | D2: Copy Job | E2: NA
C3: DB12287N | D3: Load DB2 | E3: NA
C4: DB12005N | D4: Load DB2 | E4: NA | H4: This sheet contains the Mapping of COBOL Programs (Main Programs) Being invoked from the JOB. Typically a Mainframe JOB contains steps, that execute in a sequential order and each step of the JOB executes an Application Programs or Utility Program (Load, Unload, Sort)
C5: AR13895 | D5: Load DB2 | E5: NA
C6: AR13872 | D6: Copy Job | E6: NA
C7: AR13687 | D7: FTP Contract Payroll Files | E7: NA
C8: AR13587 | D8: FTP Executive Payroll Files | E8: NA
B9: Maintain | C9: TR33106N | D9: Maintains table TTR_JOBS | E9: TR014
C10: TR33107 | D10: Maintains table TTR_ASSOCIATIONS | E10: TR015 TR085
C11: TR33102 | D11: HR interface via Common Employee | E11: TR009 TR129
B12: Seniority | C12: TR33136N | D12: Seniority Accrual | E12: TI0510 TR127
B13: TRBE | C13: TR33115N | D13: TRBE Process | E13: TI0504 TI0503 TI0538 TI1003 TI0508
B14: Contract Payroll | C14: TR33103N | D14: Contract Pre Payroll | E14: TR033 TR001 TR039 TR051 TR052 TR003 TR050 TR021 TR117 TR003C TR050C TR021C TR104 TR115 TR105 TR106 TR108 TR004 TR005 TR077 TR029
C15: TR33101N | D15: Contract Daily Payroll | E15: TR001 TR051 TR052 TR003 TR050 TR021 TR003C TR050C TR021C TR105 TR106 TR108 TR004 TR005 TR077 TR029
C16: TR33200 | D16: Contract Final Payroll | E16: TR001 TR039 TR051 TR052 TR003 TR050 TR021 TR003C TR050C TR021C TR105 TR106 TR131 TR108 TR004 TR005 TR060 TR033 TR037
C17: TR33206 | D17: Contract Final (Update sick leave banks/generate reports) | E17: TR109 TR107 TR077 TR042 TR029 TR026 TR135 TR136 TR137 TR111 TR134
B18: Executive Payroll | C18: TR33201 | D18: Executive Final Payroll | E18: TR001 TR033 TR039 TR051 TR052 TR003 TR050 TR021 TR103 TR004 TR005 TR044 TR060 TR077 TR029 TR026 TR135 TR128 TR037
B19: Overtime | C19: TR33108 | D19: Delayed Overtime Bank Charges | E19: TR008
C20: TR33211 | D20: Weekly Overtime Report (Missouri) | E20: TR053
B21: Monthly | C21: TR33311 | D21: Seniority List Local | E21: TR090 TR091 TR092 TR093 TR094 TR083
C22: TR33137 | D22: Absence Exception Report | E22: TI0545 TR078 (A,B,C,D,E) TR086
C23: TR33408 | D23: Sick Leave Summary Report | E23: TI0544 TR058
B24: Quaterly | C24: TR33400 | D24: E&C Report (Project / Non-Project) | E24: TR121 TR122
C25: TR33402 | D25: Seniority List Union Local | E25: TR095 TR096 TR097
C26: TR33407 | D26: Overtime Report | E26: TR087
C27: TR33401 | D27: Sick Leave Reports | E27: TR130 TI0544 TR041 TR099 TR049
B28: Yearly | C28: TR33445 | D28: Vacation Carry Over and update report | E28: TR114
C29: TR33446 | D29: Annual Sick Leave and Vacation Summary | E29: TR110 TR139 TR140 TR098 TI0543 TR070 TR071 TR072 TR074 TR132
C30: TR33406 | D30: CIPS Local 702 Sick Leave Report | E30: TR043
B31: On Request | C31: TR33442 | D31: Build Holidays (Runs October) | E31: TI0505 TI1004
C32: TR33451 | D32: Vacation Allotment Management Employee Report (Runs October) | E32: TR113
C33: TR33440 | D33: Vacation Allotment Contract Employee Report (Runs October) | E33: TR113
C34: TR33000 | D34: RECALCULATE SICK LEAVE BALANCE | E34: TR426
C35: TR33112 | D35: Executive Preliminary Payroll | E35: TR033 TR001 TR039 TR051 TR052 TR003 TR050 TR021 TR103 TR004 TR005 TR029 TR048 TR128
B36: Stored PROCs | C36: TR33122 | D36: OVERTIME EQUALIZATION REPORT | E36: TR126 (2)
C37: TR33142 | D37: Seniority | E37: TR081 (4)
C38: TR33145 | D38: Vacation Summary | E38: TR133 (3)
C39: TR33128 | D39: Overtime Adjustment Report | E39: TR125 (1)
C40: TR33120 | D40: Overtime Canvass (TTR_JCL -- INSERTS GOOD) | E40: TR027

Sheet Program Mapping
B1: Job | C1: Program | D1: Legacy Autosys Job
A2: Maintain | B2: TR33106N | D2: TRIS_RH_daily_410_MF_TR33106
B3: TR33107 | C3: TR015 TR085 | D3: TRIS_RH_daily_420_MF_TR33107
B4: TR33102 | C4: TR009 TR129 | D4: TRIS_RH_daily_430_MF_TR33102
A5: Seniority | B5: TR33136N | C5: TI0510 TR127 | D5: TRIS_RH_daily_440_MF_TR33136
A6: TRBE | B6: TR33115N | C6: TI0504 TI0503 TI0538 TI1003 TI0508 | D6: TRIS_RH_daily_450_MF_TR33115
A7: Contract Payroll | B7: TR33101N | C7: TR001 TR051 TR052 TR003 TR050 TR021 TR003C TR050C TR021C TR105 TR106 TR108 TR004 TR005 TR077 TR029 | D7: TRIS_RH_daily_700_MF_TR33101N
B8: TR33103N | C8: TR033 TR001 TR039 TR051 TR052 TR003 TR050 TR021 TR117 TR003C TR050C TR021C TR104 TR115 TR105 TR106 TR108 TR004 TR005 TR077 TR029 | D8: TRIS_RH_Contract_Preliminary_OnRequest_MF_TR33103N
B9: TR33200 | C9: TR001 TR039 TR051 TR052 TR003 TR050 TR021 TR003C TR050C TR021C TR105 TR106 TR131 TR108 TR004 TR005 TR060 TR033 TR037 | D9: TRIS_RH_Contract_Final_410_MF_TR33200
B10: TR33206 | C10: TR109 TR107 TR077 TR042 TR029 TR026 TR135 TR136 TR137 TR111 TR134 | D10: TRIS_RH_Contract_Final_600_MF_TR33206
A11: Executive Payroll | B11: TR33201 | C11: TR001 TR033 TR039 TR051 TR052 TR003 TR050 TR021 TR103 TR004 TR005 TR044 TR060 TR077 TR029 TR026 TR135 TR128 TR037 | D11: TRIS_RH_Executive_Final_410_MF_TR33201
A12: Overtime | B12: TR33108 | C12: TR008 | D12: TRIS_RH_Daily_everyday_0005_DelayedOTBanks_MF_TR33108
B13: TR33211 | C13: TR053
A14: Monthly | B14: TR33311 | C14: TR090 TR091 TR092 TR093 TR094 TR083
B15: TR33137 | C15: TI0545 TR078 (A,B,C,D,E) TR086
B16: TR33408 | C16: TI0544 TR058
A17: Quaterly | B17: TR33400 | C17: TR121 TR122
B18: TR33402 | C18: TR095 TR096 TR097
B19: TR33407 | C19: TR087
B20: TR33401 | C20: TR130 TI0544 TR041 TR099 TR049
A21: Yearly | B21: TR33445 | C21: TR114 | D21: TRIS_RH_yearly_Jan25_1730_MF_TR33445
B22: TR33446 | C22: TR110 TR139 TR140 TR098 TI0543 TR070 TR071 TR072 TR074 TR132 | D22: TRIS_RH_yearly_Jan25_1800_MF_TR33446
B23: TR33406 | C23: TR043 | D23: TRIS_RH_yearly_Jan25_2000_MF_TR33406
A24: On Request | B24: TR33442 | C24: TI0505 TI1004
B25: TR33451 | C25: TR113
B26: TR33440 | C26: TR113
B27: TR33000 | C27: TR426 | D27: TRIS_RN_Sick_Leave_Recalculate_Bank_Balances_MF_TR33000
B28: TR33112 | C28: TR033 TR001 TR039 TR051 TR052 TR003 TR050 TR021 TR103 TR004 TR005 TR029 TR048 TR128 | D28: TRIS_RH_Executive_Preliminary_OnRequest_MF_TR33112
A29: MuleSoft Integration | D29: TRIS_RH_monthly_020_PayrollAccruals
D30: TRIS_RH_monthly_030_PayrollDistributionInterface
A34: ARCO Integration | D34: TRIS_RH_ARCOS_HR_Daily
D35: TRIS_RH_ARCOS_Overtime_Daily
D36: TRIS_RH_ARCOS_Overtime_Weekly
D37: TRIS_RH_ARCOS_Overtime_Yearly
D38: TRIS_RH_ARCOS_Sched_Daily
A44: Workday Integration | D44: TRIS_RH_Contract_Final_550_Send_ToPayroll
D45: TRIS_RH_daily_445_workday_Seniority_Interface
D46: TRIS_RH_Daily_everyday_1900_workday_FMLA_Interface
D47: TRIS_RH_Executive_Final_550_Send_ToPayroll
A51: Maximo Integration | D51: TRIS_RH_monthly_100_MaximoAccountingInterface

Sheet TRIS Autosys Jobs
A1: Please see the bottom Notes for more info on highlighted jobs.
A2: Job Name | B2: New TRIS & C# | C2: Description | D2: SME -- Comments | E2: Condition | F2: Job Type | G2: Box Name | H2: Owner | I2: Machine | J2: Command | K2: Permissions | L2: JCL library | M2: JCL member | N2: Has Date Condition | O2: Days of Week | P2: Start Time | Q2: Run Calendar | R2: Exclude Calendar | S2: Alarm | T2: Profile | U2: Send Notification | V2: Schedule Priority | W2: Email Notified | X2: Email Message | Y2: Mainframe Condtion Code | Z2: Start Mins | AA2: std out file | AB2: std err file | AC2: FTP transfer type | AD2: FTP transfer direction | AE2: FTP local name | AF2: FTP remote name | AG2: FTP server name | AH2: FTP use ssl | AI2: FTP local user | AJ2: FTP user type | AK2: max run alarm | AL2: box terminator | AM2: term run time | AN2: Status
A3: TRIS_RH_ARCOS_Daily_Box | C3: TRIS ARCOS Daily Interface Files CHG0000000xxxxx | F3: BOX | H3: TRISBATCH@ameren | K3: gx,mx | N3: 1 | O3: su,mo,tu,we,th,fr,sa | P3: 0.54166667 | S3: 1 | V3: 3
A4: TRIS_RH_ARCOS_HR_Daily | B4: /api/core/payroll/v1/ARCOSHRInterface/strike/process | C4: TRIS daily ARCOS HR interface #RH#DV-HR-TR# CHG CHG0000000xxxxx | E4: s(TRIS_RH_ARCOS_Overtime_Daily) | F4: CMD | G4: TRIS_RH_ARCOS_Daily_Box | H4: TRISBATCH@ameren | I4: V_TRIS_BATCH | J4: $$TRIS_BATCHDIR\ARCOSHRInterface\ARCOSHRInterface.exe | K4: gx,mx | N4: 0 | S4: 1 | T4: TRIS | U4: F | V4: 3 | W4: DLTRISTeam@ameren.com | X4: TRIS_RH_ARCOS_HR_Daily FAILED. | AA4: >>$$TRIS_BATCHDIR\Logs\%AUTO_JOB_NAME%_stdout.txt | AB4: >>$$TRIS_BATCHDIR\Logs\%AUTO_JOB_NAME%_stderr.txt
A5: TRIS_RH_ARCOS_Overtime_Daily | B5: /api/core/payroll/v1/ArcosOvertimeInterface/interface | C5: TRIS daily ARCOS Overtime interface #RH#DV-HR-TR# CHG0000000xxxxx | F5: CMD | G5: TRIS_RH_ARCOS_Daily_Box | H5: TRISBATCH@ameren | I5: V_TRIS_BATCH | J5: $$TRIS_BATCHDIR\ARCOSOvertimeInterface\ARCOSOvertimeInterface.exe | K5: gx,mx | N5: 0 | S5: 1 | T5: TRIS | U5: F | V5: 3 | W5: DLTRISTeam@ameren.com | X5: TRIS_RH_ARCOS_Overtime_Daily FAILED. | AA5: >>$$TRIS_BATCHDIR\Logs\%AUTO_JOB_NAME%_stdout.txt | AB5: >>$$TRIS_BATCHDIR\Logs\%AUTO_JOB_NAME%_stderr.txt
A6: TRIS_RH_ARCOS_Overtime_Weekly | B6: /api/core/payroll/v1/ARCOSOvertimeWeekly/build-all-standings | C6: TRIS weekly ARCOS Build Next Standing #RN#DV-HR-TR# CHG0000000xxxxx | F6: CMD | G6: TRIS_RH_ARCOS_Weekly_Box | H6: TRISBATCH@ameren | I6: V_TRIS_BATCH | J6: $$TRIS_BATCHDIR\ARCOSOvertimeWeeklyProcess\ARCOSOvertimeWeeklyProcess.exe | K6: gx,mx | N6: 0 | S6: 1 | T6: TRIS | U6: F | V6: 3 | W6: DLTRISTeam@ameren.com | X6: TRIS_RH_ARCOS_Overtime_Weekly FAILED. | AA6: >>$$TRIS_BATCHDIR\Logs\%AUTO_JOB_NAME%_stdout.txt | AB6: >>$$TRIS_BATCHDIR\Logs\%AUTO_JOB_NAME%_stderr.txt
A7: TRIS_RH_ARCOS_Overtime_Yearly | B7: /api/core/payroll/v1/ARCOSOvertimeYearly/rezero-standings | C7: TRIS ARCOS Yearly -- Re-Zero Standings -- Jim Barnett 314-630-7969 #RN#DV-HR-TR# CHG0000000xxxxx | F7: CMD | G7: TRIS_RH_ARCOS_Yearly_Box | H7: TRISBATCH@ameren | I7: V_TRIS_BATCH | J7: $$TRIS_BATCHDIR\ARCOSOvertimeYearlyProcess\ARCOSOvertimeYearlyProcess.exe | K7: gx,mx | N7: 0 | S7: 1 | T7: TRIS | U7: F | V7: 3 | W7: DLTRISTeam@ameren.com | X7: TRIS_RH_ARCOS_Overtime_Yearly FAILED. | AA7: >>$$TRIS_BATCHDIR\Logs\%AUTO_JOB_NAME%_stdout.txt | AB7: >>$$TRIS_BATCHDIR\Logs\%AUTO_JOB_NAME%_stderr.txt
A8: TRIS_RH_ARCOS_Sched_Daily | B8: /api/core/payroll/v1/ARCOSSchedulingInterface/build-schedule-file | C8: TRIS daily ARCOS Schedule interface #RH#DV-HR-TR# CHG CHG0000000xxxxx | E8: s(TRIS_RH_ARCOS_HR_Daily) | F8: CMD | G8: TRIS_RH_ARCOS_Daily_Box | H8: TRISBATCH@ameren | I8: V_TRIS_BATCH | J8: $$TRIS_BATCHDIR\ARCOSScheduleInterface\ARCOSSchedulingInterface.exe | K8: gx,mx | N8: 0 | S8: 1 | T8: TRIS | U8: F | V8: 3 | W8: DLTRISTeam@ameren.com | X8: TRIS_RH_ARCOS_Sched_Daily FAILED. | AA8: >>$$TRIS_BATCHDIR\Logs\%AUTO_JOB_NAME%_stdout.txt | AB8: >>$$TRIS_BATCHDIR\Logs\%AUTO_JOB_NAME%_stderr.txt
A9: TRIS_RH_ARCOS_Weekly_Box | B9: /api/core/payroll/v1/ARCOSOvertimeWeekly/build-all-standings | C9: TRIS ARCOS Weekly Create next Standing CHG0000000xxxxx | F9: BOX | H9: TRISBATCH@ameren | K9: gx,mx | N9: 1 | O9: we | P9: 0.25 | S9: 1 | V9: 3
A10: TRIS_RH_ARCOS_Yearly_Box | B10: /api/core/payroll/v1/ARCOSOvertimeYearly/rezero-standings | C10: TRIS ARCOS Yearly -- Re-Zero Standings -- Jim Barnett 314-630-7969 CHG0000000xxxxx | F10: BOX | H10: TRISBATCH@ameren | K10: gx,mx | N10: 1 | O10: we | P10: 0.27083333 | S10: 1 | V10: 3
A11: TRIS_RH_Contract_Final | C11: This runs the TRIS portion of the contract payroll | F11: BOX | H11: TRISBATCH@ameren | K11: gx,mx | N11: 0 | S11: 1 | V11: 3
A12: TRIS_RH_Contract_Final_010_BuildPayrollFiles_vJOB_TR | B12: /api/core/notification/v1/jobs/buildFile | C12: Build File for DB2 Load of VJOB_TR #RH#DV-HR-TR# CHG0000000xxxxx | F12: CMD | G12: TRIS_RH_Contract_Final | H12: TRISBATCH@ameren | I12: V_TRIS_BATCH | J12: $$TRIS_BATCHDIR\BuildDB2LoadFiles\BuildVjob\BuildVjob.exe | K12: gx,mx | N12: 0 | S12: 1 | T12: TRIS | U12: F | V12: 3 | W12: DLTRISTeam@ameren.com | X12: TRIS_RH_Contract_Final_010_BuildPayrollFiles_vJOB_TR FAILED | AA12: >>$$TRIS_BATCHDIR\Logs\%AUTO_JOB_NAME%_stdout.txt | AB12: >>$$TRIS_BATCHDIR\Logs\%AUTO_JOB_NAME%_stderr.txt
A13: TRIS_RH_Contract_Final_020_BuildPayrollFiles_vDEPT_TBL_TR | B13: /api/core/notification/v1/departments/buildFile | C13: Build File for DB2 Load of VDEPT_TBL_TR #RH#DV-HR-TR# CHG0000000xxxxx | E13: s(TRIS_RH_Contract_Final_010_BuildPayrollFiles_vJOB_TR) | F13: CMD | G13: TRIS_RH_Contract_Final | H13: TRISBATCH@ameren | I13: V_TRIS_BATCH | J13: $$TRIS_BATCHDIR\BuildDB2LoadFiles\BuildVdept\BuildVdept.exe | K13: gx,mx | N13: 0 | S13: 1 | T13: TRIS | U13: F | V13: 3 | W13: DLTRISTeam@ameren.com | X13: TRIS_RH_Contract_Final_020_BuildPayrollFiles_vDEPT_TBL_TR FAILED | AA13: >>$$TRIS_BATCHDIR\Logs\%AUTO_JOB_NAME%_stdout.txt | AB13: >>$$TRIS_BATCHDIR\Logs\%AUTO_JOB_NAME%_stderr.txt
A14: TRIS_RH_Contract_Final_030_BuildPayrollFiles_vJOBCODE_TR | B14: /api/core/notification/v1/jobcodes/buildFile | C14: Build File for DB2 Load of VJOBCODE_TBL_TR #RH#DV-HR-TR# CHG0000000xxxxx | E14: s(TRIS_RH_Contract_Final_020_BuildPayrollFiles_vDEPT_TBL_TR) | F14: CMD | G14: TRIS_RH_Contract_Final | H14: TRISBATCH@ameren | I14: V_TRIS_BATCH | J14: $$TRIS_BATCHDIR\BuildDB2LoadFiles\BuildVjobcode\BuildVjobcode.exe | K14: gx,mx | N14: 0 | S14: 1 | T14: TRIS | U14: F | V14: 3 | W14: DLTRISTeam@ameren.com | X14: TRIS_RH_Contract_Final_030_BuildPayrollFiles_vJOBCODE_TBL_TR FAILED | AA14: >>$$TRIS_BATCHDIR\Logs\%AUTO_JOB_NAME%_stdout.txt | AB14: >>$$TRIS_BATCHDIR\Logs\%AUTO_JOB_NAME%_stderr.txt
A15: TRIS_RH_Contract_Final_040_BuildPayrollFiles_vSAL_STEP_TR | B15: /api/core/common/v1/JobSalaryStep/generate-file | C15: Build File for DB2 Load of VSAL_STEP_TBL_TR #RH#DV-HR-TR# CHG0000000xxxxx | E15: s(TRIS_RH_Contract_Final_030_BuildPayrollFiles_vJOBCODE_TR) | F15: CMD | G15: TRIS_RH_Contract_Final | H15: TRISBATCH@ameren | I15: V_TRIS_BATCH | J15: $$TRIS_BATCHDIR\BuildDB2LoadFiles\BuildVsalarystep\BuildVsalarystep.exe | K15: gx,mx | N15: 0 | S15: 1 | T15: TRIS | U15: F | V15: 3 | W15: DLTRISTeam@ameren.com | X15: TRIS_RH_Contract_Final_040_BuildPayrollFiles_vSAL_STEP_TR FAILED | AA15: >>$$TRIS_BATCHDIR\Logs\%AUTO_JOB_NAME%_stdout.txt | AB15: >>$$TRIS_BATCHDIR\Logs\%AUTO_JOB_NAME%_stderr.txt
A16: TRIS_RH_Contract_Final_050_BuildPayrollFiles_FTP_vJOB_TR | B16: FTP Jobs Not Applicable | C16: FTP of file to load into VJOB_TR load #RH#DV-HR-TR# CHG0000000xxxxx | E16: s(TRIS_RH_Contract_Final_040_BuildPayrollFiles_vSAL_STEP_TR) | F16: FTP | G16: TRIS_RH_Contract_Final | H16: ASYSFTPP@SYSC | I16: V_TRIS_BATCH | K16: gx,mx | N16: 0 | S16: 1 | U16: F | V16: 3 | W16: DLTRISTeam@ameren.com | X16: TRIS_RH_Contract_Final_050_BuildPayrollFiles_FTP_vJOB_TR FAILED | AC16: A | AD16: UPLOAD | AE16: $$TRIS_BATCHDIR\\DB2LoadFiles\\VJOB-TR-EXTRACT.txt | AF16: ITP.DATA.JOB | AG16: SYSC.ameren.com | AH16: 0 | AI16: TRISBATCH@ameren | AJ16: Simple
A17: TRIS_RH_Contract_Final_060_BuildPayrollFiles_FTP_vDEPT_TR | B17: FTP Jobs Not Applicable | C17: FTP of file to load into VDEPT_TBL_TR load #RH#DV-HR-TR# CHG0000000xxxxx | E17: s(TRIS_RH_Contract_Final_050_BuildPayrollFiles_FTP_vJOB_TR) | F17: FTP | G17: TRIS_RH_Contract_Final | H17: ASYSFTPP@SYSC | I17: V_TRIS_BATCH | K17: gx,mx | N17: 0 | S17: 1 | U17: F | V17: 3 | W17: DLTRISTeam@ameren.com | X17: TRIS_RH_Contract_Final_060_BuildPayrollFiles_FTP_vDEPT_TR FAILED | AC17: A | AD17: UPLOAD | AE17: $$TRIS_BATCHDIR\\DB2LoadFiles\\VDEPT-TBL-TR-EXTRACT.txt | AF17: ITP.DATA.DEPT | AG17: SYSC.ameren.com | AH17: 0 | AI17: TRISBATCH@ameren | AJ17: Simple
A18: TRIS_RH_Contract_Final_070_BuildPayrollFiles_FTP_vJOBCODE | B18: FTP Jobs Not Applicable | C18: FTP of file to load into VJOBCODE_TBL_TR load #RH#DV-HR-TR# CHG0000000xxxxx | E18: s(TRIS_RH_Contract_Final_060_BuildPayrollFiles_FTP_vDEPT_TR) | F18: FTP | G18: TRIS_RH_Contract_Final | H18: ASYSFTPP@SYSC | I18: V_TRIS_BATCH | K18: gx,mx | N18: 0 | S18: 1 | U18: F | V18: 3 | W18: DLTRISTeam@ameren.com | X18: TRIS_RH_Contract_Final_070_BuildPayrollFiles_FTP_vJOBCODE FAILED | AC18: A | AD18: UPLOAD | AE18: $$TRIS_BATCHDIR\\DB2LoadFiles\\VJOBCODE-TBL-TR-EXTRACT.txt | AF18: ITP.DATA.JOBCODE | AG18: SYSC.ameren.com | AH18: 0 | AI18: TRISBATCH@ameren | AJ18: Simple
A19: TRIS_RH_Contract_Final_080_BuildPayrollFiles_FTP_vSAL | B19: FTP Jobs Not Applicable | C19: FTP of file to load into VSAL_STEP_TBL_TR load #RH#DV-HR-TR# CHG0000000xxxxx | E19: s(TRIS_RH_Contract_Final_070_BuildPayrollFiles_FTP_vJOBCODE) | F19: FTP | G19: TRIS_RH_Contract_Final | H19: ASYSFTPP@SYSC | I19: V_TRIS_BATCH | K19: gx,mx | N19: 0 | S19: 1 | U19: F | V19: 3 | W19: DLTRISTeam@ameren.com | X19: TRIS_RH_Contract_Final_080_BuildPayrollFiles_FTP_vSAL FAILED | AC19: A | AD19: UPLOAD | AE19: $$TRIS_BATCHDIR\\DB2LoadFiles\\VSAL-STEP-TBL-TR-EXTRACT.txt | AF19: ITP.DATA.SAL.STP | AG19: SYSC.ameren.com | AH19: 0 | AI19: TRISBATCH@ameren | AJ19: Simple
A20: TRIS_RH_Contract_Final_200_MF_AR13895 | B20: Cobol DB2 load Not in Autosys | C20: Loads the FTP files that contained HR data for Payroll into DB2 Tables #RH#DV-HR-TR# CHG0000000xxxxx | D20: OBULA | E20: s(TRIS_RH_Contract_Final_080_BuildPayrollFiles_FTP_vSAL) | F20: ZOS | G20: TRIS_RH_Contract_Final | H20: ESPAE | I20: V_TRIS_TRJobs2MF | L20: CF.STARTPDS | M20: AR13895 | N20: 0 | S20: 1 | U20: F | W20: DLTRISTeam@ameren.com | X20: TRIS_RH_Contract_Final_200_MF_AR13895 FAILED. Loads the FTP files that contained HR data for Payroll into DB2 Tables | Y20: action=STOP,rc=4\:4095,result=FAILURE
A21: TRIS_RH_Contract_Final_300_Build_HR_History_View | C21: Fills tables for view VJOB_TR_EFF which allows the HR History records to have a start and end date versus just an effective date. #RH#DV-HR-TR# CHG00000000xxxx | E21: s(TRIS_RH_Contract_Final_200_MF_AR13895) | F21: CMD | G21: TRIS_RH_Contract_Final | H21: TRISBATCH@ameren | I21: V_TRIS_BATCH | J21: $$TRIS_BATCHDIR\PSJobViewRefresh\PS2TRIS.exe | K21: gx,mx | N21: 0 | S21: 1 | T21: TRIS | U21: F | V21: 3 | W21: DLTRISTeam@ameren.com | X21: TRIS_RH_Contract_Final_300_Build_HR_History_View FAILED. Fills tables for view VJOB_TR_EFF which allows the HR History records to have a start and end date versus just an effective date. Look in \C\\TRISBatch\\Logs\ on server | AA21: >>$$TRIS_BATCHDIR\Logs\%AUTO_JOB_NAME%_stdout.txt | AB21: >>$$TRIS_BATCHDIR\Logs\%AUTO_JOB_NAME%_stderr.txt
A22: TRIS_RH_Contract_Final_410_MF_TR33200 | B22: TR_RN_ContractPayroll_TR33200_Trigger_HTTP | C22: Mainframe Contract Payroll processing that produces Payroll file that is used in TRIS_RH_Contract_Final_550_Send_ToPayroll to build a JSON request to send to Workday #RH#DV-HR-TR# CHG0000000xxxxx | D22: OBULA | E22: s(TRIS_RH_Contract_Final_300_Build_HR_History_View) | F22: ZOS | G22: TRIS_RH_Contract_Final | H22: ESPAE | I22: V_TRIS_TRJobs2MF | L22: UE.STARTPDS | M22: TR33200 | N22: 0 | S22: 1 | U22: F | W22: DLTRISTeam@ameren.com | X22: TRIS_RH_Contract_Final_410_MF_TR33200 FAILED. Mainframe Contract Payroll processing that produces Payroll file that is used in TRIS_RH_Contract_Final_550_Send_ToPayroll to build a JSON request to send to Workday | Y22: action=STOP,rc=1\:4095,result=FAILURE
A23: TRIS_RH_Contract_Final_420_MF_AR13687 | B23: Cobol DB2 load Not in Autosys | C23: FTPs Mainframe Payroll File built in TRIS_RH_Contract_Final_410_MF_TR33200 to Autosys server #RH#DV-HR-TR# CHG0000000xxxxx | D23: OBULA | E23: s(TRIS_RH_Contract_Final_410_MF_TR33200) | F23: ZOS | G23: TRIS_RH_Contract_Final | H23: ESPAE | I23: V_TRIS_TRJobs2MF | L23: CF.STARTPDS | M23: AR13687 | N23: 0 | S23: 1 | U23: F | W23: DLTRISTeam@ameren.com | X23: TRIS_RH_Contract_Final_420_MF_AR13687 FAILED. FTPs Mainframe Payroll File built in TRIS_RH_Contract_Final_410_MF_TR33200 to Autosys server | Y23: action=STOP,rc=1\:4095,result=FAILURE
A24: TRIS_RH_Contract_Final_530_Send_Copy_PayrollFile | B24: Cobol DB2 load Not in Autosys | C24: Copies Mainframe payroll file on the Autosys server to the RIS folder on the Corporate share drive #RH#DV-HR-TR# CHG0000000xxxxx | F24: CMD | G24: TRIS_RH_Contract_Final | H24: TRISBATCH@ameren | I24: V_TRIS_MFFTP | J24: %FTPDir2%\Exec\copy_file.bat %FTPDir%\tr_payroll_cont.txt \\corp.dir.ameren.com\dfs\Orgdrv\TRIS\MKS\tr_payroll_cont.txt | K24: gx,mx | N24: 0 | S24: 1 | T24: TRIS | U24: F | V24: 3 | W24: DLTRISTeam@ameren.com | X24: TRIS_RH_Contract_Final_530_Send_Copy_PayrollFile JOB FAILED. Copies Mainframe payroll file on the Autosys server to the RIS folder on the Corporate share drive | AA24: %FTPDir2%\Logs\Payroll_stdout.txt | AB24: %FTPDir2%\Logs\Payroll_stderr.txt
A25: TRIS_RH_Contract_Final_540_Send_Move_PayrollFile | B25: Cobol DB2 load Not in Autosys | C25: Moves Mainframe Payroll file from the TRIS folder on the Corporate share drive to the TRIS Server (V_TRIS_BATCH) #RH#DV-HR-TR# CHG0000000xxxxx | E25: s(TRIS_RH_Contract_Final_530_Send_Copy_PayrollFile) | F25: CMD | G25: TRIS_RH_Contract_Final | H25: TRISBATCH@ameren | I25: V_TRIS_BATCH | J25: $$TRIS_BATCHDIR\MoveMainframeFiles\MovePayrollFile\MovePayrollFile.exe | K25: gx,mx | N25: 0 | S25: 1 | T25: TRIS | U25: F | V25: 3 | W25: DLTRISTeam@ameren.com | X25: TRIS_RH_Contract_Final_540_Send_Move_PayrollFile FAILED. Moves Mainframe Payroll file from the TRIS folder on the Corporate share drive to the TRIS Server (V_TRIS_BATCH) | AA25: >>$$TRIS_BATCHDIR\Logs\%AUTO_JOB_NAME%_stdout.txt | AB25: >>$$TRIS_BATCHDIR\Logs\%AUTO_JOB_NAME%_stderr.txt
A26: TRIS_RH_Contract_Final_550_Send_ToPayroll | B26: /api/core/notification/v1/WorkdayPayroll/execute | C26: Send Payroll to Workday #RH#DV-HR-TR# CHG0000000xxxxx | D26: "Escalate to Venka when called by Pager Duty" | E26: s(TRIS_RH_Contract_Final_540_Send_Move_PayrollFile) | F26: CMD | G26: TRIS_RH_Contract_Final | H26: TRISBATCH@ameren | I26: V_TRIS_BATCH | J26: $$TRIS_BATCHDIR\WorkdayPayrollInterface\WorkdayPayrollInterface.exe | K26: gx,mx | N26: 0 | S26: 1 | T26: TRIS | U26: F | V26: 3 | W26: DLTRISTeam@ameren.com | X26: TRIS_RH_Contract_Final_550_Send_ToPayroll FAILED | AA26: >>$$TRIS_BATCHDIR\Logs\%AUTO_JOB_NAME%_stdout.txt | AB26: >>$$TRIS_BATCHDIR\Logs\%AUTO_JOB_NAME%_stderr.txt
A27: TRIS_RH_Contract_Final_600_MF_TR33206 | B27: TR_RN_ContractPayroll_TR33206_Trigger_HTTP | C27: Updates the sick leave banks to be viewed in TRIS after the Contract Final Job completes TRIS_RH_Contract_Final_210_MF_TR33200 #RH#DV-HR-TR# CHG0000000xxxxx (dynamic sick leave processing) | D27: OBULA | E27: s(TRIS_RH_Contract_Final_410_MF_TR33200) | F27: ZOS | G27: TRIS_RH_Contract_Final | H27: ESPAE | I27: V_TRIS_TRJobs2MF | L27: UE.STARTPDS | M27: TR33206 | N27: 0 | S27: 1 | U27: F | W27: DLTRISTeam@ameren.com | X27: TRIS_RH_Contract_Final_600_MF_TR33206 FAILED. Updates the sick leave banks to be viewed in TRIS after the Contract Final Job completes TRIS_RH_Contract_Final_210_MF_TR33200 | Y27: action=STOP,rc=1\:4095,result=FAILURE
A28: TRIS_RH_Contract_Preliminary_OnRequest_MF_TR33103N | B28: TR_RN_ContractPayroll_TR33103N_Trigger_HTTP | C28: Contract Preliminary Job on Request #RH#DV-HR-TR# CHG0000000xxxxx | F28: ZOS | H28: ESPAE | I28: V_TRIS_TRJobs2MF | L28: UE.STARTPDS | M28: TR33103N | N28: 0 | S28: 1 | U28: F | W28: DLTRISTeam@ameren.com | X28: TRIS_RH_Contract_Preliminary_OnRequest_MF_TR33103N FAILED. Contract Preliminary Job on Request | Y28: action=STOP,rc=1\:4095,result=FAILURE
A29: TRIS_RH_daily_010_BuildCommon_Department | B29: /api/core/notification/v1/departments/common/buildFile | C29: Builds File for DB2 Load of TAR_COMN_DEPT_TBL. #RH#DV-HR-TR# CHG0000000xxxxx | F29: CMD | G29: TRIS_RH_dailyBox | H29: TRISBATCH@ameren | I29: V_TRIS_BATCH | J29: $$TRIS_BATCHDIR\BuildDB2LoadFiles\BuildCommonDepartment\BuildCommonDepartment.exe | K29: gx,mx | N29: 0 | S29: 1 | T29: TRIS | U29: F | V29: 3 | W29: DLTRISTeam@ameren.com | X29: TRIS_RH_daily_010_BuildCommon_Department FAILED. Builds File for DB2 Load of TAR_COMN_DEPT_TBL. Look in \C\\TRISBatch\\Logs\ on server | AA29: >>$$TRIS_BATCHDIR\Logs\%AUTO_JOB_NAME%_stdout.txt | AB29: >>$$TRIS_BATCHDIR\Logs\%AUTO_JOB_NAME%_stderr.txt
A30: TRIS_RH_daily_020_BuildCommon_Employee | B30: /api/core/notification/v1/employees/buildFile | C30: Builds File for DB2 Load of TAR_COMN_EMP_TBL and Builds for DB2 Load of THRDB_EMPLOYEE_TBL #RH#DV-HR-TR# CHG0000000xxxxx | E30: s(TRIS_RH_daily_010_BuildCommon_Department) | F30: CMD | G30: TRIS_RH_dailyBox | H30: TRISBATCH@ameren | I30: V_TRIS_BATCH | J30: $$TRIS_BATCHDIR\BuildDB2LoadFiles\BuildCommonEmployeeFile\BuildCommonEmployeeFile.exe | K30: gx,mx | N30: 0 | S30: 1 | T30: TRIS | U30: F | V30: 3 | W30: DLTRISTeam@ameren.com | X30: TRIS_RH_daily_020_BuildCommon_Employee FAILED. Builds File for DB2 Load of TAR_COMN_EMP_TBL and Builds for DB2 Load of THRDB_EMPLOYEE_TBL. Look in \C\\TRISBatch\\Logs\ on server | AA30: >>$$TRIS_BATCHDIR\Logs\%AUTO_JOB_NAME%_stdout.txt | AB30: >>$$TRIS_BATCHDIR\Logs\%AUTO_JOB_NAME%_stderr.txt
A31: TRIS_RH_daily_030_BuildCommon_FTP_Department | B31: FTP Jobs Not Applicable | C31: FTP of file to load into TAR_COMN_DEPT_TBL. #RH#DV-HR-TR# CHG0000000xxxxx | E31: s(TRIS_RH_daily_020_BuildCommon_Employee) | F31: FTP | G31: TRIS_RH_dailyBox | H31: ASYSFTPP@SYSC | I31: V_TRIS_BATCH | K31: gx,mx | N31: 0 | S31: 1 | U31: F | V31: 3 | W31: DLTRISTeam@ameren.com | X31: TRIS_RH_daily_030_BuildCommon_FTP_Department FAILED. FTP of file to load into TAR_COMN_DEPT_TBL. | AC31: A | AD31: UPLOAD | AE31: $$TRIS_BATCHDIR\\DB2LoadFiles\\CommonDepartment-EXTRACT.txt | AF31: ITP.DATA.GDG.DEPT.EXTRT | AG31: SYSC.ameren.com | AH31: 0 | AI31: TRISBATCH@ameren | AJ31: Simple
A32: TRIS_RH_daily_040_BuildCommon_FTP_Employee | B32: FTP Jobs Not Applicable | C32: FTP a file to load into TAR_COMN_EMPL_TBL. #RH#DV-HR-TR# CHG0000000xxxxx | E32: s(TRIS_RH_daily_030_BuildCommon_FTP_Department) | F32: FTP | G32: TRIS_RH_dailyBox | H32: ASYSFTPP@SYSC | I32: V_TRIS_BATCH | K32: gx,mx | N32: 0 | S32: 1 | U32: F | V32: 3 | W32: DLTRISTeam@ameren.com | X32: TRIS_RH_daily_040_BuildCommon_FTP_Employee FAILED. FTP a file to load into TAR_COMN_EMPL_TBL | AC32: A | AD32: UPLOAD | AE32: $$TRIS_BATCHDIR\\DB2LoadFiles\\COMNEMPL-EXTRACT.txt | AF32: ITP.DATA.GDG.EMPL.EXTRT | AG32: SYSC.ameren.com | AH32: 0 | AI32: TRISBATCH@ameren | AJ32: Simple
A33: TRIS_RH_daily_050_BuildCommon_FTP_THRDBEmployee | B33: FTP Jobs Not Applicable | C33: FTP a File for DB2 Load of THRDB_EMPLOYEE_TBL #RH#DV-HR-TR# CHG0000000xxxxx | E33: s(TRIS_RH_daily_040_BuildCommon_FTP_Employee) | F33: FTP | G33: TRIS_RH_dailyBox | H33: ASYSFTPP@SYSC | I33: V_TRIS_BATCH | K33: gx,mx | N33: 0 | S33: 1 | U33: F | V33: 3 | W33: DLTRISTeam@ameren.com | X33: TRIS_RH_daily_050_BuildCommon_FTP_THRDBEmployee FAILED. FTP a File for DB2 Load of THRDB_EMPLOYEE_TBL | AC33: A | AD33: UPLOAD | AE33: $$TRIS_BATCHDIR\\DB2LoadFiles\\THRDB-EMPLOYEE-EXTRACT.txt | AF33: ITP.DATA.GDG.EMPL.DB2 | AG33: SYSC.ameren.com | AH33: 0 | AI33: TRISBATCH@ameren | AJ33: Simple
A34: TRIS_RH_daily_070_BuildCommon_Associations | B34: /api/core/notification/v1/build/associations/buildFile | C34: Builds File for maintaining the TTR_ASSOCIATIONS table in mainframe job UE.STARTPDS(TR33107N). #RH#DV-HR-TR# CHG0000000xxxxx | E34: s(TRIS_RH_daily_050_BuildCommon_FTP_THRDBEmployee) | F34: CMD | G34: TRIS_RH_dailyBox | H34: TRISBATCH@ameren | I34: V_TRIS_BATCH | J34: $$TRIS_BATCHDIR\BuildDB2LoadFiles\BuildAssociations\BuildAssociations.exe | K34: gx,mx | N34: 0 | S34: 1 | T34: TRIS | U34: F | V34: 3 | W34: DLTRISTeam@ameren.com | X34: TRIS_RH_daily_070_BuildCommon_Associations FAILED. Builds File for maintaining the TTR_ASSOCIATIONS table in mainframe job UE.STARTPDS(TR33107N). Look in \C\\TRISBatch\\Logs\ on server | AA34: >>$$TRIS_BATCHDIR\Logs\%AUTO_JOB_NAME%_stdout.txt | AB34: >>$$TRIS_BATCHDIR\Logs\%AUTO_JOB_NAME%_stderr.txt
A35: TRIS_RH_daily_080_BuildCommon_FTP_Associations | B35: FTP Jobs Not Applicable | C35: FTP a file to process in UE.STARTPDS(TR33107N). #RH#DV-HR-TR# CHG0000000xxxxx | E35: s(TRIS_RH_daily_070_BuildCommon_Associations) | F35: FTP | G35: TRIS_RH_dailyBox | H35: ASYSFTPP@SYSC | I35: V_TRIS_BATCH | K35: gx,mx | N35: 0 | S35: 1 | U35: F | V35: 3 | W35: DLTRISTeam@ameren.com | X35: TRIS_RH_daily_080_BuildCommon_FTP_Associations FAILED. FTP a file to process in UE.STARTPDS(TR33107N). | AC35: A | AD35: UPLOAD | AE35: $$TRIS_BATCHDIR\\DB2LoadFiles\\TTR-ASSOCIATIONS-EXTRACT.txt | AF35: ITP.DATA..DPTTABLE | AG35: SYSC.ameren.com | AH35: 0 | AI35: TRISBATCH@ameren | AJ35: Simple
A36: TRIS_RH_daily_100_BuildPayrollFiles_vJOB_TR | B36: /api/core/notification/v1/jobs/buildFile | C36: Build File for DB2 Load of VJOB_TR #RH#DV-HR-TR# CHG0000000xxxxx | E36: s(TRIS_RH_daily_080_BuildCommon_FTP_Associations) | F36: CMD | G36: TRIS_RH_dailyBox | H36: TRISBATCH@ameren | I36: V_TRIS_BATCH | J36: $$TRIS_BATCHDIR\BuildDB2LoadFiles\BuildVjob\BuildVjob.exe | K36: gx,mx | N36: 0 | S36: 1 | T36: TRIS | U36: F | V36: 3 | W36: DLTRISTeam@ameren.com | X36: TRIS_RH_daily_100_BuildPayrollFiles_vJOB_TR FAILED. Build File for DB2 Load of VJOB_TR. Look in \C\\TRISBatch\\Logs\ on server | AA36: >>$$TRIS_BATCHDIR\Logs\%AUTO_JOB_NAME%_stdout.txt | AB36: >>$$TRIS_BATCHDIR\Logs\%AUTO_JOB_NAME%_stderr.txt
A37: TRIS_RH_daily_110_BuildPayrollFiles_vDEPT_TBL_TR | B37: /api/core/notification/v1/departments/buildFile | C37: Build File for DB2 Load of VDEPT_TBL_TR #RH#DV-HR-TR# CHG0000000xxxxx | E37: s(TRIS_RH_daily_100_BuildPayrollFiles_vJOB_TR) | F37: CMD | G37: TRIS_RH_dailyBox | H37: TRISBATCH@ameren | I37: V_TRIS_BATCH | J37: $$TRIS_BATCHDIR\BuildDB2LoadFiles\BuildVdept\BuildVdept.exe | K37: gx,mx | N37: 0 | S37: 1 | T37: TRIS | U37: F | V37: 3 | W37: DLTRISTeam@ameren.com | X37: TRIS_RH_daily_110_BuildPayrollFiles_vDEPT_TBL_TR FAILED. Build File for DB2 Load of VDEPT_TBL_TR. Look in \C\\TRISBatch\\Logs\ on server | AA37: >>$$TRIS_BATCHDIR\Logs\%AUTO_JOB_NAME%_stdout.txt | AB37: >>$$TRIS_BATCHDIR\Logs\%AUTO_JOB_NAME%_stderr.txt
A38: TRIS_RH_daily_120_BuildPayrollFiles_vJOBCODE_TBL_TR | B38: /api/core/notification/v1/jobcodes/buildFile | C38: Build File for DB2 Load of VJOBCODE_TBL_TR #RH#DV-HR-TR# CHG0000000xxxxx | E38: s(TRIS_RH_daily_110_BuildPayrollFiles_vDEPT_TBL_TR) | F38: CMD | G38: TRIS_RH_dailyBox | H38: TRISBATCH@ameren | I38: V_TRIS_BATCH | J38: $$TRIS_BATCHDIR\BuildDB2LoadFiles\BuildVjobcode\BuildVjobcode.exe | K38: gx,mx | N38: 0 | S38: 1 | T38: TRIS | U38: F | V38: 3 | W38: DLTRISTeam@ameren.com | X38: TRIS_RH_daily_120_BuildPayrollFiles_vJOBCODE_TBL_TR FAILED. Build File for DB2 Load of VJOBCODE_TBL_TR. Look in \C\\TRISBatch\\Logs\ on server | AA38: >>$$TRIS_BATCHDIR\Logs\%AUTO_JOB_NAME%_stdout.txt | AB38: >>$$TRIS_BATCHDIR\Logs\%AUTO_JOB_NAME%_stderr.txt
A39: TRIS_RH_daily_130_BuildPayrollFiles_vSAL_STEP_TBL_TR | B39: /api/core/common/v1/JobSalaryStep/generate-file | C39: Build File for DB2 Load of VSAL_STEP_TBL_TR #RH#DV-HR-TR# CHG0000000xxxxx | E39: s(TRIS_RH_daily_120_BuildPayrollFiles_vJOBCODE_TBL_TR) | F39: CMD | G39: TRIS_RH_dailyBox | H39: TRISBATCH@ameren | I39: V_TRIS_BATCH | J39: $$TRIS_BATCHDIR\BuildDB2LoadFiles\BuildVsalarystep\BuildVsalarystep.exe | K39: gx,mx | N39: 0 | S39: 1 | T39: TRIS | U39: F | V39: 3 | W39: DLTRISTeam@ameren.com | X39: TRIS_RH_daily_130_BuildPayrollFiles_vSAL_STEP_TBL_TR FAILED. Build File for DB2 Load of VSAL_STEP_TBL_TR. Look in \C\\TRISBatch\\Logs\ on server | AA39: >>$$TRIS_BATCHDIR\Logs\%AUTO_JOB_NAME%_stdout.txt | AB39: >>$$TRIS_BATCHDIR\Logs\%AUTO_JOB_NAME%_stderr.txt
A40: TRIS_RH_daily_140_BuildPayrollFiles_FTP_vJOB_TR | B40: FTP Jobs Not Applicable | C40: FTP of file to load into VJOB_TR load #RH#DV-HR-TR# CHG0000000xxxxx | E40: s(TRIS_RH_daily_130_BuildPayrollFiles_vSAL_STEP_TBL_TR) | F40: FTP | G40: TRIS_RH_dailyBox | H40: ASYSFTPP@SYSC | I40: V_TRIS_BATCH | K40: gx,mx | N40: 0 | S40: 1 | U40: F | V40: 3 | W40: DLTRISTeam@ameren.com | X40: TRIS_RH_daily_140_BuildPayrollFiles_FTP_vJOB_TR FAILED. FTP of file to load into VJOB_TR load. | AC40: A | AD40: UPLOAD | AE40: $$TRIS_BATCHDIR\\DB2LoadFiles\\VJOB-TR-EXTRACT.txt | AF40: ITP.DATA.JOB | AG40: SYSC.ameren.com | AH40: 0 | AI40: TRISBATCH@ameren | AJ40: Simple
A41: TRIS_RH_daily_150_BuildPayrollFiles_FTP_vDEPT_TBL_TR | B41: FTP Jobs Not Applicable | C41: FTP of file to load into VDEPT_TBL_TR #RH#DV-HR-TR# CHG0000000xxxxx | E41: s(TRIS_RH_daily_140_BuildPayrollFiles_FTP_vJOB_TR) | F41: FTP | G41: TRIS_RH_dailyBox | H41: ASYSFTPP@SYSC | I41: V_TRIS_BATCH | K41: gx,mx | N41: 0 | S41: 1 | U41: F | V41: 3 | W41: DLTRISTeam@ameren.com | X41: TRIS_RH_daily_150_BuildPayrollFiles_FTP_vDEPT_TBL_TR FAILED. FTP of file to load into VDEPT_TBL_TR. | AC41: A | AD41: UPLOAD | AE41: $$TRIS_BATCHDIR\\DB2LoadFiles\\VDEPT-TBL-TR-EXTRACT.txt | AF41: ITP.DATA.DEPT | AG41: SYSC.ameren.com | AH41: 0 | AI41: TRISBATCH@ameren | AJ41: Simple
A42: TRIS_RH_daily_160_BuildPayrollFiles_FTP_vJOBCODE_TBL_TR | B42: FTP Jobs Not Applicable | C42: FTP of file to load into VJOBCODE_TBL_TR #RH#DV-HR-TR# CHG0000000xxxxx | E42: s(TRIS_RH_daily_150_BuildPayrollFiles_FTP_vDEPT_TBL_TR) | F42: FTP | G42: TRIS_RH_dailyBox | H42: ASYSFTPP@SYSC | I42: V_TRIS_BATCH | K42: gx,mx | N42: 0 | S42: 1 | U42: F | V42: 3 | W42: DLTRISTeam@ameren.com | X42: TRIS_RH_daily_160_BuildPayrollFiles_FTP_vJOBCODE_TBL_TR FAILED. FTP of file to load into VJOBCODE_TBL_TR | AC42: A | AD42: UPLOAD | AE42: $$TRIS_BATCHDIR\\DB2LoadFiles\\VJOBCODE-TBL-TR-EXTRACT.txt | AF42: ITP.DATA.JOBCODE | AG42: SYSC.ameren.com | AH42: 0 | AI42: TRISBATCH@ameren | AJ42: Simple
A43: TRIS_RH_daily_170_BuildPayrollFiles_FTP_vSAL_STEP_TBL_TR | B43: FTP Jobs Not Applicable | C43: FTP of file to load into VSAL_STEP_TBL_TR #RH#DV-HR-TR# CHG0000000xxxxx | E43: s(TRIS_RH_daily_160_BuildPayrollFiles_FTP_vJOBCODE_TBL_TR) | F43: FTP | G43: TRIS_RH_dailyBox | H43: ASYSFTPP@SYSC | I43: V_TRIS_BATCH | K43: gx,mx | N43: 0 | S43: 1 | U43: F | V43: 3 | W43: DLTRISTeam@ameren.com | X43: TRIS_RH_daily_170_BuildPayrollFiles_FTP_vSAL_STEP_TBL_TR FAILED. FTP of file to load into VSAL_STEP_TBL_TR | AC43: A | AD43: UPLOAD | AE43: $$TRIS_BATCHDIR\\DB2LoadFiles\\VSAL-STEP-TBL-TR-EXTRACT.txt | AF43: ITP.DATA.SAL.STP | AG43: SYSC.ameren.com | AH43: 0 | AI43: TRISBATCH@ameren | AJ43: Simple
A44: TRIS_RH_daily_300_MF_AR13872 | B44: Cobol DB2 load Not in Autosys | C44: Moves the Associations File that were sent in job TRIS_RH_daily_080_BuildCommon_FTP_Associations from Mainframe FTP directory to a Mainframe dataset. #RH#DV-HR-TR# CHG0000000xxxxx | D44: OBULA | E44: s(TRIS_RH_daily_170_BuildPayrollFiles_FTP_vSAL_STEP_TBL_TR) | F44: ZOS | G44: TRIS_RH_dailyBox | H44: ESPAE | I44: V_TRIS_TRJobs2MF | L44: CF.STARTPDS | M44: AR13872 | N44: 0 | S44: 1 | U44: F | W44: DLTRISTeam@ameren.com | X44: TRIS_RH_daily_300_MF_AR13872 FAILED. Moves the Associations File that were sent in job TRIS_RH_daily_080_BuildCommon_FTP_Associations from Mainframe FTP directory to a Mainframe dataset. | Y44: action=STOP,rc=1\:4095,result=FAILURE
A45: TRIS_RH_daily_310_MF_AR13999 | B45: Cobol DB2 load Not in Autosys | C45: Moves the Files that were sent in jobs TRIS_RH_daily_030, TRIS_RH_daily_040, & TRIS_RH_daily_050 from Mainframe FTP directory to Mainframe datasets #RH#DV-HR-TR# CHG0000000xxxxx | D45: OBULA | E45: s(TRIS_RH_daily_300_MF_AR13872) | F45: ZOS | G45: TRIS_RH_dailyBox | H45: ESPAE | I45: V_TRIS_TRJobs2MF | L45: CF.STARTPDS | M45: AR13999 | N45: 0 | S45: 1 | U45: F | W45: DLTRISTeam@ameren.com | X45: TRIS_RH_daily_310_MF_AR13999 FAILED. Moves the Files that were sent in jobs TRIS_RH_daily_030, TRIS_RH_daily_040, & TRIS_RH_daily_050 from Mainframe FTP directory to Mainframe datasets | Y45: action=STOP,rc=1\:4095,result=FAILURE
A46: TRIS_RH_daily_320_MF_AR13895 | B46: Cobol DB2 load Not in Autosys | C46: Moves the Files that were sent in jobs TRIS_RH_daily_140, TRIS_RH_daily_150, TRIS_RH_daily_160, & TRIS_RH_daily_170 from Mainframe FTP directory to Mainframe datasets. It then loads the data into DB2 Tables #RH#DV-HR-TR# CHG0000000xxxxx | D46: OBULA | E46: s(TRIS_RH_daily_310_MF_AR13999) | F46: ZOS | G46: TRIS_RH_dailyBox | H46: ESPAE | I46: V_TRIS_TRJobs2MF | L46: CF.STARTPDS | M46: AR13895 | N46: 0 | S46: 1 | U46: F | W46: DLTRISTeam@ameren.com | X46: TRIS_RH_daily_320_MF_AR13895 FAILED. Moves the Files that were sent in jobs TRIS_RH_daily_140, TRIS_RH_daily_150, TRIS_RH_daily_160, & TRIS_RH_daily_170 from Mainframe FTP directory to Mainframe datasets. It then loads the data into DB2 Tables | Y46: action=STOP,rc=5\:4095,result=FAILURE
A47: TRIS_RH_daily_330_MF_DB12287N | B47: Cobol DB2 load Not in Autosys | C47: Loads the Common Employee and Common Department tables sent from jobs TRIS_RH_daily_030, TRIS_RH_daily_040 and moved in job TRIS_RH_daily_310_MF_AR13999 #RH#DV-HR-TR# CHG0000000xxxxx | D47: OBULA | E47: s(TRIS_RH_daily_320_MF_AR13895) | F47: ZOS | G47: TRIS_RH_dailyBox | H47: ESPAE | I47: V_TRIS_TRJobs2MF | L47: UE.STARTPDS | M47: DB12287N | N47: 0 | S47: 1 | U47: F | W47: DLTRISTeam@ameren.com | X47: TRIS_RH_daily_330_MF_DB12287N FAILED. Loads the Common Employee and Common Department tables sent from jobs TRIS_RH_daily_030, TRIS_RH_daily_040 and moved in job TRIS_RH_daily_310_MF_AR13999 | Y47: action=STOP,rc=1\:4095,result=FAILURE
A48: TRIS_RH_daily_340_MF_DB12005N | B48: Cobol DB2 load Not in Autosys | C48: Loads the THRDB Employee table sent from job TRIS_RH_daily_050 and moved in job TRIS_RH_daily_310_MF_AR13999 #RH#DV-HR-TR# CHG0000000xxxxx | D48: OBULA | E48: s(TRIS_RH_daily_330_MF_DB12287N) | F48: ZOS | G48: TRIS_RH_dailyBox | H48: ESPAE | I48: V_TRIS_TRJobs2MF | L48: UE.STARTPDS | M48: DB12005N | N48: 0 | S48: 1 | U48: F | W48: DLTRISTeam@ameren.com | X48: TRIS_RH_daily_340_MF_DB12005N FAILED. Loads the THRDB Employee table sent from job TRIS_RH_daily_050 and moved in job TRIS_RH_daily_310_MF_AR13999 | Y48: action=STOP,rc=1\:4095,result=FAILURE
A49: TRIS_RH_daily_380_Build_HR_History_View | C49: Fills tables for view VJOB_TR_EFF which allows the HR History records to have a start and end date versus just an effective date. #RH#DV-HR-TR# CHG00000000xxxx | E49: s(TRIS_RH_daily_340_MF_DB12005N) | F49: CMD | G49: TRIS_RH_dailyBox | H49: TRISBATCH@ameren | I49: V_TRIS_BATCH | J49: $$TRIS_BATCHDIR\PSJobViewRefresh\PS2TRIS.exe | K49: gx,mx | N49: 0 | S49: 1 | T49: TRIS | U49: F | V49: 3 | W49: DLTRISTeam@ameren.com | X49: TRIS_RH_daily_380_Build_HR_History_View FAILED. Fills tables for view VJOB_TR_EFF which allows the HR History records to have a start and end date versus just an effective date | AA49: >>$$TRIS_BATCHDIR\Logs\%AUTO_JOB_NAME%_stdout.txt | AB49: >>$$TRIS_BATCHDIR\Logs\%AUTO_JOB_NAME%_stderr.txt
A50: TRIS_RH_daily_410_MF_TR33106 | B50: TR_RN_Maintain_TR33106N_Trigger_HTTP | C50: Maintains the TTR_JOBS table (TR014) #RH#DV-HR-TR# CHG0000000xxxxx | E50: s(TRIS_RH_daily_380_Build_HR_History_View) | F50: ZOS | G50: TRIS_RH_dailyBox | H50: ESPAE | I50: V_TRIS_TRJobs2MF | L50: UE.STARTPDS | M50: TR33106N | N50: 0 | S50: 1 | U50: F | W50: DLTRISTeam@ameren.com | X50: TRIS_RH_daily_410_MF_TR33106 FAILED. Maintains the TTR_JOBS table (TR014) | Y50: action=STOP,rc=1\:4095,result=FAILURE
A51: TRIS_RH_daily_420_MF_TR33107 | B51: TR_RN_Maintain_TR33107_Trigger_HTTP | C51: Maintains the TTR_ASSOCIATIONS table (TR015) #RH#DV-HR-TR# CHG0000000xxxxx | E51: s(TRIS_RH_daily_410_MF_TR33106) | F51: ZOS | G51: TRIS_RH_dailyBox | H51: ESPAE | I51: V_TRIS_TRJobs2MF | L51: UE.STARTPDS | M51: TR33107N | N51: 0 | S51: 1 | U51: F | W51: DLTRISTeam@ameren.com | X51: TRIS_RH_daily_420_MF_TR33107 FAILED. Maintains the TTR_ASSOCIATIONS table (TR015) | Y51: action=STOP,rc=1\:4095,result=FAILURE
A52: TRIS_RH_daily_430_MF_TR33102 | B52: TR_RN_Maintain_TR33102_Trigger_HTTP | C52: HR/TRIS interface employee update (TR009 & TR129) #RH#DV-HR-TR# CHG0000000xxxxx | E52: s(TRIS_RH_daily_420_MF_TR33107) | F52: ZOS | G52: TRIS_RH_dailyBox | H52: ESPAE | I52: V_TRIS_TRJobs2MF | L52: UE.STARTPDS | M52: TR33102N | N52: 0 | S52: 1 | U52: F | W52: DLTRISTeam@ameren.com | X52: TRIS_RH_daily_430_MF_TR33102 FAILED. HR/TRIS interface employee update (TR009 & TR129) | Y52: action=STOP,rc=1\:4095,result=FAILURE
A53: TRIS_RH_daily_435_Vacation_Allotment | B53: /api/core/payroll/v1/VacAllotment/Main | C53: Updates the Vacation allotment for new hires | E53: s(TRIS_RH_daily_430_MF_TR33102) | F53: CMD | G53: TRIS_RH_dailyBox | H53: TRISBATCH@ameren | I53: V_TRIS_BATCH | J53: $$TRIS_BATCHDIR\VacationAllotment\Ameren.TRIS.Server.Batch.VAllotment.exe | K53: gs,mx | N53: 0 | S53: 1 | U53: F | W53: DLTRISTeam@ameren.com | X53: TRIS_RH_daily_435_Vacation_Allotment FAILED | AA53: >>$$TRIS_BATCHDIR\Logs\%AUTO_JOB_NAME%_stdout.txt | AB53: >>$$TRIS_BATCHDIR\Logs\%AUTO_JOB_NAME%_stderr.txt
A54: TRIS_RH_daily_437_Maintain_Holidays | B54: Need to update | C54: Removes exceptions for terminated employees and add Holidays for new hires | E54: s(TRIS_RH_daily_435_Vacation_Allotment) | F54: CMD | G54: TRIS_RH_dailyBox | H54: TRISBATCH@ameren | I54: V_TRIS_BATCH | J54: $$TRIS_BATCHDIR\MaintainHolidays\MaintainHolidays.exe | K54: gx,mx | N54: 0 | S54: 1 | U54: F | W54: DLTRISTeam@ameren.com | X54: TRIS_RH_daily_437_Maintain_Holidays FAILED | AA54: >>$$TRIS_BATCHDIR\Logs\%AUTO_JOB_NAME%_stdout.txt | AB54: >>$$TRIS_BATCHDIR\Logs\%AUTO_JOB_NAME%_stderr.txt
A55: TRIS_RH_daily_440_MF_TR33136 | B55: Cobol DB2 load Not in Autosys | C55: Seniority accrual -- Adds one day of seniority (TI0510) #RH#DV-HR-TR# CHG0000000xxxxx | E55: s(TRIS_RH_daily_437_Maintain_Holidays) | F55: ZOS | G55: TRIS_RH_dailyBox | H55: ESPAE | I55: V_TRIS_TRJobs2MF | L55: UE.STARTPDS | M55: TR33136N | N55: 0 | S55: 1 | U55: F | W55: DLTRISTeam@ameren.com | X55: TRIS_RH_daily_440_MF_TR33136 FAILED. Seniority accrual -- Adds one day of seniority (TI0510) | Y55: action=STOP,rc=1\:4095,result=FAILURE
A56: TRIS_RH_daily_445_workday_Seniority_Interface | B56: /api/core/notification/v1/WorkdaySeniority/execute | C56: Send Seniority to Workday #RH#DV-HR-TR# CHG0000000xxxxx | D56: If TRIS_RH_daily_445_workday_Seniority_Interface keeps failing, the status of TRIS_RH_daily_445_workday_Seniority_Interface needs to be changed to Success. | E56: s(TRIS_RH_daily_440_MF_TR33136) | F56: CMD | G56: TRIS_RH_dailyBox | H56: TRISBATCH@ameren | I56: V_TRIS_BATCH | J56: $$TRIS_BATCHDIR\WorkdaySeniorityInterface\WorkdaySeniorityInterface.exe | K56: gx,mx | N56: 0 | O56: su,mo,tu,we,th,fr, | S56: 1 | T56: TRIS | U56: F | V56: 3 | W56: DLTRISTeam@ameren.com | X56: TRIS_RH_workday_Seniority_Interface FAILED | AA56: >>$$TRIS_BATCHDIR\Logs\%AUTO_JOB_NAME%_stdout.txt | AB56: >>$$TRIS_BATCHDIR\Logs\%AUTO_JOB_NAME%_stderr.txt
A57: TRIS_RH_daily_450_MF_TR33115 | B57: Cobol DB2 load Not in Autosys | C57: Auto Builds scheduled exception (Holiday, Vacation) time for employees in variable departments and all time for employees in fixed & exception based departments. #RH#DV-HR-TR# CHG0000000xxxxx (i.e. TRBE) | E57: s(TRIS_RH_daily_440_MF_TR33136) | F57: ZOS | G57: TRIS_RH_dailyBox | H57: ESPAE | I57: V_TRIS_TRJobs2MF | L57: UE.STARTPDS | M57: TR33115N | N57: 0 | S57: 1 | U57: F | W57: DLTRISTeam@ameren.com | X57: TRIS_RH_daily_450_MF_TR33115 FAILED. Auto Builds scheduled exception (Holiday, Vacation) time for employees in variable departments and all time for employees in fixed & exception based departments. | Y57: action=STOP,rc=1\:4095,result=FAILURE
A58: TRIS_RH_daily_600_MF_TR33103N | B58: TR_RN_ContractPayroll_TR33103N_Trigger_HTTP | C58: Contract Preliminary Job #RH#DV-HR-TR# CHG0000000xxxxx | E58: s(TRIS_RH_daily_450_MF_TR33115) | F58: ZOS | G58: TRIS_RH_dailyBox | H58: ESPAE | I58: V_TRIS_TRJobs2MF | L58: UE.STARTPDS | M58: TR33103N | N58: 0 | O58: mo,tu | P58: 01:00 | R58: exclude_calendar: AM_holidays | S58: 1 | U58: F | W58: DLTRISTeam@ameren.com | X58: TRIS_RH_daily_600_MF_TR33103N FAILED. Contract Preliminary Job | Y58: action=STOP,rc=1\:4095,result=FAILURE
A59: TRIS_RH_daily_700_MF_TR33101N | B59: TR_RN_ContractPayroll_TR33101N_Trigger_HTTP | C59: Contract Daily Job #RH#DV-HR-TR# CHG0000000xxxxx | E59: s(TRIS_RH_daily_600_MF_TR33103N) | F59: ZOS | G59: TRIS_RH_dailyBox | H59: ESPAE | I59: V_TRIS_TRJobs2MF | L59: UE.STARTPDS | M59: TR33101N | N59: 0 | S59: 1 | U59: F | W59: DLTRISTeam@ameren.com | X59: TRIS_RH_daily_700_MF_TR33101N FAILED. Contract Daily Job | Y59: action=STOP,rc=1\:4095,result=FAILURE
A60: TRIS_RH_daily_800_TRISBIExtract | B60: Cobol DB2 load Not in Autosys | C60: TRIS BI extract #RN#DV-HR-TR# CHG00000000xxxx | E60: s(TRIS_RH_daily_700_MF_TR33101N) | F60: CMD | G60: TRIS_RH_dailyBox | H60: TRISBATCH@ameren | I60: V_TRIS_BATCH | J60: $$TRIS_BATCHDIR\TRISIMRInterface\TRISBIExtract.exe | K60: gx,mx | N60: 1 | O60: mo,tu,we,th,fr | P60: 01:30 | S60: 1 | T60: TRIS | U60: F | V60: 3 | W60: DLTRISTeam@ameren.com | X60: TRISBI_RN_TRISBIExtract FAILED. | AA60: >>$$TRIS_BATCHDIR\Logs\%AUTO_JOB_NAME%_stdout.txt | AB60: >>$$TRIS_BATCHDIR\Logs\%AUTO_JOB_NAME%_stderr.txt
A61: TRIS_RH_daily_810_IMREmail | B61: /api/core/notification/v1/TRISIMRInterface/execute | C61: TRIS IMR email #RN#DV-HR-TR# CHG00000000xxxx | E61: s(TRIS_RH_daily_800_TRISBIExtract) | F61: CMD | G61: TRIS_RH_dailyBox | H61: TRISBATCH@ameren | I61: V_TRIS_BATCH | J61: $$TRIS_BATCHDIR\TRISIMRInterface\IMREmail.exe | K61: gx,mx | N61: 1 | O61: mo,tu,we,th,fr | P61: 01:30 | S61: 1 | T61: TRIS | U61: F | V61: 3 | W61: DLTRISTeam@ameren.com | X61: TRISBI_RN_IMREmail FAILED. | AA61: >>$$TRIS_BATCHDIR\Logs\%AUTO_JOB_NAME%_stdout.txt | AB61: >>$$TRIS_BATCHDIR\Logs\%AUTO_JOB_NAME%_stderr.txt
A62: TRIS_RH_Daily_everyday_0005_DelayedOTBanks_MF_TR33108 | B62: Cobol DB2 load Not in Autosys | C62: Processes delayed overtime bank charges (TR008) at 00:05 every day. #RH#DV-HR-TR# CHG0000000xxxxx | F62: ZOS | H62: ESPAE | I62: V_TRIS_TRJobs2MF | L62: UE.STARTTPDS | M62: TR33108 | N62: 1 | O62: su,mo,tu,we,th,fr,sa | P62: 0.0034722222 | S62: 1 | U62: F | W62: DLTRISTeam@ameren.com | X62: TRIS_RH_Daily_everyday_0005_DelayedOTBanks_MF_TR33108. Processes delayed overtime bank charges at 00:05 every day. | Y62: action=STOP,rc=1\:4095,result=FAILURE
A63: TRIS_RH_Daily_everyday_1900_DepartmentMaintenance | B63: Need to update | C63: Maintains the TRIS TTR_DEPT table using the Accounting System Department Master from TRIS_RH_Daily_everyday_1900_DeptMaint_01_MF_TR33321 (TR013) #RH#DV-HR-TR# CHG0000000xxxxx | E63: s(TRIS_RH_Daily_everyday_1900_DeptMaint_01_MF_TR33321) | F63: ZOS | H63: ESPAE | I63: V_TRIS_TRJobs2MF | L63: ITP.DV.STARTPDS | M63: TR33300N (NOT USED) | N63: 0 | S63: 1 | U63: F | W63: DLTRISTeam@ameren.com | X63: TRIS_RH_Daily_everyday_1900_DeptMaint_02_MF_TR33300 FAILED. Maintains the TRIS TTR_DEPT table using the Accounting System Department Master from TRIS_RH_Daily_everyday_1900_DeptMaint_01_MF_TR33321 (TR013) | Y63: action=STOP,rc=1\:4095,result=FAILURE
A64: TRIS_RH_Daily_everyday_1900_workday_FMLA_Interface | B64: /api/core/notification/v1/WorkdayFmla/execute | C64: Get Workday FMLA data to maintain the TTR_EMP_FMLA table. Runs at 19:00 everyday TTR_EMP_FMLA #RH#DV-HR-TR# CHG0000000xxxxx | F64: CMD | H64: TRISBATCH@ameren | I64: V_TRIS_BATCH | J64: $$TRIS_BATCHDIR\WorkdayFLMAInterface\WorkdayFLMAInterface.exe | N64: 1 | O64: su,mo,tu,we,th,fr,sa | P64: 0.79166667 | S64: 1 | T64: TRIS | U64: F | V64: 3 | W64: DLTRISTeam@ameren.com | X64: TRIS_RH_Daily_everyday_1900_workday_FMLA_Interface FAILED. Get Workday FMLA data to maintain the TTR_EMP_FMLA table. Look in \C\\TRISBatch\\Logs\ on server | AA64: >>$$TRIS_BATCHDIR\Logs\%AUTO_JOB_NAME%_stdout.txt | AB64: >>$$TRIS_BATCHDIR\Logs\%AUTO_JOB_NAME%_stderr.txt
A65: TRIS_RH_dailyBox | C65: Runs TRIS Daily Processes Monday through Saturday | F65: BOX | H65: TRISBATCH@ameren | K65: gx,mx | N65: 1 | O65: mo,tu,we,th,fr,sa | P65: 0.041666667 | S65: 1 | V65: 3
A66: TRIS_RH_Executive_Final | B66: /api/core/notification/v1/WorkdayPayroll/execute | C66: This runs the TRIS portion of the Executive payroll | F66: BOX | H66: TRISBATCH@ameren | K66: gx,mx | N66: 0 | S66: 1 | V66: 3
A67: TRIS_RH_Executive_Final_010_BuildPayrollFiles_vJOB_TR | B67: /api/core/notification/v1/jobs/buildFile | C67: Build File for DB2 Load of VJOB_TR #RH#DV-HR-TR# CHG0000000xxxxx | F67: CMD | G67: TRIS_RH_Executive_Final | H67: TRISBATCH@ameren | I67: V_TRIS_BATCH | J67: $$TRIS_BATCHDIR\BuildDB2LoadFiles\BuildVjob\BuildVjob.exe | K67: gx,mx | N67: 0 | S67: 1 | T67: TRIS | U67: F | V67: 3 | W67: DLTRISTeam@ameren.com | X67: TRIS_RH_Executive_Final_010_BuildPayrollFiles_vJOB_TR FAILED | AA67: >>$$TRIS_BATCHDIR\Logs\%AUTO_JOB_NAME%_stdout.txt | AB67: >>$$TRIS_BATCHDIR\Logs\%AUTO_JOB_NAME%_stderr.txt
A68: TRIS_RH_Executive_Final_020_BuildPayrollFiles_vDEPT_TBL_TR | B68: /api/core/notification/v1/departments/buildFile | C68: Build File for DB2 Load of VDEPT_TBL_TR #RH#DV-HR-TR# CHG0000000xxxxx | E68: s(TRIS_RH_Executive_Final_010_BuildPayrollFiles_vJOB_TR) | F68: CMD | G68: TRIS_RH_Executive_Final | H68: TRISBATCH@ameren | I68: V_TRIS_BATCH | J68: $$TRIS_BATCHDIR\BuildDB2LoadFiles\BuildVdept\BuildVdept.exe | K68: gx,mx | N68: 0 | S68: 1 | T68: TRIS | U68: F | V68: 3 | W68: DLTRISTeam@ameren.com | X68: TRIS_RH_Executive_Final_020_BuildPayrollFiles_vDEPT_TBL_TR FAILED | AA68: >>$$TRIS_BATCHDIR\Logs\%AUTO_JOB_NAME%_stdout.txt | AB68: >>$$TRIS_BATCHDIR\Logs\%AUTO_JOB_NAME%_stderr.txt
A69: TRIS_RH_Executive_Final_030_BuildPayrollFiles_vJOBCODE_TR | B69: /api/core/notification/v1/jobcodes/buildFile | C69: Build File for DB2 Load of VJOBCODE_TBL_TR #RH#DV-HR-TR# CHG0000000xxxxx | E69: s(TRIS_RH_Executive_Final_020_BuildPayrollFiles_vDEPT_TBL_TR) | F69: CMD | G69: TRIS_RH_Executive_Final | H69: TRISBATCH@ameren | I69: V_TRIS_BATCH | J69: $$TRIS_BATCHDIR\BuildDB2LoadFiles\BuildVjobcode\BuildVjobcode.exe | K69: gx,mx | N69: 0 | S69: 1 | T69: TRIS | U69: F | V69: 3 | W69: DLTRISTeam@ameren.com | X69: TRIS_RH_Executive_Final_030_BuildPayrollFiles_vJOBCODE_TR FAILED | AA69: >>$$TRIS_BATCHDIR\Logs\%AUTO_JOB_NAME%_stdout.txt | AB69: >>$$TRIS_BATCHDIR\Logs\%AUTO_JOB_NAME%_stderr.txt
A70: TRIS_RH_Executive_Final_040_BuildPayrollFiles_vSAL_STEP_TR | B70: /api/core/common/v1/JobSalaryStep/generate-file | C70: Build File for DB2 Load of VSAL_STEP_TBL_TR #RH#DV-HR-TR# CHG0000000xxxxx | E70: s(TRIS_RH_Executive_Final_030_BuildPayrollFiles_vJOBCODE_TR) | F70: CMD | G70: TRIS_RH_Executive_Final | H70: TRISBATCH@ameren | I70: V_TRIS_BATCH | J70: $$TRIS_BATCHDIR\BuildDB2LoadFiles\BuildVsalarystep\BuildVsalarystep.exe | K70: gx,mx | N70: 0 | S70: 1 | T70: TRIS | U70: F | V70: 3 | W70: DLTRISTeam@ameren.com | X70: TRIS_RH_Executive_Final_040_BuildPayrollFiles_vSAL_STEP_TR FAILED | AA70: >>$$TRIS_BATCHDIR\Logs\%AUTO_JOB_NAME%_stdout.txt | AB70: >>$$TRIS_BATCHDIR\Logs\%AUTO_JOB_NAME%_stderr.txt
A71: TRIS_RH_Executive_Final_050_BuildPayrollFiles_FTP_vJOB_TR | B71: FTP Jobs Not Applicable | C71: FTP of file to load into VJOB_TR load #RH#DV-HR-TR# CHG0000000xxxxx | E71: s(TRIS_RH_Executive_Final_040_BuildPayrollFiles_vSAL_STEP_TR) | F71: FTP | G71: TRIS_RH_Executive_Final | H71: ASYSFTPP@SYSC | I71: V_TRIS_BATCH | K71: gx,mx | N71: 0 | S71: 1 | U71: F | V71: 3 | W71: DLTRISTeam@ameren.com | X71: TRIS_RH_Executive_Final_050_BuildPayrollFiles_FTP_vJOB_TR FAILED | AC71: A | AD71: UPLOAD | AE71: $$TRIS_BATCHDIR\\DB2LoadFiles\\VJOB-TR-EXTRACT.txt | AF71: ITP.DATA.JOB | AG71: SYSC.ameren.com | AH71: 0 | AI71: TRISBATCH@ameren | AJ71: Simple
A72: TRIS_RH_Executive_Final_060_BuildPayrollFiles_FTP_vDEPT_TR | B72: FTP Jobs Not Applicable | C72: FTP of file to load into VDEPT_TBL_TR load #RH#DV-HR-TR# CHG0000000xxxxx | E72: s(TRIS_RH_Executive_Final_050_BuildPayrollFiles_FTP_vJOB_TR) | F72: FTP | G72: TRIS_RH_Executive_Final | H72: ASYSFTPP@SYSC | I72: V_TRIS_BATCH | K72: gx,mx | N72: 0 | S72: 1 | U72: F | V72: 3 | W72: DLTRISTeam@ameren.com | X72: TRIS_RH_Executive_Final_060_BuildPayrollFiles_FTP_vDEPT_TR FAILED | AC72: A | AD72: UPLOAD | AE72: $$TRIS_BATCHDIR\\DB2LoadFiles\\VDEPT-TBL-TR-EXTRACT.txt | AF72: ITP.DATA.DEPT | AG72: SYSC.ameren.com | AH72: 0 | AI72: TRISBATCH@ameren | AJ72: Simple
A73: TRIS_RH_Executive_Final_070_BuildPayrollFiles_FTP_vJOBCODE | B73: FTP Jobs Not Applicable | C73: FTP of file to load into VJOBCODE_TBL_TR load #RH#DV-HR-TR# CHG0000000xxxxx | E73: s(TRIS_RH_Executive_Final_060_BuildPayrollFiles_FTP_vDEPT_TR) | F73: FTP | G73: TRIS_RH_Executive_Final | H73: ASYSFTPP@SYSC | I73: V_TRIS_BATCH | K73: gx,mx | N73: 0 | S73: 1 | U73: F | V73: 3 | W73: DLTRISTeam@ameren.com | X73: TRIS_RH_Executive_Final_070_BuildPayrollFiles_FTP_vJOBCODE FAILED | AC73: A | AD73: UPLOAD | AE73: $$TRIS_BATCHDIR\\DB2LoadFiles\\VJOBCODE-TBL-TR-EXTRACT.txt | AF73: ITP.DATA.JOBCODE | AG73: SYSC.ameren.com | AH73: 0 | AI73: TRISBATCH@ameren | AJ73: Simple
A74: TRIS_RH_Executive_Final_080_BuildPayrollFiles_FTP_vSAL | B74: FTP Jobs Not Applicable | C74: FTP of file to load into VSAL_STEP_TBL_TR load #RH#DV-HR-TR# CHG0000000xxxxx | E74: s(TRIS_RH_Executive_Final_070_BuildPayrollFiles_FTP_vJOBCODE) | F74: FTP | G74: TRIS_RH_Executive_Final | H74: ASYSFTPP@SYSC | I74: V_TRIS_BATCH | K74: gx,mx | N74: 0 | S74: 1 | U74: F | V74: 3 | W74: DLTRISTeam@ameren.com | X74: TRIS_RH_Executive_Final_080_BuildPayrollFiles_FTP_vSAL FAILED | AC74: A | AD74: UPLOAD | AE74: $$TRIS_BATCHDIR\\DB2LoadFiles\\VSAL-STEP-TBL-TR-EXTRACT.txt | AF74: ITP.DATA.SAL.STP | AG74: SYSC.ameren.com | AH74: 0 | AI74: TRISBATCH@ameren | AJ74: Simple
A75: TRIS_RH_Executive_Final_200_MF_AR13895 | B75: Cobol DB2 load Not in Autosys | C75: Moves the Files that were sent in jobs TRIS_RH_Executive_Final_050, TRIS_RH_Executive_Final_060, TRIS_RH_Executive_Final_070, & TRIS_RH_Executive_Final_080 from Mainframe FTP directory to Mainframe datasets. It then loads the data into DB2 Tables #RH#DV-HR-TR# CHG0000000xxxxx | E75: s(TRIS_RH_Executive_Final_080_BuildPayrollFiles_FTP_vSAL) | F75: ZOS | G75: TRIS_RH_Executive_Final | H75: ESPAE | I75: V_TRIS_TRJobs2MF | L75: CF.STARTPDS | M75: AR13895 | N75: 0 | S75: 1 | U75: F | W75: DLTRISTeam@ameren.com | X75: TRIS_RH_Executive_Final_200_MF_AR13895 FAILED. Moves the Files that were sent in jobs TRIS_RH_Executive_Final_050, TRIS_RH_Executive_Final_060, TRIS_RH_Executive_Final_070, & TRIS_RH_Executive_Final_080 from Mainframe FTP directory to Mainframe datase | Y75: action=STOP,rc=1\:4095,result=FAILURE
A76: TRIS_RH_Executive_Final_300_Build_HR_History_View | C76: Fills tables for view VJOB_TR_EFF which allows the HR History records to have a start and end date versus just an effective date. #RH#DV-HR-TR# CHG00000000xxxx | E76: s(TRIS_RH_Executive_Final_200_MF_AR13895) | F76: CMD | G76: TRIS_RH_Executive_Final | H76: TRISBATCH@ameren | I76: V_TRIS_BATCH | J76: $$TRIS_BATCHDIR\PSJobViewRefresh\PS2TRIS.exe | K76: gx,mx | N76: 0 | S76: 1 | T76: TRIS | U76: F | V76: 3 | W76: DLTRISTeam@ameren.com | X76: TRIS_RH_Executive_Final_300_Build_HR_History_View FAILED. Fills tables for view VJOB_TR_EFF which allows the HR History records to have a start and end date versus just an effective date. Look in \C\\TRISBatch\\Logs\ on server | AA76: >>$$TRIS_BATCHDIR\Logs\%AUTO_JOB_NAME%_stdout.txt | AB76: >>$$TRIS_BATCHDIR\Logs\%AUTO_JOB_NAME%_stderr.txt
A77: TRIS_RH_Executive_Final_310_COPtoUOP | B77: /api/core/notification/v1/CopToUop/update | C77: Changes unapproved COP time to UOP #RH#DV-HR-TR# CHG0000000xxxxx | E77: s(TRIS_RH_Executive_Final_300_Build_HR_History_View) | F77: CMD | G77: TRIS_RH_Executive_Final | H77: TRISBATCH@ameren | I77: V_TRIS_BATCH | J77: $$TRIS_BATCHDIR\COPtoUOP\COPtoUOP.exe | K77: gx,mx | N77: 0 | S77: 1 | T77: TRIS | U77: F | V77: 3 | W77: DLTRISTeam@ameren.com | X77: TRIS_RH_Executive_Final_310_COPtoUOP FAILED | AA77: >>$$TRIS_BATCHDIR\Logs\%AUTO_JOB_NAME%_stdout.txt | AB77: >>$$TRIS_BATCHDIR\Logs\%AUTO_JOB_NAME%_stderr.txt
A78: TRIS_RH_Executive_Final_410_MF_TR33201 | B78: TR_RN_ExecutivePayroll_TR33201_Trigger_HTTP | C78: Executive Final Payroll Processing that produces Payroll file that is used in TRIS_RH_Executive_Final_550_Send_ToPayroll to build a JSON request to send to Workday #RH#DV-HR-TR# CHG0000000xxxxx | E78: s(TRIS_RH_Executive_Final_310_COPtoUOP) | F78: ZOS | G78: TRIS_RH_Executive_Final | H78: ESPAE | I78: V_TRIS_TRJobs2MF | L78: UE.STARTPDS | M78: TR33201N | N78: 0 | S78: 1 | U78: F | W78: DLTRISTeam@ameren.com | X78: TRIS_RH_Executive_Final_410_MF_TR33201 FAILED. Executive Final Payroll Processing that produces Payroll file that is used in TRIS_RH_Executive_Final_550_Send_ToPayroll to build a JSON request to send to Workday | Y78: action=STOP,rc=1\:4095,result=FAILURE
A79: TRIS_RH_Executive_Final_420_MF_AR13587 | B79: Cobol DB2 load Not in Autosys | C79: Sends the Executive Payroll file built in TRIS_RH_Executive_Final_410_MF_TR33201 via FTP to the Autosys server #RH#DV-HR-TR# CHG0000000xxxxx | E79: s(TRIS_RH_Executive_Final_410_MF_TR33201) | F79: ZOS | G79: TRIS_RH_Executive_Final | H79: ESPAE | I79: V_TRIS_TRJobs2MF | L79: CF.STARTPDS | M79: AR13587 | N79: 0 | S79: 1 | U79: F | W79: DLTRISTeam@ameren.com | X79: TRIS_RH_Executive_Final_420_MF_AR13587 FAILED. Sends the Executive Payroll file built in TRIS_RH_Executive_Final_410_MF_TR33201 via FTP to the Autosys server | Y79: action=STOP,rc=1\:4095,result=FAILURE
A80: TRIS_RH_Executive_Final_530_Send_Copy_PayrollFile | B80: Cobol DB2 load Not in Autosys | C80: Copies Mainframe payroll file on the Autosys server to the RIS folder on the Corporate share drive #RH#DV-HR-TR# CHG0000000xxxxx | E80: s(TRIS_RH_Executive_Final_420_MF_AR13587) | F80: CMD | G80: TRIS_RH_Executive_Final | H80: TRISBATCH@ameren | I80: V_TRIS_MFFTP | J80: %FTPDir2%\Exec\copy_file.bat %FTPDir%\tr_payroll_exec.txt \\corp.dir.ameren.com\dfs\Orgdrv\TRIS\MKS\tr_payroll_exec.txt | K80: gx,mx | N80: 0 | S80: 1 | T80: TRIS | U80: F | V80: 3 | W80: DLTRISTeam@ameren.com | X80: TRIS_RH_Executive_Final_530_Send_Copy_PayrollFile JOB FAILED. Copies Mainframe payroll file on the Autosys server to the RIS folder on the Corporate share drive. Look in \C\\TRISBatch\\Logs\ on server | AA80: %FTPDir2%\Logs\Payroll_stdout.txt | AB80: %FTPDir2%\Logs\Payroll_stderr.txt
A81: TRIS_RH_Executive_Final_540_Send_Move_PayrollFile | B81: Cobol DB2 load Not in Autosys | C81: Moves Mainframe Payroll file from the TRIS folder on the Corporate share drive to the TRIS Server (V_TRIS_BATCH) #RH#DV-HR-TR# CHG0000000xxxxx | E81: s(TRIS_RH_Executive_Final_530_Send_Copy_PayrollFile) | F81: CMD | G81: TRIS_RH_Executive_Final | H81: TRISBATCH@ameren | I81: V_TRIS_BATCH | J81: $$TRIS_BATCHDIR\MoveMainframeFiles\MovePayrollFile\MovePayrollFile.exe | K81: gx,mx | N81: 0 | S81: 1 | T81: TRIS | U81: F | V81: 3 | W81: DLTRISTeam@ameren.com | X81: TRIS_RH_Executive_Final_540_Send_Move_PayrollFile FAILED. Moves Mainframe Payroll file from the TRIS folder on the Corporate share drive to the TRIS Server (V_TRIS_BATCH). Look in \C\\TRISBatch\\Logs\ on server | AA81: >>$$TRIS_BATCHDIR\Logs\%AUTO_JOB_NAME%_stdout.txt | AB81: >>$$TRIS_BATCHDIR\Logs\%AUTO_JOB_NAME%_stderr.txt
A82: TRIS_RH_Executive_Final_550_Send_ToPayroll | B82: /api/core/notification/v1/WorkdayPayroll/execute | C82: Sends Payroll data to Workday #RH#DV-HR-TR# CHG0000000xxxxx | D82: "Escalate to Venka when called by Pager Duty" | E82: s(TRIS_RH_Executive_Final_540_Send_Move_PayrollFile) | F82: CMD | G82: TRIS_RH_Executive_Final | H82: TRISBATCH@ameren | I82: V_TRIS_BATCH | J82: $$TRIS_BATCHDIR\WorkdayPayrollInterface\WorkdayPayrollInterface.exe | K82: gx,mx | N82: 0 | S82: 1 | T82: TRIS | U82: F | V82: 3 | W82: DLTRISTeam@ameren.com | X82: TRIS_RH_Executive_Final_550_Send_ToPayroll FAILED. Sends Payroll data to Workday. Look in \C\\TRISBatch\\Logs\ on server | AA82: >>$$TRIS_BATCHDIR\Logs\%AUTO_JOB_NAME%_stdout.txt | AB82: >>$$TRIS_BATCHDIR\Logs\%AUTO_JOB_NAME%_stderr.txt
A83: TRIS_RH_Executive_Preliminary_OnRequest_MF_TR33112 | B83: TR_RN_OnRequest_TR33112_Trigger_Box | C83: Executive Preliminary Job on Request #RH#DV-HR-TR# CHG0000000xxxxx | F83: ZOS | H83: ESPAE | I83: V_TRIS_TRJobs2MF | L83: UE.STARTPDS | M83: TR33112 | N83: 0 | S83: 1 | U83: F | W83: DLTRISTeam@ameren.com | X83: TRIS_RH_Executive_Preliminary_OnRequest_MF_TR33112 FAILED. Contract Preliminary Job on Request | Y83: action=STOP,rc=1\:4095,result=FAILURE
A84: TRIS_RH_monthly_000_PDCLOSEBox | C84: The PDCLOSE process runs on the 1st working day of the month | F84: BOX | H84: TRISBATCH@ameren | K84: gx,mx | N84: 1 | P84: 0.16666667 | Q84: run_calendar: AM_1stWkDyNoHol | S84: 1 | V84: 3
A85: TRIS_RH_monthly_010_FixedAccountingAllocationsInterface | B85: /api/core/notification/v1/monthly-labor-hours/process | C85: Inserts fixed accounting allocations into METHDBA.TTR_OTTC_DEPT_FIXED_ALLOCATION & METHDBA.TTR_OTTC_EMP_FIXED_ALLOCATION. Used for Monthly Labor hours report #RH#DV-HR-TR# CHG0000000xxxxx | F85: CMD | G85: TRIS_RH_monthly_000_PDCLOSEBox | H85: TRISBATCH@ameren | I85: V_TRIS_BATCH | J85: $$TRIS_BATCHDIR\PayrollDistributionFixedAllocationsInterface\PayrollDistributionFixedAllocationsInterface.exe | K85: gx,mx | N85: 0 | S85: 1 | T85: TRIS | U85: F | V85: 3 | W85: DLTRISTeam@ameren.com | X85: TRIS_RH_monthly_010_FixedAccountingAllocationsInterface failed | AA85: >>$$TRIS_BATCHDIR\Logs\%AUTO_JOB_NAME%_stdout.txt | AB85: >>$$TRIS_BATCHDIR\Logs\%AUTO_JOB_NAME%_stderr.txt
A86: TRIS_RH_monthly_020_PayrollAccruals | B86: /api/core/notification/v1/accrual | C86: Inserts summarized TRIS Accrual hours by department for the Calendar month into TTR_OTTC_ACCRUAL_INTF . A process, written by the Mule Soft integration team, will follow this job and will call the GET Accrual API . #RH#DV-HR-TR# CHG0000000xxxxx | E86: s(TRIS_RH_monthly_010_FixedAccountingAllocationsInterface) | F86: CMD | G86: TRIS_RH_monthly_000_PDCLOSEBox | H86: TRISBATCH@ameren | I86: V_TRIS_BATCH | J86: $$TRIS_BATCHDIR\PayrollAccrualMonthlyInterface\PayrollAccrualMonthlyInterface.exe | K86: gx,mx | N86: 0 | S86: 1 | T86: TRIS | U86: F | V86: 3 | W86: DLTRISTeam@ameren.com | X86: TRIS_RH_monthly_020_PayrollAccruals JOB FAILED. Inserts summarized TRIS Accrual hours by department f for the Calendar month into TTR_OTTC_ACCRUAL_INTF . A process, written by MuleSoft will be dependent on this job | AA86: >>$$TRIS_BATCHDIR\Logs\%AUTO_JOB_NAME%_stdout.txt | AB86: >>$$TRIS_BATCHDIR\Logs\%AUTO_JOB_NAME%_stderr.txt
A87: TRIS_RH_monthly_030_PayrollDistributionInterface | B87: /api/core/payroll/v1/PayrollDistributionMonthlyInterface/monthly-labor-accounting | C87: Inserts summarized TRIS Accrual hours by department for the Calendar month into METHDBA.TTR_OTTC_LABOR_ACCOUNTING_INTF . A process, written by the Mule Soft integration team, will follow this job and will call the GET LaborAccounting API . #RH#DV-HR-TR# CHG0000000xxxxx | E87: s(TRIS_RH_monthly_020_PayrollAccruals) | F87: CMD | G87: TRIS_RH_monthly_000_PDCLOSEBox | H87: TRISBATCH@ameren | I87: V_TRIS_BATCH | J87: $$TRIS_BATCHDIR\PayrollDistributionMonthlyInterface\PayrollDistributionMonthlyInterface.exe | K87: gx,mx | N87: 0 | S87: 1 | T87: TRIS | U87: F | V87: 3 | W87: DLTRISTeam@ameren.com | X87: TRIS_RH_monthly_030_PayrollDistributionInterface JOB FAILED. | AA87: >>$$TRIS_BATCHDIR\Logs\%AUTO_JOB_NAME%_stdout.txt | AB87: >>$$TRIS_BATCHDIR\Logs\%AUTO_JOB_NAME%_stderr.txt
A88: TRIS_RH_monthly_100_MaximoAccountingInterface | B88: /api/core/notification/v1/MaximoAccountingInterface/create | C88: Inserts summarized TRIS time by department for each MAXIMO job number job task combination charged in TRIS for the Calendar month into TTR_ASPIRE_MAXIMO_ACCOUNTING_INTF . A process, written by the Mule Soft integration team, will follow this job and will call the GET Accounting API . #RH#DV-HR-TR# CHG0000000xxxxx | D88: Now runs at 00:01 on 1st working day of month and is outside the TRIS_RH_monthly_000_PDCLOSEBOX | F88: CMD | H88: TRISBATCH@ameren | I88: V_TRIS_BATCH | J88: $$TRIS_BATCHDIR\MaximoAccountingInterface\MaximoAccountingInterface.exe | K88: gx,mx | N88: 0 | P88: 0.00069444444 | Q88: run_calendar: AM_1stWkDyNoHol | S88: 1 | T88: TRIS | U88: F | V88: 3 | W88: DLTRISTeam@ameren.com | X88: TRIS_RH_monthly_100_MaximoAccountingInterface JOB FAILED. Inserts summarized TRIS time by department for each MAXIMO job number job task combination charged in TRIS for the Calendar month into TTR_ASPIRE_MAXIMO_ACCOUNTING_INTF . A process, written by | AA88: >>$$TRIS_BATCHDIR\Logs\%AUTO_JOB_NAME%_stdout.txt | AB88: >>$$TRIS_BATCHDIR\Logs\%AUTO_JOB_NAME%_stderr.txt
A89: TRIS_RH_monthly_150_LaborHours_Interface | B89: /api/core/notification/v1/monthly-labor-hours/process | C89: Loads the Mainframe Labor Hours file into the TTR_LABOR_HOURS table for OBIEE which will distribute the Monthly Labor Hours Reports and collects signatures. TRIS_RH_monthly_110_Copy_LaborHoursFile copied Monthly Labor Hours file to TRIS folder on the Corporate share drive. TRIS_RH_monthly_120_Move_LaborHoursFile moved the Mainframe Labor Hours file from TRIS folder on the Corporate share drive to TRIS Server. #RN#DV-HR-TR# CHG0000000xxxxx | E89: s(TRIS_RH_monthly_140_Move_LaborHoursFile) | F89: CMD | G89: TRIS_RH_monthly_000_PDCLOSEBox | H89: TRISBATCH@ameren | I89: V_TRIS_BATCH | J89: $$TRIS_BATCHDIR\MonthlyLaborHoursInterface\MonthlyLaborHoursInterface.exe | K89: gx,mx | N89: 0 | S89: 1 | T89: TRIS | U89: F | V89: 3 | W89: DLTRISTeam@ameren.com | X89: TRIS_RH_monthly_130_LaborHours_Interface FAILED. Loads the Mainframe Labor Hours file into the TTR_LABOR_HOURS table for OBIEE which will distribute the Monthly Labor Hours Reports and collects signatures. TRIS_RH_monthly_110_Copy_LaborHoursFile copied | AA89: >>$$TRIS_BATCHDIR\Logs\%AUTO_JOB_NAME%_stdout.txt | AB89: >>$$TRIS_BATCHDIR\Logs\%AUTO_JOB_NAME%_stderr.txt
A90: TRIS_RH_sunday_010_BuildCommon_Department | B90: /api/core/notification/v1/departments/common/buildFile | C90: Build File for DB2 Load of TAR_COMN_DEPT_TBL #RH#DV-HR-TR# CHG0000000xxxxx | F90: CMD | G90: TRIS_RH_sundayBox | H90: TRISBATCH@ameren | I90: V_TRIS_BATCH | J90: $$TRIS_BATCHDIR\BuildDB2LoadFiles\BuildCommonDepartment\BuildCommonDepartment.exe | K90: gx,mx | N90: 0 | S90: 1 | T90: TRIS | U90: F | V90: 3 | W90: DLTRISTeam@ameren.com | X90: TRIS_RH_sunday_010_BuildCommon_Department FAILED | AA90: >>$$TRIS_BATCHDIR\Logs\%AUTO_JOB_NAME%_stdout.txt | AB90: >>$$TRIS_BATCHDIR\Logs\%AUTO_JOB_NAME%_stderr.txt | AE90: F
A91: TRIS_RH_sunday_020_BuildCommon_Employee | B91: /api/core/notification/v1/employees/buildFile | C91: Builds File for DB2 Load of TAR_COMN_EMP_TBL and Builds for DB2 Load of THRDB_EMPLOYEE_TBL #RH#DV-HR-TR# CHG0000000xxxxx | E91: s(TRIS_RH_sunday_010_BuildCommon_Department) | F91: CMD | G91: TRIS_RH_sundayBox | H91: TRISBATCH@ameren | I91: V_TRIS_BATCH | J91: $$TRIS_BATCHDIR\BuildDB2LoadFiles\BuildCommonEmployeeFile\BuildCommonEmployeeFile.exe | K91: gx,mx | N91: 0 | S91: 1 | T91: TRIS | U91: F | V91: 3 | W91: DLTRISTeam@ameren.com | X91: TRIS_RH_sunday_020_BuildCommon_Employee FAILED | AA91: >>$$TRIS_BATCHDIR\Logs\%AUTO_JOB_NAME%_stdout.txt | AB91: >>$$TRIS_BATCHDIR\Logs\%AUTO_JOB_NAME%_stderr.txt
A92: TRIS_RH_sunday_030_BuildCommon_FTP_Department | B92: FTP Jobs Not Applicable | C92: FTP of file to load into TAR_COMN_DEPT_TBL load #RH#DV-HR-TR# CHG0000000xxxxx | E92: s(TRIS_RH_sunday_020_BuildCommon_Employee) | F92: FTP | G92: TRIS_RH_sundayBox | H92: ASYSFTPP@SYSC | I92: V_TRIS_BATCH | K92: gx,mx | N92: 0 | S92: 1 | U92: F | V92: 3 | W92: DLTRISTeam@ameren.com | X92: TRIS_RH_sunday_030_BuildCommon_FTP_Department FAILED | AC92: A | AD92: UPLOAD | AE92: $$TRIS_BATCHDIR\\DB2LoadFiles\\CommonDepartment-EXTRACT.txt | AF92: ITP.DATA.GDG.DEPT.EXTRT | AG92: SYSC.ameren.com | AH92: 0 | AI92: TRISBATCH@ameren | AJ92: Simple
A93: TRIS_RH_sunday_040_BuildCommon_FTP_Employee | B93: FTP Jobs Not Applicable | C93: FTP a file to load into TAR_COMN_EMPL_TBL #RH#DV-HR-TR# CHG0000000xxxxx | E93: s(TRIS_RH_sunday_030_BuildCommon_FTP_Department) | F93: FTP | G93: TRIS_RH_sundayBox | H93: ASYSFTPP@SYSC | I93: V_TRIS_BATCH | K93: gx,mx | N93: 0 | S93: 1 | U93: F | V93: 3 | W93: DLTRISTeam@ameren.com | X93: TRIS_RH_sunday_040_BuildCommon_FTP_Employee FAILED | AC93: A | AD93: UPLOAD | AE93: $$TRIS_BATCHDIR\\DB2LoadFiles\\COMNEMPL-EXTRACT.txt | AF93: ITP.DATA.GDG.EMPL.EXTRT | AG93: SYSC.ameren.com | AH93: 0 | AI93: TRISBATCH@ameren | AJ93: Simple
A94: TRIS_RH_sunday_050_BuildCommon_FTP_THRDBEmployee | B94: FTP Jobs Not Applicable | C94: FTP a File for DB2 Load of THRDB_EMPLOYEE_TBL #RH#DV-HR-TR# CHG0000000xxxxx | E94: s(TRIS_RH_sunday_040_BuildCommon_FTP_Employee) | F94: FTP | G94: TRIS_RH_sundayBox | H94: ASYSFTPP@SYSC | I94: V_TRIS_BATCH | K94: gx,mx | N94: 0 | S94: 1 | U94: F | V94: 3 | W94: DLTRISTeam@ameren.com | X94: TRIS_RH_sunday_050_BuildCommon_FTP_THRDBEmployee FAILED | AC94: A | AD94: UPLOAD | AE94: $$TRIS_BATCHDIR\\DB2LoadFiles\\THRDB-EMPLOYEE-EXTRACT.txt | AF94: ITP.DATA.GDG.EMPL.DB2 | AG94: SYSC.ameren.com | AH94: 0 | AI94: TRISBATCH@ameren | AJ94: Simple
A95: TRIS_RH_sunday_070_BuildCommon_Associations | B95: /api/core/notification/v1/build/associations/buildFile | C95: Builds File for maintaining the TTR_ASSOCIATIONS table in mainframe job UE.STARTPDS(TR33107N) #RH#DV-HR-TR# CHG0000000xxxxx | E95: s(TRIS_RH_sunday_050_BuildCommon_FTP_THRDBEmployee) | F95: CMD | G95: TRIS_RH_sundayBox | H95: TRISBATCH@ameren | I95: V_TRIS_BATCH | J95: $$TRIS_BATCHDIR\BuildDB2LoadFiles\BuildAssociations\BuildAssociations.exe | K95: gx,mx | N95: 0 | S95: 1 | T95: TRIS | U95: F | V95: 3 | W95: DLTRISTeam@ameren.com | X95: TRIS_RH_sunday_070_BuildCommon_Associations FAILED | AA95: >>$$TRIS_BATCHDIR\Logs\%AUTO_JOB_NAME%_stdout.txt | AB95: >>$$TRIS_BATCHDIR\Logs\%AUTO_JOB_NAME%_stderr.txt
A96: TRIS_RH_sunday_080_BuildCommon_FTP_Associations | B96: FTP Jobs Not Applicable | C96: FTP a file to process in UE.STARTPDS(TR33107N) #RH#DV-HR-TR# CHG0000000xxxxx | E96: s(TRIS_RH_sunday_070_BuildCommon_Associations) | F96: FTP | G96: TRIS_RH_sundayBox | H96: ASYSFTPP@SYSC | I96: V_TRIS_BATCH | K96: gx,mx | N96: 0 | S96: 1 | U96: F | V96: 3 | W96: DLTRISTeam@ameren.com | X96: TRIS_RH_sunday_080_BuildCommon_FTP_Associations FAILED | AC96: A | AD96: UPLOAD | AE96: $$TRIS_BATCHDIR\\DB2LoadFiles\\TTR-ASSOCIATIONS-EXTRACT.txt | AF96: ITP.DATA.DATA.DPTTABLE | AG96: SYSC.ameren.com | AH96: 0 | AI96: TRISBATCH@ameren | AJ96: Simple
A97: TRIS_RH_sunday_100_BuildPayrollFiles_vJOB_TR | B97: /api/core/notification/v1/jobs/buildFile | C97: Build File for DB2 Load of VJOB_TR #RH#DV-HR-TR# CHG0000000xxxxx | E97: s(TRIS_RH_sunday_080_BuildCommon_FTP_Associations) | F97: CMD | G97: TRIS_RH_sundayBox | H97: TRISBATCH@ameren | I97: V_TRIS_BATCH | J97: $$TRIS_BATCHDIR\BuildDB2LoadFiles\BuildVjob\BuildVjob.exe | K97: gx,mx | N97: 0 | S97: 1 | T97: TRIS | U97: F | V97: 3 | W97: DLTRISTeam@ameren.com | X97: TRIS_RH_sunday_100_BuildPayrollFiles_vJOB_TR FAILED | AA97: >>$$TRIS_BATCHDIR\Logs\%AUTO_JOB_NAME%_stdout.txt | AB97: >>$$TRIS_BATCHDIR\Logs\%AUTO_JOB_NAME%_stderr.txt
A98: TRIS_RH_sunday_110_BuildPayrollFiles_vDEPT_TBL_TR | B98: /api/core/notification/v1/departments/buildFile | C98: Build File for DB2 Load of VDEPT_TBL_TR #RH#DV-HR-TR# CHG0000000xxxxx | E98: s(TRIS_RH_sunday_100_BuildPayrollFiles_vJOB_TR) | F98: CMD | G98: TRIS_RH_sundayBox | H98: TRISBATCH@ameren | I98: V_TRIS_BATCH | J98: $$TRIS_BATCHDIR\BuildDB2LoadFiles\BuildVdept\BuildVdept.exe | K98: gx,mx | N98: 0 | S98: 1 | T98: TRIS | U98: F | V98: 3 | W98: DLTRISTeam@ameren.com | X98: TRIS_RH_sunday_110_BuildPayrollFiles_vDEPT_TBL_TR FAILED | AA98: >>$$TRIS_BATCHDIR\Logs\%AUTO_JOB_NAME%_stdout.txt | AB98: >>$$TRIS_BATCHDIR\Logs\%AUTO_JOB_NAME%_stderr.txt
A99: TRIS_RH_sunday_120_BuildPayrollFiles_vJOBCODE_TBL_TR | B99: /api/core/notification/v1/jobcodes/buildFile | C99: Build File for DB2 Load of VJOBCODE_TBL_TR #RH#DV-HR-TR# CHG0000000xxxxx | E99: s(TRIS_RH_sunday_110_BuildPayrollFiles_vDEPT_TBL_TR) | F99: CMD | G99: TRIS_RH_sundayBox | H99: TRISBATCH@ameren | I99: V_TRIS_BATCH | J99: $$TRIS_BATCHDIR\BuildDB2LoadFiles\BuildVjobcode\BuildVjobcode.exe | K99: gx,mx | N99: 0 | S99: 1 | T99: TRIS | U99: F | V99: 3 | W99: DLTRISTeam@ameren.com | X99: TRIS_RH_sunday_120_BuildPayrollFiles_vJOBCODE_TBL_TR FAILED | AA99: >>$$TRIS_BATCHDIR\Logs\%AUTO_JOB_NAME%_stdout.txt | AB99: >>$$TRIS_BATCHDIR\Logs\%AUTO_JOB_NAME%_stderr.txt
A100: TRIS_RH_sunday_130_BuildPayrollFiles_vSAL_STEP_TBL_TR | B100: /api/core/common/v1/JobSalaryStep/generate-file | C100: Build File for DB2 Load of VSAL_STEP_TBL_TR #RH#DV-HR-TR# CHG0000000xxxxx | E100: s(TRIS_RH_sunday_120_BuildPayrollFiles_vJOBCODE_TBL_TR) | F100: CMD | G100: TRIS_RH_sundayBox | H100: TRISBATCH@ameren | I100: V_TRIS_BATCH | J100: $$TRIS_BATCHDIR\BuildDB2LoadFiles\BuildVsalarystep\BuildVsalarystep.exe | K100: gx,mx | N100: 0 | S100: 1 | T100: TRIS | U100: F | V100: 3 | W100: DLTRISTeam@ameren.com | X100: TRIS_RH_sunday_130_BuildPayrollFiles_vSAL_STEP_TBL_TR FAILED | AA100: >>$$TRIS_BATCHDIR\Logs\%AUTO_JOB_NAME%_stdout.txt | AB100: >>$$TRIS_BATCHDIR\Logs\%AUTO_JOB_NAME%_stderr.txt
...

Sheet Master List Programs
A1: SL No | B1: Program Name | C1: Type | D1: LOC | E1: Description
A2: 1 | B2: TI0503 | C2: Program | D2: 1886 | E2: TRBE Auto Build Time | G2: This is an exchaustive list of all COBOL Programs In Scope. This tab contains the list of All COBOL Programs which are being invoked from Mainframe Batch Jobs. As well as all the Called COBOL Sub Program which are being invoked from the Main COBOL Programs. Mainframe Programs are marked as Type Programs while the Called Programs are marked as Sub-Programs
A3: 2 | B3: TI0504 | C3: Program | D3: 1199
A4: 3 | B4: TI0505 | C4: Program | D4: 2370 | E4: CREATE HOLIDAY EXCEPTIONS
A5: 4 | B5: TI0507 | C5: Program | D5: 1900 | E5: Obsolete | F5: Jim Confirmed program No longer needed
A6: 5 | B6: TI0508 | C6: Program | D6: 1057 | E6: UPDATE TRBE SUNDAY DATE
A7: 6 | B7: TI0510 | C7: Program | D7: 1481 | E7: SENIORITY ACCRUALS
A8: 7 | B8: TI0534 | C8: Program | D8: 1368 | E8: Obsolete | F8: Jim Confirmed program No longer needed
A9: 8 | B9: TI0538 | C9: Program | D9: 2475 | E9: TRBE REBUILD STRAIGHT TIME
A10: 9 | B10: TI0543 | C10: Program | D10: 1104
A11: 10 | B11: TI0544 | C11: Program | D11: 1979
A12: 11 | B12: TI0545 | C12: Program | D12: 1099
A13: 12 | B13: TI1003 | C13: Program | D13: 1209 | E13: TRBE ERROR REPORT
A14: 13 | B14: TI1004 | C14: Program | D14: 1170
A15: 14 | B15: TI1009 | C15: Program | D15: 1262 | E15: Obsolete | F15: Jim Confirmed program No longer needed
A16: 15 | B16: TI1021 | C16: Program | D16: 1906 | E16: Obsolete | F16: Program Obsolete as Reports are not needed anymore
A17: 16 | B17: TR001 | C17: Program | D17: 2296 | E17: TIME RECORD EXTRACT
A18: 17 | B18: TR003 | C18: Program | D18: 5953 | E18: ALLOWED TIME (ACTUAL TIME)
A19: 18 | B19: TR003C | C19: Program | D19: 2931 | E19: ACTUAL TIME SICK LEAVE BANK MAINT
A20: 19 | B20: TR004 | C20: Program | D20: 2925 | E20: EARNINGS PROOF
A21: 20 | B21: TR005 | C21: Program | D21: 700 | E21: DEVIATIONS
A22: 21 | B22: TR008 | C22: Program | D22: 652 | E22: UPDATE OT BANKS
A23: 22 | B23: TR009 | C23: Program | D23: 7847 | E23: HR/TRIS INTERFACE
A24: 23 | B24: TR014 | C24: Program | D24: 1012 | E24: JOBS TABLE BATCH MAINTENANCE
A25: 24 | B25: TR015 | C25: Program | D25: 837 | E25: ASSOCIATION TABLE MAINTENANCE
A26: 25 | B26: TR017 | C26: Program | D26: 3531 | E26: Obsolete | F26: Program Obsolete as Reports are not needed anymore
A27: 26 | B27: TR018 | C27: Program | D27: 3488 | E27: Obsolete | F27: Program Obsolete as Reports are not needed anymore
A28: 27 | B28: TR021 | C28: Program | D28: 5357 | E28: ALLOWED TIME (ADJUSTMENTS)
A29: 28 | B29: TR021C | C29: Program | D29: 2314 | E29: CIPS SICK LEAVE ADJUSTMENT PROCESS
A30: 29 | B30: TR026 | C30: Program | D30: 729 | E30: SPLIT EXCEPTION CODES ALLOWED TIME
A31: 30 | B31: TR027 | C31: Program | D31: 22772 | E31: OVERTIME CANVASS REPORT
A32: 31 | B32: TR029 | C32: Program | D32: 1594 | E32: REPORT OF ADJUSTMENTS
A33: 32 | B33: TR033 | C33: Program | D33: 315 | E33: LOCK/UNLOCK DEPARTMENTS
A34: 33 | B34: TR037 | C34: Program | D34: 644 | E34: UPDATE PROCESSED IND ACT/ADJ REQ
A35: 34 | B35: TR039 | C35: Program | D35: 1807 | E35: MISSING TIME REPORT
A36: 35 | B36: TR041 | C36: Program | D36: 1994 | E36: YTD SICK LEAVE SUMMARY BY BUDGET
A37: 36 | B37: TR042 | C37: Program | D37: 1626 | E37: CIPS LOCAL 702 SICK LEAVE REPORT
A38: 37 | B38: TR043 | C38: Program | D38: 1455 | E38: CIPS 702 SICK LEAVE YTD REPORT
A39: 38 | B39: TR044 | C39: Program | D39: 682 | E39: REASSIGN EXECUTIVE OT CODES
... A47: 46 | B47: TR060 | C47: Program | D47: 5647 | E47: PAYSHEET PREP.
A48: 47 | B48: TR061 | C48: Program | D48: 557 | E48: Obsolete | F48: Program Obsolete as Reports are not needed anymore
A49: 48 | B49: TR070 | C49: Program | D49: 1040 | E49: ANNUAL SUMMARY BY SYMBOL REPORT
A50: 49 | B50: TR071 | C50: Program | D50: 958 | E50: ANNUAL SUMMARY LEAVE AND PERSONAL
A51: 50 | B51: TR072 | C51: Program | D51: 1069 | E51: ANNUAL ROUGH SMOOTH RELIEF REPORT
A52: 51 | B52: TR074 | C52: Program | D52: 1340 | E52: ANNUAL VACATION SUMMARY REPORT
A53: 52 | B53: TR077 | C53: Program | D53: 2306 | E53: SICK LEAVE DETAIL REPORT
A54: 53 | B54: TR078 | C54: Program | D54: 1625 | E54: ABSENCE EXCEPTION REPORT
A55: 54 | B55: TR081 | C55: Program | D55: 5262 | E55: SENIORITY REPORT
A56: 55 | B56: TR083 | C56: Program | D56: 636 | E56: LOCAL UNION SENIORITY REPORT
A57: 56 | B57: TR085 | C57: Program | D57: 434 | E57: ASSOCIATIONS TABLE DATA ISSUES
A58: 57 | B58: TR086 | C58: Program | D58: 344 | E58: LEFT SERVICE WORK GROUP ARCHIVE
A59: 58 | B59: TR087 | C59: Program | D59: 1698 | E59: MANAGEMENT OVERTIME REPORT
A60: 59 | B60: TR090 | C60: Program | D60: 1186 | E60: EMPLOYEE NUMBER SENIORITY LIST
... A86: 85 | B86: TR126 | C86: Program | D86: 2134 | E86: OVERTIME EQUALIZATION REPORT
A87: 86 | B87: TR127 | C87: Program | D87: 334
A88: 87 | B88: TR128 | C88: Program | D88: 736 | E88: MGMT SICK LEAVE BALANCE REPORT
A89: 88 | B89: TR129 | C89: Program | D89: 1341
A90: 89 | B90: TR130 | C90: Program | D90: 2422 | E90: QUARTERLY ABSENCE REPORT
A91: 90 | B91: TR131 | C91: Program | D91: 530 | E91: SICK LEAVE EXTENDED ILLNESS MSG
A92: 91 | B92: TR132 | C92: Program | D92: 2167 | E92: YEARLY ABSENCE REPORT 33814
A93: 92 | B93: TR133 | C93: Program | D93: 2673 | E93: VACATION SUMMARY REPORT
A94: 93 | B94: TR134 | C94: Program | D94: 1572 | E94: LOCAL 148 12 SHIFT CERTIFY SICKLV
A95: 94 | B95: TR135 | C95: Program | D95: 510 | E95: INSERT ALLOWED TIME DETAILS
A96: 95 | B96: TR136 | C96: Program | D96: 1062 | E96: RELIEF HOURS TABLE INSERT/DELETE
A97: 96 | B97: TR137 | C97: Program | D97: 945 | E97: HOURS OF RELIEF 33705 AND 33712
A98: 97 | B98: TR139 | C98: Program | D98: 1369 | E98: EMPLOYEES FOR SICK LEAVE REVIEW USING AVERAGE
A99: 98 | B99: TR140 | C99: Program | D99: 1387
A100: 99 | B100: TI4061 | C100: Sub Program | D100: 341
A101: 100 | B101: TI4062 | C101: Sub Program | D101: 341
A102: 101 | B102: TI4067 | C102: Sub Program | D102: 466
A103: 102 | B103: TI4086 | C103: Sub Program | D103: 345
A104: 103 | B104: TI4164 | C104: Sub Program | D104: 352
A105: 104 | B105: TI4068 | C105: Sub Program | D105: 351
A106: 105 | B106: TI4033 | C106: Sub Program | D106: 345
A107: 106 | B107: TI4088 | C107: Sub Program | D107: 346
A108: 107 | B108: TI4132 | C108: Sub Program | D108: 373
A109: 108 | B109: TI4212 | C109: Sub Program | D109: 3555
A110: 109 | B110: TI4233 | C110: Sub Program | D110: 926
... A116: 115 | B116: TI4040 | C116: Sub Program | D116: 410
A117: 116 | B117: TI4042 | C117: Sub Program | D117: 4 | E117: Obsolete
A118: 117 | B118: TI4008 | C118: Sub Program | D118: 355
A119: 118 | B119: TI4083 | C119: Sub Program | D119: 347 | E119: Obsolete
A120: 119 | B120: TI4009 | C120: Sub Program | D120: 344
A121: 120 | B121: TI4027 | C121: Sub Program | D121: 354
A122: 121 | B122: TI4103 | C122: Sub Program | D122: 1299
A123: 122 | B123: TI4005 | C123: Sub Program | D123: 260
A124: 123 | B124: TI4035 | C124: Sub Program | D124: 426
A125: 124 | B125: TI4091 | C125: Sub Program | D125: 361
A126: 125 | B126: TI4092 | C126: Sub Program | D126: 913
A127: 126 | B127: TI4136 | C127: Sub Program | D127: 1293
A128: 127 | B128: TI4141 | C128: Sub Program | D128: 345
A129: 128 | B129: TI4169 | C129: Sub Program | D129: 517
A130: 129 | B130: TI4039 | C130: Sub Program | D130: 441
A131: 130 | B131: TI4045 | C131: Sub Program | D131: 686
... A147: 146 | B147: TI4227 | C147: Sub Program | D147: 341
A148: 147 | B148: TI4161 | C148: Sub Program | D148: 458 | E148: Obsolete
A149: 148 | B149: TI4168 | C149: Sub Program | D149: 317
A150: 149 | B150: TI4170 | C150: Sub Program | D150: 1303
A151: 150 | B151: TI4286 | C151: Sub Program | D151: 337 | E151: Obsolete
A152: 151 | B152: TI4287 | C152: Sub Program | D152: 304 | E152: Obsolete
...

Sheet Master List Jobs
A1: SL No | B1: Job Name | C1: Job Description | D1: Category
A2: 1 | B2: TR33115N | C2: TRBE Process | D2: Daily-Weekly
A3: =1+A2 -> 2 | B3: TR33103N | C3: Contract Pre Payroll | D3: Daily-Weekly | F3: This Sheet Contains the List of All Mainframe Batch JOBs in scope.
A4: =1+A3 -> 3 | B4: TR33101N | C4: Contract Daily Payroll | D4: Daily-Weekly
A5: =1+A4 -> 4 | B5: TR33200 | C5: Contract Final Payroll | D5: Daily-Weekly
A6: =1+A5 -> 5 | B6: TR33206 | C6: Contract Sick Leave | D6: Daily-Weekly
A7: =1+A6 -> 6 | B7: TR33201 | C7: Executive Final Payroll | D7: Daily-Weekly
A8: =1+A7 -> 7 | B8: AR13999 | C8: Copy Job | D8: Daily-Weekly
A9: =1+A8 -> 8 | B9: DB12287N | C9: Load DB2 | D9: Daily-Weekly
A10: =1+A9 -> 9 | B10: DB12005N | C10: Load DB2 | D10: Daily-Weekly
A11: 10 | B11: TR33000 | C11: Recalculate Sick Leave balance | D11: On Request
A12: 11 | B12: AR13895 | C12: Load DB2 | D12: Daily-Weekly
A13: 12 | B13: AR13872 | C13: Copy Job | D13: Daily-Weekly
A14: 13 | B14: AR13687 | C14: FTP Contract Payroll Files | D14: Daily-Weekly
A15: 14 | B15: AR13587 | C15: FTP Executive Payroll Files | D15: Daily-Weekly
A16: 15 | B16: TR33106N | C16: Maintains table TTR_JOBS | D16: Daily-Weekly
A17: 16 | B17: TR33108 | C17: Delayed Overtime Bank Charges | D17: Daily-Weekly
A18: 17 | B18: TR33211 | C18: Weekly Overtime Report (Missouri) | D18: Daily-Weekly
A19: 18 | B19: TR33107N | C19: Maintains table TTR_ASSOCIATIONS | D19: Daily-Weekly
A20: 19 | B20: TR33102N | C20: HR interface via Common Employee | D20: Daily-Weekly
A21: 20 | B21: TR33136N | C21: Seniority Accrual | D21: Daily-Weekly
A22: 21 | B22: TR33311 | C22: Seniority List Local | D22: Monthly
... A42: 41 | B42: TR33406 | C42: CIPS Local 702 Sick Leave Report | D42: Yearly

Sheet Other Autosys Jobs
A1: ERPCS_RN_MuleProjectCostsTRISToOracleTrigger_HTTP | B1: Oracle OTTC
A2: ERPCS_RN_MuleMonthEndTRISLaborAcctToPDTrigger_HTTP | B2: Oracle OTTC
A3: ERPCS_RN_MuleProjecTaskOraclePublishOutboundTrigger_HTTP | B3: Oracle OTTC
A4: ERPCS_RN_MuleMonthEndTRISLaborAcctToPDTrigger_HTTP | B4: Oracle OTTC
A5: WRKM_RN_MuleTrisAccountingHttp | B5: WAM
A6: WRKM_RN_MuleTrisLaborhoursHttp | B6: WAM

Sheet Job Sequence Info
B2: Process Name | C2: Job Name | D2: Program | E2: Job description | F2: Job Schedule | G2: Job Dependency | H2: Comments | I2: Parallel PGM Execution Possible? | J2: Dependency Type
B3: Reconciliation | C3: AR13999 | D3: NA | E3: Load HR data | F3: Daily & Sunday | G3: Run before- DB12287 & DB12005N . | H3: Feeds Files to DB12287 and DB12005 for DB load . So Should run before that | I3: NA | J3: Feeds Files to DB12287 and DB12005 . So Should run before that
C4: DB12287N | D4: NA | E4: Load Common Employee table | F4: Daily & Sunday | G4: Run after AR13999 | H4: Receives Files from AR13999 for DB load . So Should run after that | I4: NA
C5: DB12005N | D5: NA | E5: Load OAS Employee table | F5: Daily & Sunday | G5: Run after AR13999 | H5: Receives Files from AR13999 for DB load . So Should run after that | I5: NA
C6: AR13895 | D6: NA | E6: Load HR data | F6: Daily & Sunday & during (TR33200- Contract Final-Every Alternate Tuesday)& (TR33201-Executive Final -Monthly twice (7th and 21st mostly) on demand) | G6: Run Before TR33201 and TR33200 on days when they are executed . | H6: Does some DB load. The tables are used in both the jobs . | I6: NA
C7: AR13872 | D7: NA | E7: Load HR data | F7: Daily & Sunday | G7: Run Before TR33107 | H7: Feeds Files to TR33107 . So Should run before that | I7: NA
C8: AR13687 | D8: NA | F8: Contract Final-Every Alternate Tuesday | G8: Run After TR33200 | H8: Receives Files from TR33200 . So Should run after that | I8: NA
C9: AR13587 | D9: NA | F9: Executive Final -Monthly twice (7th and 21st mostly) on demand | G9: Run After TR33201 | H9: Receives Files from TR33201 . So Should run after that | I9: NA
B10: Maintain | C10: TR33106N | D10: TR014 | E10: Maintains the TTR_JOBS table (TR014) | F10: Daily(01:00 AM) & Sunday(9:00 AM) | G10: Starting Job | I10: NA
C11: TR33107 | D11: TR015 TR085 | E11: Maintains the TTR_ASSOCIATIONS table (TR015) | F11: Daily(01:00 AM) & Sunday(9:00 AM) | G11: Run After TR33106 and AR13872 | H11: No file Dependency on TR33106 . Only on AR13872 | I11: No | J11: DB2 Table
C12: TR33102 | D12: TR009 TR129 | E12: HR/TRIS interface employee update (TR009 & TR129) | F12: Daily(01:00 AM) & Sunday(9:00 AM) | G12: Run After TR33107 | H12: No file Dependency on TR33107 | I12: No | J12: DB2 Table
B13: Seniority | C13: TR33136N | D13: TI0510 TR127 | E13: Seniority accrual -- Adds one day of seniority (TI0510) | F13: Daily(01:00 AM) & Sunday(9:00 AM) | G13: Run After TR33102 | H13: No file Dependency on TR33102 | I13: No | J13: DB2 Table
B14: TRBE | C14: TR33115N | D14: TI0504 TI0503 TI0538 TI1003 TI0508 | E14: Auto Builds scheduled exception (Holiday, Vacation) time for employees in variable departments and all time for employees in fixed & exception based departments. | F14: Daily & Sunday | G14: Run After TR33136 | H14: No file Dependency on TR33136 (Pending Jim's final review) | I14: No | J14: DB2 Table and File
B15: Contract Payroll | C15: TR33101N | D15: TR001 TR051 TR052 TR003 TR050 TR021 TR003C TR050C TR021C TR105 TR106 TR108 TR004 TR005 TR077 TR029 | E15: Contract Daily Job | F15: Daily except Sunday | G15: Run After TR33103 on Monday and Tuesday . After TR33115 on other days | H15: Group 1 (Must Execute First): Step 1: TR001 (Extract Actual Time and Adjustments) Group 2 (Depends on Group 1 for File ):No Table Contention so can run parallel Step 2: TR051 (Allowed Time Records) Step 3: TR052 (Split Extract File) Group 3 (UE Processing - Depends on Group 2 TR052 for files ): FIle Dependency exists across the 3 steps so cant run parallel( i.e. TR050 depends on output from both TR052 and TR003 TR021 depends on output from TR052, TR003, and TR050) Step 4: TR003 (UE Allowed Time Processing) Step 5: TR050 (Create UE Sick Leave Detail) Step 6: TR021 (UE Adjustment Processing) Group 4 (CIPS Processing - Depends on Group 2 TR052 Files ):FIle Dependency exists across the 3 steps so cant run parallel( i.e. TR050C depends on output from both TR052 and TR003C TR021C depends on output from TR052, TR003C, and TR050C) Step 7: TR003C (CIPS Allowed Time Processing) Step 8: TR050C (Create CIPS Sick Leave Detail) Step 9: TR021C (CIPS Adjustment Processing) Group 5 (Sick Leave Processing - Depends on Group 2-TR106 uses file from TR052 ): TR105 Does some INSERT/DELETE operations on tables which are consumed by TR106 so cant run in parallel. Also TR108 has File Dependency on TR106 to generate report Step 10: UT133B (Sort Extract File) Step 11: TR105 (Load Sick Leave Detail) Step 12: TR106 (Process Sick Leave) Step 13: UT133C & TR108 (Sort & Report Sick Leave Messages) Group 6 (Final Processing - Depends on Groups 3, 4, 5): TR004 needs to run first as it creates input file for TR005 ..TR005,TR077 & TR029 can run in parallel as there is no file dependency and no Table Updates ..All 3 just perform read operations Step 14: UT041A (Combine Extract Files) Step 15: TR004 Step 16: TR005 Step 17: TR077 (Sick Leave Detail Report) Step 18: TR029 Final DB2 Update (SPUFI01) | I15: Partially Yes - TR051 and TR052 can run in parallel in Group 2 In Group 6,TR077,TR005 and TR029
C16: TR33103N | D16: TR033 TR001 TR039 TR051 TR052 TR003 TR050 TR021 TR117 TR003C TR050C TR021C TR104 TR115 TR105 TR106 TR108 TR004 TR005 TR077 TR029 | E16: Contract Preliminary Job Contract Preliminary Job on Request | F16: Mon,Tue | G16: Run after TR33115 on Mondays and Tuesdays | H16: Groupings for TR33103: Group 1 (Must Execute First) Step 1: TR033 (Lock Departments on Last Prelim Run) Step 2: TR001 (Extract Actual Time and Adjustments) Parallel Program Run: Table Dependencies exists, so need to run sequentially Group 2 (Depends on Group 1 for Files) Step 3: UT133A (Sort Extract File for Missing Time) Step 4: TR039 (Missing Time Report) Step 5: TR051 (Allowed Time Records) Step 6: TR052 (Split Sick Leave Extract File) Parallel Program Run: These steps all depend on the initial extract files from TR001. Within them, TR052 can run in parallel with TR039 & TR051 separately, but the other 2 cannot. Group 3 (UE Processing - Depends on Group 2 TR052 for files) Step 7: TR003 (UE Allowed Time Processing) Step 8: TR050 (Create UE Sick Leave Detail) Step 9: TR021 (UE Adjustment Processing) Parallel Program Run: These steps must run sequentially as TR050 depends on output from TR003, and TR021 depends on outputs from both TR003 and TR050. Group 4 (CIPS Processing - Depends on Group 2 TR052 for files) Step 10: TR117 (CIPS Local 702 Check Previous Year FMLA) Step 11: TR003C (CIPS Allowed Time Processing) Step 12: TR050C (Create CIPS Sick Leave Detail) Step 13: TR021C (CIPS Adjustment Processing) Parallel Program Run: Similar to Group 3, these steps have sequential dependencies within the group, with TR050C depending on TR003C and TR021C depending on both. Also TR117 has Table/Data integrity issues with TR003C on Parallel execution Group 5 (Sick Leave Processing - Depends on Group 2) Step 14: TR104 (Sick Leave Certification) Step 15: TR115 (Sick Leave FMLA Updates) Step 16: UT133B (Sort Extract File for TR105) Step 17: TR105 (Load Sick Leave Detail and Banks Work Tables) Step 18: TR106 (Process Sick Leave) Step 19-20: UT133C & TR108 (Sort & Report Sick Leave Messages) Parallel Program Run: TR105 performs table operations needed by TR106, and TR108 depends on the output from TR106, requiring sequential execution within this group. TR104 and TR115 have table contention/Integrity issues due to UDPATE transactions performed. Also TR105 reads some of the tables TR115 updates. So none of these Programs in this group can run in parallel. Group 6 (Final Processing - Depends on Groups 3, 4, 5) Step 21: UT041A (Combine Extract Files) Step 22: TR004 (Creates input for TR005) Steps 23-25: These can run in parallel: TR005 (Deviation Reports) TR077 (Sick Leave Detail Report) TR029 (Final Report) Parallel Program Run: UT041A combines files from previous groups, TR004 processes these combined files, and the final three steps generate various reports independently. So TR005,TR077 & TR029 can run parallely | I16: Partially yes: In Group 2 , Only TR052 can run in parallel with TR039 or TR051 In Group 6, TR005,TR029 and TR077 can run in parallel | J16: Table/File
C17: TR33200 | D17: TR001 TR039 TR051 TR052 TR003 TR050 TR021 TR003C TR050C TR021C TR105 TR106 TR131 TR108 TR004 TR005 TR060 TR033 TR037 | E17: Mainframe Contract Payroll processing that produces Payroll file that is used in TRIS_RH_Contract_Final_550_Send_ToPayroll to build a JSON request to send to Workday | F17: Every Alternate Tuesday | G17: Run after AR13895 as it loads some DB2 tables | H17: Group 1 (Must Execute First) Step 1: TR001 (Extract Actual Time and Adjustments) Step 2: UT133F (Sort Extract File for Missing Time) Step 3: TR039 (Missing Time Report) Parallel Program Run: These steps have sequential dependencies as TR039 uses the sorted output from UT133F which processes TR001's output. Group 2 (Database Quiesce - Must Execute After Group 1) Step 4: QUIESCE1 (Quiesce TRIS DB2 Tablespaces) Step 5: UT467A (Verify Quiesce Success) Parallel Program Run: These steps must run sequentially as UT467A verifies the success of QUIESCE1. Group 3 (Initial Processing - Depends on Group 1) Step 6: TR051 (Allowed Time Records) Step 7: TR052 (Split Extract File for Sick Leave) Parallel Program Run: TR051 and TR052 both process the extract file from TR001 and could potentially run in parallel. Group 4 (UE Processing - Depends on Group 3) Step 8: TR003 (UE Allowed Time Processing) Step 9: TR050 (Create UE Sick Leave Detail) Step 10: TR021 (UE Adjustment Processing) Parallel Program Run: These steps must run sequentially as TR050 depends on output from TR003, and TR021 depends on outputs from both TR003 and TR050. Group 5 (CIPS Processing - Depends on Group 3) Step 11: TR003C (CIPS Allowed Time Processing) Step 12: TR050C (Create CIPS Sick Leave Detail) Step 13: TR021C (CIPS Adjustment Processing) Parallel Program Run: Similar to Group 4, these steps have sequential dependencies, with TR050C depending on TR003C and TR021C depending on both. Group 6 (Sick Leave Processing - Depends on Group 3) Step 14: UT133G (Sort Extract File for TR105) Step 15: TR105 (Load Sick Leave Detail and Banks Work Tables) Step 16: TR106 (Process Sick Leave) Parallel Program Run: These steps must run sequentially as TR105 needs the sorted data from UT133G and TR106 depends on the tables loaded by TR105. Group 7 (Sick Leave Messages - Depends on Group 6) Step 17: TR131 (Sick Leave LTD Messages) Step 18: UT133H (Sort Sick Leave Messages) Step 19: TR108 (Sick Leave Messages Report) Parallel Program Run: These steps must run sequentially as they process and format the sick leave message data. Group 8 (Database Quiesce After Updates - Must Execute After Groups 4, 5, 6, 7) Step 20: QUIESCE2 (Quiesce TRIS DB2 Tablespaces after updates) Step 21: UT467B (Verify Quiesce Success) Parallel Program Run: These steps must run sequentially as UT467B verifies the success of QUIESCE2. Group 9 (Final Processing - Depends on Groups 4, 5, 6, 7, 8) Step 22: UT041 (Combine Extract Files) Step 23: TR004 (Process Combined Extract Files) Step 24: TR005 (Process Deviation Files) Step 25: TR060 (Create Paysheet) Parallel Program Run: These steps have sequential dependencies as each step processes data from the previous step. Group 10 (Final Steps - Depends on All Previous Groups) Step 29: TR033 (Unlock Departments) Step 30: TR037 (Update Final Cycle Number) Parallel Program Run: TR033 and TR037 Update common tables. So Can cause Data integrity issues | I17: Partially Yes: In Group 3 , TR051 and TR052 can run parallel. | J17: File /Table
C18: TR33206 | D18: TR109 TR107 TR077 TR042 TR029 TR026 TR135 TR136 TR137 TR111 TR134 | E18: Updates the sick leave banks to be viewed in TRIS after the Contract Final Job completes TRIS_RH_Contract_Final_410_MF_TR33200 | F18: Every Alternate Tuesday | G18: Run after TR33200 | H18: Group 1 (Sick Leave Processing - Must Execute First) Step 1: TR109 (Update Sick Leave Banks with Current Balances) Step 2: TR107 (Update Sick Leave Detail and Banks from Work Tables) Parallel Program Run: These steps Cannot run parallel as TR107 likely needs the updated balances from TR109. They operate on sick leave data tables with potential for data contention if run in parallel. Group 2 (Sick Leave Reports - Depends on Group 1) Step 3: TR077 (Sick Leave Detail Report) Step 4: TR042 (CIPS/GEN Local 702 Sick Leave Reports) Parallel Program Run: These steps both read from the sick leave output files but perform independent report generation, so they could potentially run in parallel after Group 1 completes. Group 3 (Final Report Processing - Independent of Group 2) Step 5: TR029 (Final Report Processing) Parallel Program Run: This step reads from the ACCUM.EXTRACT file generated in the previous job and is independent of the sick leave processing in Group 2. Group 4 (Allowed Time Processing - Independent from Groups 2-3) Step 6: TR026 (Split Exception Codes for Allowed Time) Step 7: TR135 (Allowed Time Detail Table Update) Parallel Program Run: These steps must run sequentially as TR135 depends on the output from TR026 (EXT.ALTIME file). Group 5 (Relief Hours Processing - Independent from Group 4) Step 8: UT133D (Sort ACCUM.EXTRACT File) Step 9: TR136 (Relief Hours Table Update) Step 10: TR137 (Hours Worked of Relief Reports) Parallel Program Run: These steps have sequential dependencies as TR136 uses the sorted output from UT133D, and TR137 likely depends on the updates made by TR136. Group 6 (Special Reports - Can Run Independently) Step 11: TR111 (Temporary Referral Worker Report) Step 12: TR134 (Union OA 12 Hour Shift Sick Leave Certification) Parallel Program Run: These reports appear to be independent processes that generate specialized reports. They could potentially run in parallel with each other and possibly with Groups 4-5. | I18: Contract Final (ctd.)
B19: Executive Payroll | C19: TR33201 | D19: TR001 TR033 TR039 TR051 TR052 TR003 TR050 TR021 TR103 TR004 TR005 TR044 TR060 TR077 TR029 TR026 TR135 TR128 TR037 | E19: Executive Final Payroll Processing that produces Payroll file that is used in TRIS_RH_Executive_Final_550_Send_ToPayroll to build a JSON request to send to Workday | F19: Monthly twice (7th and 21st mostly) on demand | G19: Run after AR13895 as it loads some DB2 tables | H19: Group 1 (Initial Extraction and Department Management) Step 1: TR001 (Extract Actual Time and Adjustments) Step 2: TR033 (Unlock Departments) Parallel Program Run: These must run sequentially as they handle initial data extraction and department unlocking Group 2 (Missing Time Processing) Step 3: UT133C (Sort Extract File for Missing Time) Step 4: TR039 (Missing Time Report) Parallel Program Run: These steps depend on the output from TR001 and must run sequentially Group 3 (Database Protection - First Quiesce) Step 5: QUIESCE1 (Before Quiesce on TRIS DB2 Tables) Step 6: UT467A (Validation step for QUIESCE1) Note: Critical database protection step that must run before updates Group 4 (UE Processing) Step 7: TR051 (Allowed Time Records) Step 8: TR052 (Split Sick Leave Extract File) Step 9: TR003 (UE Allowed Time Processing) Step 10: TR050 (Create UE Sick Leave Detail) Step 11: TR021 (UE Adjustment Processing) Parallel Program Run: These steps have sequential dependencies as each relies on output from previous steps Group 5 (Combine and Process UE Data) Step 12: UT041 (Combine Extract Files) Step 13: TR103 (Management Exempt Partial Day) Note: These steps consolidate and further process the UE data Group 6 (Database Protection - Second Quiesce) Step 14: QUIESCE2 (After Quiesce on TRIS DB2 Tables) Step 15: UT467B (Validation step for QUIESCE2) Note: Second database protection step after updates Group 7 (Final Processing and Reporting) Step 16: TR004 (Create input for other reports) Step 17: TR005 (Deviation Reports) Step 18: TR044 (Assign Executive Overtime Codes) Step 19: TR060 (Paysheet Generation) Step 20: UT133A (Sort Paysheet) Parallel Program run :Once TR004 completes, TR005 and TR044 can run in parallel . TR060 can run only after TR044 as it depends on Output file Group 8 (Reports Generation - Can run in parallel after Group 7) Step 21: TR077 (Sick Leave Detail Report) Step 22: TR029 (Final Report) Step 23: TR026 (Split Exception Codes for Allowed Time) Step 25: TR135 (Allowed Time Detail Table Update) Step 26: TI0534 (Create Variable Accounting Variation File) Step 27: TI1009 (Create GES Report) Step 28: TR128 (Management Sick Leave Balance Report) Parallel Program run: TR077,TR029 ,TR026 & TR128 can run in parallel. TR135 needs to run after TR026 as it has file dependencies. Group 9 (Final System Update) Step 29: TR037 (Update Final Cycle Number) Note: Final step to update cycle numbers - must run last | I19: Partially yes: In Group 7, TR005 and TR044 can run in parallel In Group 8, TR077,TR029 ,TR026 & TR128 can run in parallel | J19: Table/File
B20: Overtime | C20: TR33108 | D20: TR008 | E20: Processes delayed overtime bank charges (TR008) at 00:05 every day. | F20: Daily 00:05 AM | G20: Scheduled Run No dependency | I20: NA
C21: TR33211 | D21: TR053 | E21: Ameren Missouri Stores Weekly Overtime Report (TR053) | F21: Tue 2:00 AM | G21: Scheduled Run No dependency | I21: NA
B22: Monthly | C22: TR33311 | D22: TR090 TR091 TR092 TR093 TR094 TR083 | E22: Seniority reports for Local 148 (OA) and 1455 (JA,JB) | F22: 1st Day of Month(5PM) | G22: Scheduled Run No dependency | I22: Yes | J22: NA
C23: TR33137 | D23: TI0545 TR078 (A,B,C,D,E) TR086 | E23: Absence exception reports -- | F23: 20th Day of Month (5PM) | G23: Scheduled Run No dependency | I23: No | J23: File
C24: TR33408 | D24: TI0544 TR058 | E24: Sick leave summary report. | F24: 20th Day of Month(JAN MAR APR JUN JUL SEP) (5PM) | G24: Scheduled Run No dependency | I24: No | J24: File
B25: Quaterly | C25: TR33400 | D25: TR121 TR122 | E25: E&C project hours reports. | F25: 1st Day of Month(JAN APR JUL OCT) (4 AM) | G25: Scheduled Run No dependency | I25: Yes | J25: NA
C26: TR33402 | D26: TR095 TR096 TR097 | E26: Seniority list for union local 1439 (IA) , 309 (PA), 609 (VA). | F26: 20th Day of Month(JAN APR JUL OCT) (5PM) | G26: Scheduled Run No dependency | I26: Yes | J26: NA
C27: TR33407 | D27: TR087 | E27: Executive quarterly overtime report | F27: 15th Day of Month(JAN APR JUL OCT) (5PM) | G27: Scheduled Run No dependency | I27: NA | J27: NA
C28: TR33401 | D28: TR130 TI0544 TR041 TR099 TR049 | E28: Sick Leave Reports Quarterly. | F28: 20th Day of Month(JAN APR JUL OCT) (5PM) | G28: Scheduled Run No dependency | I28: Partially Yes - TR130 ,TI0544,TR099,TR049 can run parallely. TR041 expects file from TI0544 to create report | J28: File
B29: Yearly | C29: TR33445 | D29: TR114 | E29: Vacation carryover update and report. | F29: 20th Jan 5.30 PM | G29: Scheduled Run No dependency | I29: NA
C30: TR33446 | D30: TR110 TR139 TR140 TR098 TI0543 TR070 TR071 TR072 TR074 TR132 | E30: Sick Leave and Vacation reports. | F30: 20th Jan 6 PM | G30: Scheduled Run No dependency | I30: No
C31: TR33406 | D31: TR043 | E31: CIPS local 702 sick leave reports. | F31: 20th Jan 8 PM | G31: Scheduled Run No dependency | I31: NA
B32: On Request | C32: TR33442 | D32: TI0505 TI1004 | E32: Build holidays for the next year | F32: 20th Oct | G32: Scheduled Run No dependency | H32: (Pending Jim's final review) | I32: No | J32: File
C33: TR33451 | D33: TR113 | E33: Vacation allotment for management employees report | F33: 20th Oct | G33: Scheduled Run No dependency | I33: NA
C34: TR33440 | D34: TR113 | E34: Vacation allotment for contract employees report | F34: 20th Oct | G34: Scheduled Run No dependency | I34: NA
C35: TR33000 | D35: TR426 | E35: sick leave recalculate | F35: NA | G35: No Depedency | H35: (Pending Jim's final review) | I35: NA
